Workbook
Name ADV2MAC: #REF!
Name cafr: Actual!$C$32
Name DIFFUSION_INDEXES: #REF!
Name EXCELFILE: #REF!

Sheet Actual
A1: $ millions | C1: PIT | D1: PIT | E1: PIT | F1: PIT | G1: PIT | H1: PIT | I1: PIT | J1: PIT | K1: PIT | L1: PIT | M1: PIT | N1: PIT | O1: PIT | Q1: CIT | R1: CIT | S1: CIT | T1: CIT | U1: CIT | V1: CIT | W1: CIT | X1: CIT | Y1: CIT | Z1: CIT | AA1: CIT | AB1: CIT | AC1: CIT | AE1: Sales | AF1: Sales | AG1: Sales | AH1: Sales | AI1: Sales | AJ1: Sales | AK1: Sales | AL1: Sales | AM1: Sales | AN1: Sales | AO1: Sales | AP1: Sales | AQ1: Sales | AT1: Total | AU1: Total | AV1: Total | AW1: Total | AX1: Total | AY1: Total | AZ1: Total | BA1: Total | BB1: Total | BC1: Total | BD1: Total | BE1: Total | BF1: Total
A2: State | B2: Abbr | C2: FY 2013 | D2: FY 2014 | E2: FY 2015 | F2: FY 2016 | G2: FY 2017 | H2: FY 2018 | I2: FY 2019 | J2: FY 2020 | K2: FY 2021 | L2: FY 2022 | M2: FY 2023 | N2: FY 2024 | O2: FY 2025 | Q2: FY 2013 | R2: FY 2014 | S2: FY 2015 | T2: FY 2016 | U2: FY 2017 | V2: FY 2018 | W2: FY 2019 | X2: FY 2020 | Y2: FY 2021 | Z2: FY 2022 | AA2: FY 2023 | AB2: FY 2024 | AC2: FY 2025 | AE2: FY 2013 | AF2: FY 2014 | AG2: FY 2015 | AH2: FY 2016 | AI2: FY 2017 | AJ2: FY 2018 | AK2: FY 2019 | AL2: FY 2020 | AM2: FY 2021 | AN2: FY 2022 | AO2: FY 2023 | AP2: FY 2024 | AQ2: FY 2025 | AT2: FY 2013 | AU2: FY 2014 | AV2: FY 2015 | AW2: FY 2016 | AX2: FY 2017 | AY2: FY 2018 | AZ2: FY 2019 | BA2: FY 2020 | BB2: FY 2021 | BC2: FY 2022 | BD2: FY 2023 | BE2: FY 2024 | BF2: FY 2025
A3: Alabama | B3: AL | C3: 3452.4006 | D3: 3480.1711 | E3: 3725.2994 | F3: 3722.13 | G3: 3892.5255 | H3: 4208.4364 | I3: 4548.4707 | J3: 4657.1673 | K3: 5643.8764 | L3: 7182.5684 | M3: 7032.0939 | N3: 7267.1289 | O3: 7495.1795 | Q3: 43.989986 | R3: 65.258757 | S3: 170.85135 | T3: 56.831934 | U3: 75.499764 | V3: 96.063758 | W3: 95.856519 | X3: 96.428942 | Y3: 98.708994 | Z3: 98.997911 | AA3: 103.45026 | AB3: 103.54586 | AC3: 103.32133 | AE3: 1978.0943 | AF3: 2020.5428 | AG3: 2108.0702 | AH3: 2230.1832 | AI3: 2287.6947 | AJ3: 2419.3148 | AK3: =2013.911327+150.44723+11.251939+23.292598+111.941527+205.423028+4.118373+33.755908 -> 2554.1419 | AL3: 2682.0885 | AM3: 3012.631 | AN3: 3269.6576 | AO3: 3446.0096 | AP3: 3422.3503 | AQ3: 3519.3319 | AT3: 7390.2268 | AU3: 7474.8923 | AV3: 7929.1673 | AW3: 7893.8605 | AX3: 8202.6535 | AY3: 8693.3721 | AZ3: =(2108210346+7214724451)/1000000 -> 9322.9348 | BA3: 9634.9796 | BB3: 11153.861 | BC3: 13134.348 | BD3: 13621.779 | BE3: 14050.105 | BF3: 14470.873
A4: Alaska | B4: AK | C4: N/A | D4: N/A | E4: N/A | F4: N/A | G4: N/A | H4: N/A | I4: N/A | J4: N/A | K4: N/A | L4: N/A | M4: N/A | N4: N/A | O4: N/A | Q4: 112.48613 | R4: 99.869191 | S4: 136.22325 | T4: 90.243942 | U4: 86.547228 | V4: 119.55631 | W4: 114.83268 | X4: 102.4 | Y4: 102.8 | Z4: 112.2 | AA4: 124.4 | AB4: 177.2 | AC4: 228.7 | AE4: N/A | AF4: N/A | AG4: N/A | AH4: N/A | AI4: N/A | AJ4: N/A | AK4: N/A | AL4: N/A | AM4: N/A | AN4: N/A | AO4: N/A | AP4: N/A | AQ4: N/A | AT4: =15812.3-2386.8 -> 13425.5 | AU4: =17243.7-2518.7 -> 14725 | AV4: =8534.3-2518.7 -> 6015.6 | AW4: =5894.1-2641.9 -> 3252.2 | AX4: =12904.9-3199.6 -> 9705.3 | AY4: =12359.9-3148.3 -> 9211.6 | AZ4: =11179.4-3446.8 -> 7732.6 | BA4: =8673.7-4189.4 -> 4484.3 | BB4: =29764.6-7570.8 -> 22193.8 | BC4: =8660.6-6911.8 -> 1748.8 | BD4: =15484.1-5826.8 -> 9657.3 | BE4: =16298-6097.1 -> 10200.9 | BF4: =19153.2-6940.1 -> 12213.1 | BG4: PRELIMINARY
A5: Arizona | B5: AZ | C5: 3397.5451 | D5: 3462.382 | E5: 3761.344 | F5: 3956.9217 | G5: 4130.8987 | H5: 4543.9984 | I5: 5009.0216 | J5: 4530.4102 | K5: 6532.7029 | L5: 7530.0107 | M5: 5239.5529 | N5: 4845.7665 | O5: 5482.9504 | Q5: 662.0264 | R5: 575.18022 | S5: 663.00301 | T5: 549.6263 | U5: 368.13645 | V5: 373.0721 | W5: 514.2641 | X5: 511.88185 | Y5: 847.0208 | Z5: 1163.4689 | AA5: 1806.3114 | AB5: 1744.8217 | AC5: 1750.5472 | AE5: 3842.3713 | AF5: 3985.88 | AG5: 4190.533 | AH5: 4299.1539 | AI5: 4505.9148 | AJ5: 4787.4625 | AK5: 5096.7503 | AL5: 5391.913 | AM5: 6244.5835 | AN5: 7208.8535 | AO5: 7677.7893 | AP5: 7933.9142 | AQ5: 8151.8501 | AT5: 8369.7386 | AU5: 8525.4 | AV5: 9168.713 | AW5: 9401.766 | AX5: 9601.8679 | AY5: 10321.501 | AZ5: 11271.319 | BA5: 11065.384 | BB5: 14345.749 | BC5: 16717.738 | BD5: 15589.624 | BE5: 15452.589 | BF5: 16428.095
A6: Arkansas | B6: AR | C6: 2649.6 | D6: 2602.2 | E6: 2664.2 | F6: 2781.5 | G6: 2767.8 | H6: =3359.6-493.4 -> 2866.2 | I6: =3520-507.5 -> 3012.5 | J6: =3418.6-503.6 -> 2915 | K6: =3969.2-502.1 -> 3467.1 | L6: =4171.5-453.6 -> 3717.9 | M6: =3915.9-768.1 -> 3147.8 | N6: =3849.6-782.9 -> 3066.7 | O6: =3594.3-655 -> 2939.3 | Q6: 375.5 | R6: 371.2 | S6: 449.5 | T6: 417.8 | U6: 366.5 | V6: =406.7-42.8 -> 363.9 | W6: =570.2-62.7 -> 507.5 | X6: =482.1-49.3 -> 432.8 | Y6: =651.9-65.3 -> 586.6 | Z6: =837.2-52.4 -> 784.8 | AA6: =842.5-60.4 -> 782.1 | AB6: =744.8-136.1 -> 608.7 | AC6: =533.1-137.3 -> 395.8 | AE6: 2124.5 | AF6: 2173.1 | AG6: 2197.8 | AH6: 2290 | AI6: 2337.9 | AJ6: 2417.5 | AK6: 2465 | AL6: 2543.7 | AM6: 2883.8 | AN6: 3154.7 | AO6: 3418.4 | AP6: 3480.4 | AQ6: 3527.9 | AT6: 5026.9906 | AU6: 5022.4451 | AV6: 5250.534 | AW6: 5367.813 | AX6: 5348.7642 | AY6: 5494.9187 | AZ6: 5921.4386 | BA6: 5753.3868 | BB6: 6845.3 | BC6: 7477.4 | BD6: 7185.4 | BE6: 6900.5 | BF6: 6679.4
A7: California | B7: CA | C7: 64484 | D7: 67025 | E7: 76169 | F7: 78735 | G7: 83264 | H7: 93776 | I7: 99189 | J7: 99599 | K7: 128856 | L7: 137144 | M7: 101748.82 | N7: 115166 | O7: 130178 | Q7: 7783 | R7: 9093 | S7: 9417 | T7: 10460 | U7: 11020 | V7: 12313 | W7: 14075 | X7: 13954 | Y7: 22591 | Z7: 45128 | AA7: 36337 | AB7: 35456 | AC7: 41338 | AE7: 20482 | AF7: 22263 | AG7: 23682 | AH7: 24871 | AI7: 24874 | AJ7: 24974 | AK7: 26150 | AL7: 25509 | AM7: 29073 | AN7: 33026 | AO7: 33324 | AP7: 33339 | AQ7: 33602 | AT7: 99402 | AU7: 102998 | AV7: 113769 | AW7: 118864 | AX7: 123422 | AY7: 135494 | AZ7: 144471 | BA7: 145082 | BB7: 186810 | BC7: 223503 | BD7: 179214 | BE7: 195261 | BF7: 218506 | BG7: PRELIMINARY
A8: Colorado | B8: CO | C8: 5596.3 | D8: 5696.1 | E8: 6350.1 | F8: 6526.5 | G8: 6760.9 | H8: 7577.2 | I8: 8247 | J8: 8644.9 | K8: 9478.1 | L8: 11717.8 | M8: 10952.7 | N8: 10044.2 | O8: 9997.9 | Q8: 636.3 | R8: 720.7 | S8: 692.9 | T8: 652.3 | U8: 509.3 | V8: 781.9 | W8: 919.8 | X8: 728.3 | Y8: 1183.7 | Z8: 1568.6 | AA8: 2366.7 | AB8: 2796.6 | AC8: 2619.5 | AE8: =2211.7+242.7 -> 2454.4 | AF8: =2424.6+241.5 -> 2666.1 | AG8: =2619.2+260.3 -> 2879.5 | AH8: =2652.6+241.2 -> 2893.8 | AI8: =2727.7+259.5 -> 2987.2 | AJ8: =2926+309.9 -> 3235.9 | AK8: =3054+345.5 -> 3399.5 | AL8: =3196+210.5 -> 3406.5 | AM8: =3418.1+214.2 -> 3632.3 | AN8: =4089+232.6 -> 4321.6 | AO8: =4301.6+251.2 -> 4552.8 | AP8: =4362.6+233.2 -> 4595.8 | AQ8: =4441.1+216.6 -> 4657.7 | AT8: 8554.8 | AU8: 8974.8 | AV8: 9802.6 | AW8: 9971.4 | AX8: 10275.8 | AY8: 11723.9 | AZ8: 12564 | BA8: 12868 | BB8: 14310.1 | BC8: 17697.9 | BD8: 17998 | BE8: 17251.4 | BF8: 17181.3 | BG8: PRELIMINARY
A9: Connecticut | B9: CT | C9: 8719.2 | D9: 8718.7 | E9: 9151 | F9: 9181.6 | G9: 8988.7 | H9: 10770.1 | I9: 9640.1613 | J9: =6815.212581+2582.566122 -> 9397.7787 | K9: =7243.803612+3096.633081 -> 10340.437 | L9: =7886.242302+4245.558091 -> 12131.8 | M9: =(8317165509+2906224724)/1000000 -> 11223.39 | N9: =(8666448405+3136598180)/1000000 -> 11803.047 | O9: =(9152951035+3810979433)/1000000 -> 12963.93 | Q9: 742.5 | R9: 782.2 | S9: 814.8 | T9: 880.4 | U9: 1037.6 | V9: 920.7 | W9: 2232.9884 | X9: 2176.448 | Y9: =1153.079316+1549.716152 -> 2702.7955 | Z9: =1401.152532+2307.593662 -> 3708.7462 | AA9: =(1516587806+2048068395)/1000000 -> 3564.6562 | AB9: =(1555553020+1964651650)/1000000 -> 3520.2047 | AC9: =(1402568919+2367029366)/1000000 -> 3769.5983 | AE9: 3897 | AF9: 4100.6 | AG9: 4205.1 | AH9: 4290.9 | AI9: 4380.6 | AJ9: 4529.7 | AK9: 4708.7 | AL9: =4317.730196+400.90817 -> 4718.6384 | AM9: =4792.674985+482.892296 -> 5275.5673 | AN9: =4818.082809+703.39131 -> 5521.4741 | AO9: =(4944771608+837629589)/1000000 -> 5782.4012 | AP9: =(5003036029+844374157)/1000000 -> 5847.4102 | AQ9: =(5120521097+877806576)/1000000 -> 5998.3277 | AT9: =19405+1232.5-3733.9 -> 16903.6 | AU9: =17009.6+1255.7-1243.9 -> 17021.4 | AV9: =17282+1360.9-1241.2 -> 17401.7 | AW9: =17780.8+1352.8-1301.5 -> 17832.1 | AX9: =17703+1394.4-1325.2 -> 17772.2 | AY9: =18198.6+1630.1-1143.1 -> 18685.6 | AZ9: =19649.8+1688.2-2083.8 -> 19254.2 | BA9: =19193.5404229999-1796.754438+1516.585006 -> 18913.371 | BB9: =20531.418459-1496.315207+1777.716829 -> 20812.82 | BC9: =21990.856849-1934.869284+2000.854493 -> 22056.842 | BD9: =(22822893588-1997837468+2069405191)/1000000 -> 22894.461 | BE9: =(22716129951-2060691770+2410570593)/1000000 -> 23066.009 | BF9: =(23891247168.82-1935141828+2221018915)/1000000 -> 24177.124
A10: Delaware | B10: DE | C10: 1139.8 | D10: 1187.7 | E10: 1251.9 | F10: 1286.6 | G10: 1333.2 | H10: 1428.1955 | I10: 1527.5065 | J10: 1472.1499 | K10: 1888.4 | L10: 1909.4 | M10: 2112.9 | N10: 2216.8944 | O10: 2383.2 | Q10: 187.9 | R10: 102 | S10: 269.5 | T10: 143.3 | U10: 120.8 | V10: 89.730071 | W10: 147.84685 | X10: 116.4697 | Y10: 209.7 | Z10: 314.2 | AA10: 383.9 | AB10: 344.81503 | AC10: 371.4 | AE10: N/A | AF10: N/A | AG10: N/A | AH10: N/A | AI10: N/A | AJ10: N/A | AK10: N/A | AL10: N/A | AM10: N/A | AN10: N/A | AO10: N/A | AP10: N/A | AQ10: N/A | AT10: 3729.8 | AU10: 3572.7 | AV10: 3955.1 | AW10: 3944.8 | AX10: 4013.095 | AY10: 4392.9769 | AZ10: 4591.9214 | BA10: 4525.8094 | BB10: 5390.3 | BC10: 5829.9 | BD10: 6295.1 | BE10: 6348.925 | BF10: 6694.3
A11: Florida | B11: FL | C11: N/A | D11: N/A | E11: N/A | F11: N/A | G11: N/A | H11: N/A | I11: N/A | J11: N/A | K11: N/A | L11: N/A | M11: N/A | N11: N/A | O11: N/A | Q11: 2081 | R11: 2042.5 | S11: 2236.3 | T11: 2272.1 | U11: 2366.4 | V11: 2413 | W11: 3139.9 | X11: 2473.5 | Y11: 3395.6 | Z11: 3761.6 | AA11: 5517.2 | AB11: 6015.8 | AC11: 5808.9 | AE11: 18417.6 | AF11: 19707.7 | AG11: 21062.7 | AH11: 21998 | AI11: 22987.4 | AJ11: 24138.7 | AK11: 25385.3 | AL11: 24591.3 | AM11: 27158.1 | AN11: 34039.7 | AO11: 35800.2 | AP11: 36014 | AQ11: 36907 | AT11: 25314.6 | AU11: 26198 | AV11: 27681.1 | AW11: 28325.4 | AX11: 29594.5 | AY11: 31218.2 | AZ11: 33413.8 | BA11: 31366.2 | BB11: 36280.9 | BC11: 44035.7 | BD11: 47327.8 | BE11: 48342 | BF11: 49676
A12: Georgia | B12: GA | C12: 8772.2274 | D12: 8965.5724 | E12: 9678.524 | F12: 10439.534 | G12: 10977.73 | H12: 11643.862 | I12: 12176.943 | J12: 12408.176 | K12: 14220.906 | L12: 18286.845 | M12: 16969.072 | N12: 16018.875 | O12: 16234.724 | Q12: 797.25543 | R12: 943.80644 | S12: 1000.5364 | T12: 981.00234 | U12: 971.84071 | V12: 1004.2975 | W12: 1271.2703 | X12: 1232.9452 | Y12: 1750.7349 | Z12: 2509.6831 | AA12: 3807.5734 | AB12: 3614.9529 | AC12: 3256.1081 | AE12: 5277.2112 | AF12: 5125.5018 | AG12: 5390.3531 | AH12: 5480.1962 | AI12: 5715.9178 | AJ12: 5945.8776 | AK12: 6250.3097 | AL12: 6174.4508 | AM12: 6947.3331 | AN12: 8316.9506 | AO12: 8918.9444 | AP12: 9004.5913 | AQ12: 9344.6258 | AT12: 18295.859 | AU12: 19167.807 | AV12: 20434.743 | AW12: 22237.393 | AX12: 23268.422 | AY12: 24319.869 | AZ12: 25571.065 | BA12: 25478.916 | BB12: 28591.83 | BC12: 34934.855 | BD12: 35944.539 | BE12: 36441.732 | BF12: 37219.732
A13: Hawaii | B13: HI | C13: 1735.499 | D13: 1745.312 | E13: 1987.752 | F13: 2116.392 | G13: 2192.341 | H13: 2429.836 | I13: 2568.114 | J13: 2359.003 | K13: 3354.561 | L13: 3759.753 | M13: 3099.886 | N13: 3280.416 | O13: 3288.541 | Q13: 100.988 | R13: 87.021 | S13: 52.319 | T13: 93.036 | U13: 173.666 | V13: 131.119 | W13: 163.676 | X13: 8.407368 | Y13: 186.347 | Z13: 255.621 | AA13: 316.831 | AB13: 483.676 | AC13: 400.097 | AE13: 2944.487 | AF13: 2825.041 | AG13: 2992.707 | AH13: 3206.154 | AI13: 3239.225 | AJ13: 3395.566 | AK13: 3541.389 | AL13: 3429.459 | AM13: 3054.356 | AN13: 3978.993 | AO13: 4408.473 | AP13: 4446.125 | AQ13: 4596.199 | AT13: 5466.923 | AU13: 5370.268 | AV13: 5735.141 | AW13: 6194.356 | AX13: 6315.215 | AY13: 6796.036 | AZ13: 7141.79 | BA13: 6694.808 | BB13: 7250.261 | BC13: 9358.848 | BD13: 9200.308 | BE13: 9568.313 | BF13: 9974.161
A14: Idaho | B14: ID | C14: 1284.38 | D14: 1329.27 | E14: 1470.86 | F14: 1513.17 | G14: 1651.1956 | H14: 1828.282 | I14: 1661.13 | J14: 1905.2455 | K14: 2446.3163 | L14: 2602.647 | M14: 2148.7127 | N14: 2228.701 | O14: 2418.855 | Q14: 198.66 | R14: 188.29 | S14: 215.4 | T14: 186.87 | U14: 214.0201 | V14: 238.708 | W14: 283.163 | X14: 243.337 | Y14: 348.555 | Z14: 1039.046 | AA14: 1031.8542 | AB14: 867.482 | AC14: 890.614 | AE14: 1109.83 | AF14: 1145.73 | AG14: 1218.77 | AH14: 1303.03 | AI14: 1382.4182 | AJ14: 1490.015 | AK14: 1597.704 | AL14: 1689.376 | AM14: 2004.203 | AN14: 2305.373 | AO14: 2503.364 | AP14: 2341.957 | AQ14: 2269.097 | AT14: 2750.28 | AU14: 2815.43 | AV14: 3056.77 | AW14: 3183.694 | AX14: 3448.407 | AY14: 3731.606 | AZ14: 3734.606 | BA14: 4031.9784 | BB14: 5009.094 | BC14: 6197.267 | BD14: 5948.0488 | BE14: 5711.262 | BF14: 5866.303
A15: Illinois | B15: IL | C15: 16538 | D15: 16642 | E15: 15913 | F15: 13806 | G15: 13661 | H15: 18747 | I15: 20411 | J15: =21657-2058 -> 19599 | K15: =26350-2372 -> 23978 | L15: =29137-2696 -> 26441 | M15: =27889-2580 -> 25309 | N15: =30134-2758 -> 27376 | O15: =33154-3031 -> 30123 | Q15: 3177 | R15: 3164 | S15: 2690 | T15: 1972 | U15: 1332 | V15: 2150 | W15: 2556 | X15: =2596-370 -> 2226 | Y15: =4450-625 -> 3825 | Z15: =6831-1026 -> 5805 | AA15: =7318-1062 -> 6256 | AB15: =6525-914 -> 5611 | AC15: =5904-827 -> 5077 | AE15: 7355 | AF15: 7676 | AG15: 8030 | AH15: 8063 | AI15: 8043 | AJ15: 8256 | AK15: 8897 | AL15: 8691 | AM15: 9799 | AN15: 10984 | AO15: 11589 | AP15: 11710 | AQ15: 11794 | AT15: 34197 | AU15: 35037 | AV15: 35250 | AW15: 30479 | AX15: 29852 | AY15: 37235 | AZ15: 40088 | BA15: 38646 | BB15: 45251 | BC15: 52222 | BD15: 53672 | BE15: 54887 | BF15: 57594
A16: Indiana | B16: IN | C16: 4977.5 | D16: 4898.8 | E16: 5233 | F16: 5218.2 | G16: 5435.3 | H16: 5816.1 | I16: 6057 | J16: 5998.9 | K16: 6804.5 | L16: 8181.2 | M16: 7575.7 | N16: 8096.1 | O16: 8687.2 | Q16: 968.4 | R16: 1054.4 | S16: 1093.7 | T16: 984 | U16: 978.7 | V16: 660.4 | W16: 948.3 | X16: 848.8 | Y16: 1225.9 | Z16: 1539.5 | AA16: 1230.6 | AB16: 965.1 | AC16: 846.8 | AE16: 6795.8 | AF16: 6925.9 | AG16: 7194.8 | AH16: 7222.6 | AI16: 7489.5 | AJ16: 7662.6 | AK16: 7915 | AL16: 8042 | AM16: 9072.6 | AN16: 9991 | AO16: 10464.7 | AP16: 10369.9 | AQ16: 10633.7 | AT16: 14462.1 | AU16: 14402.2 | AV16: 14898.4 | AW16: 14819.5 | AX16: 15274.1 | AY16: 15571.3 | AZ16: 16406.2 | BA16: 16259.5 | BB16: 18521.1 | BC16: 21190.7 | BD16: 21058.2 | BE16: 21484.6 | BF16: 22228
A17: Iowa | B17: IA | C17: 4083.9 | D17: 3974.9 | E17: 4207.3 | F17: 4355.5 | G17: 4469 | H17: 4746.7 | I17: 4944 | J17: 4652 | K17: 5434.5 | L17: 5780.1 | M17: 5599.3 | N17: 4993.2 | O17: 4947.5 | Q17: 555.3 | R17: 549.6 | S17: 576.3 | T17: 520.5 | U17: 549.7 | V17: 565 | W17: 706.3 | X17: 648.7 | Y17: 983.8 | Z17: 919 | AA17: 984.1 | AB17: 890.5 | AC17: 825.1 | AE17: 2547.6 | AF17: 2642.3 | AG17: 2753 | AH17: 2810.5 | AI17: 2812.3 | AJ17: 2941.5 | AK17: 3045.5 | AL17: 3176.1 | AM17: 3512.3 | AN17: 3853.7 | AO17: 3937.1 | AP17: 4170.4 | AQ17: 4234.9 | AT17: 6768.7 | AU17: 6489 | AV17: 6819.7 | AW17: 6921.1 | AX17: 7240 | AY17: 7383.9 | AZ17: 7858.8 | BA17: 7930.6 | BB17: 8800.6 | BC17: 9803.4 | BD17: 9845.3 | BE17: 9755.8 | BF17: 8942.2
A18: Kansas | B18: KS | C18: 2931.168 | D18: 2218.239 | E18: 2277.541 | F18: 2248.936 | G18: 2304.027 | H18: 3374.42 | I18: 3755.7104 | J18: 3338.1852 | K18: 4590.261 | L18: 4836.131 | M18: 4507.0067 | N18: 4503.6154 | O18: 4675.736 | Q18: 403.397 | R18: 431.822 | S18: 457.946 | T18: 391.877 | U18: 366.094 | V18: 437.967 | W18: =(437400155+48648035)/1000000 -> 486.04819 | X18: =(384407313+46196537)/1000000 -> 430.60385 | Y18: =652.286+75.149 -> 727.435 | Z18: =806.035+62.227 -> 868.262 | AA18: =(1504575001+56944289)/1000000 -> 1561.5193 | AB18: =(1419200508+46579609)/1000000 -> 1465.7801 | AC18: =(1313558+48986)/1000 -> 1362.544 | AE18: 2524.617 | AF18: 2446.256 | AG18: 2484.953 | AH18: 2658.933 | AI18: 2670.524 | AJ18: 2748.207 | AK18: =(2335435779+431966950)/1000000 -> 2767.4027 | AL18: =(2352523422+479059756)/1000000 -> 2831.5832 | AM18: =2522.553+602.967 -> 3125.52 | AN18: 3534.436 | AO18: 3579.8481 | AP18: 3539.4831 | AQ18: 3475.46 | AT18: 6341.125 | AU18: 5653.197 | AV18: 5928.781 | AW18: 6073.463 | AX18: 6339.059 | AY18: 7298.073 | AZ18: 7368.432 | BA18: 6900.4488 | BB18: 8865.945 | BC18: 7916.045 | BD18: 9282.81 | BE18: 10139.561 | BF18: 10022.038
A19: Kentucky | B19: KY | C19: 3722.9638 | D19: 3749.2578 | E19: 4069.5006 | F19: 4282.081 | G19: 4393.8626 | H19: 4603.5788 | I19: 4544.6762 | J19: 4765.2355 | K19: 5143.8 | L19: 6047.5 | M19: 5843.9 | N19: 5807.4991 | O19: 5319.2 | Q19: =400.752175+246.1 -> 646.85217 | R19: =475.120319+199.3 -> 674.42032 | S19: =528.118737+223.8 -> 751.91874 | T19: =526.63787+203 -> 729.63787 | U19: =497.479037+245.6 -> 743.07904 | V19: =511.4+238.1 -> 749.5 | W19: =556+206.7 -> 762.7 | X19: =346.4+292.8 -> 639.2 | Y19: 882.8 | Z19: 1186.6 | AA19: 1221.6 | AB19: 1249.1 | AC19: 1834.5 | AE19: 3021.7944 | AF19: 3131.1269 | AG19: 3267.331 | AH19: 3462.7041 | AI19: 3485.2153 | AJ19: 3605.6613 | AK19: 3937.61 | AL19: 4070.9056 | AM19: 4561 | AN19: 5062.9 | AO19: 5576.3 | AP19: 5802.5822 | AQ19: 5821.3 | AT19: 9348.326 | AU19: 9462.035 | AV19: 9966.6309 | AW19: 10338.885 | AX19: 10477.849 | AY19: 10838.2 | AZ19: 11392.698 | BA19: 11566.622 | BB19: 12827.4 | BC19: 14702.5 | BD19: 15147.7 | BE19: 15571.259 | BF19: 15703.2
A20: Louisiana | B20: LA | C20: 2753.8 | D20: 2750.6 | E20: 2886.1 | F20: 2877.8 | G20: 2959.5 | H20: 3268.6 | I20: 3719.4 | J20: 3780.3 | K20: 3956.6 | L20: 4556.1 | M20: 4654.6 | N20: 4797.9 | O20: 4768.2 | Q20: 336.3 | R20: 329.5 | S20: 300.1 | T20: 248.8 | U20: 388.4 | V20: 477.6 | W20: 630.5 | X20: 578.5 | Y20: 805.4 | Z20: 1402.1 | AA20: 1616.8 | AB20: 1636 | AC20: 1451.9 | AE20: 2581.9 | AF20: 2620.1 | AG20: 2700.8 | AH20: 2937.6 | AI20: 3827.2 | AJ20: 3892.1 | AK20: 3459.8 | AL20: 3313.7 | AM20: 3653.1 | AN20: 4406.4 | AO20: 4445 | AP20: 4482.4 | AQ20: 4869.5 | AT20: 10233.1 | AU20: 10300.1 | AV20: 10468.4 | AW20: 10400.4 | AX20: 11935.6 | AY20: 12373.2 | AZ20: 12639.9 | BA20: 12242.8 | BB20: 13232.6 | BC20: 15602.4 | BD20: 16656.9 | BE20: 17105.3 | BF20: 16785
A21: Maine | B21: ME | C21: 1521.8628 | D21: 1406.1177 | E21: 1521.7784 | F21: 1542.6876 | G21: 1523.853 | H21: 1595.1918 | I21: 1701.0058 | J21: 1835.9728 | K21: 2069.7152 | L21: 2580.6797 | M21: 2473.4789 | N21: 2388.9911 | O21: 2723.9713 | Q21: 171.98707 | R21: 182.92818 | S21: 168.96582 | T21: 137.49244 | U21: 175.23911 | V21: 185.73707 | W21: 252.86688 | X21: 216.13149 | Y21: 284.31677 | Z21: 415.81744 | AA21: 451.21106 | AB21: 459.75287 | AC21: 410.11827 | AE21: 986.74764 | AF21: 1106.1582 | AG21: 1195.0313 | AH21: 1274.145 | AI21: 1336.9448 | AJ21: 1423.5511 | AK21: 1503.7718 | AL21: 1555.7131 | AM21: 1804.2261 | AN21: 2078.8757 | AO21: 2173.0458 | AP21: 2262.2337 | AQ21: 2313.9057 | AT21: 3094.3838 | AU21: 3113.4969 | AV21: 3329.3265 | AW21: 3366.1911 | AX21: 3454.9039 | AY21: 3587.6758 | AZ21: 3848.5111 | BA21: 3969.3437 | BB21: 4520.5911 | BC21: 5391.6136 | BD21: 5379.492 | BE21: 5352.7627 | BF21: 5722.4058
A22: Maryland | B22: MD | C22: 7691.381 | D22: 7773.773 | E22: 8346.145 | F22: 8517.585 | G22: 9019.278 | H22: 9507.776 | I22: 10272.352 | J22: 10698.875 | K22: 11704.777 | L22: 13548.045 | M22: 13469.498 | N22: 13616.685 | O22: 14565.248 | Q22: 818.221 | R22: 761.208 | S22: 777.321 | T22: 874.465 | U22: 795.594 | V22: 820.401 | W22: 1033.109 | X22: 1051.8082 | Y22: 1461.893 | Z22: 1700.268 | AA22: 1816.002 | AB22: 1903.9572 | AC22: 1876.709 | AE22: 4067.791 | AF22: 4143.174 | AG22: 4350.726 | AH22: 4444.481 | AI22: 4539.32 | AJ22: 4645.756 | AK22: 4812.09 | AL22: 4634.8736 | AM22: 4988.078 | AN22: 5966.843 | AO22: 6005.249 | AP22: 5896.6057 | AQ22: 6048.565 | AT22: 14867.527 | AU22: 15016.983 | AV22: 15778.374 | AW22: 16082.63 | AX22: 16588.505 | AY22: 17311.127 | AZ22: 18399.039 | BA22: 18634.105 | BB22: 20831.014 | BC22: 24044.529 | BD22: 23672.681 | BE22: 24862.789 | BF22: 25715.684
A23: Massachusetts | B23: MA | C23: 12831 | D23: 13202 | E23: 14449 | F23: 14394 | G23: 14684 | H23: 16240 | I23: 17099 | J23: 17361 | K23: 19593 | L23: 24337 | M23: 21781 | N23: 24117 | O23: 26712 | Q23: 2262 | R23: 2510 | S23: 2561 | T23: 2548 | U23: 2497 | V23: 2761 | W23: 3308 | X23: 2924 | Y23: 4116 | Z23: 5069 | AA23: 5065 | AB23: 4833 | AC23: 4668 | AE23: 5164 | AF23: 5496 | AG23: 5774 | AH23: 6055 | AI23: 6211 | AJ23: 6454 | AK23: 6798 | AL23: 6810 | AM23: 7834 | AN23: 8765 | AO23: 9396 | AP23: 9323 | AQ23: 9599 | AT23: 22123 | AU23: 23369 | AV23: 24932 | AW23: 25269 | AX23: 25604 | AY23: 27776 | AZ23: 29693 | BA23: 29609 | BB23: 34137 | BC23: 41105 | BD23: 39165 | BE23: 40800 | BF23: 43705
A24: Michigan | B24: MI | C24: 8269.5 | D24: 8013.1 | E24: 8979.5 | F24: 9368.2 | G24: 9452 | H24: =7266.9+2892.9 -> 10159.8 | I24: =7252.5+2845.1 -> 10097.6 | J24: =6869.7+3093 -> 9962.7 | K24: =7713.5+3458.3 -> 11171.8 | L24: =9199+4059.8 -> 13258.8 | M24: =7762.3+3907.7 -> 11670 | N24: =8333.3+3962.5 -> 12295.8 | O24: =8447.2+4232.2 -> 12679.4 | Q24: 783.1 | R24: 906.4 | S24: 1077.7 | T24: 930.4 | U24: 1105.6 | V24: 1019.9 | W24: 1278.1 | X24: 1100.1 | Y24: 1701.7 | Z24: 2029.3 | AA24: 1609.9 | AB24: 1574 | AC24: 1501.4 | AE24: 7480.4 | AF24: 7895.2 | AG24: 7819 | AH24: 7877.8 | AI24: 7987.4 | AJ24: =1270.9+801.1+5881.1+632.3 -> 8585.4 | AK24: =1277.3+752.5+6008.1+596.4 -> 8634.3 | AL24: =1299.8+747.5+6048.7+613 -> 8709 | AM24: =1470.7+1255.5+6857.6+876.1 -> 10459.9 | AN24: =1694.4+1194.9+7865.1+859.4 -> 11613.8 | AO24: =1626.5+1251.6+7806.9+909.5 -> 11594.5 | AP24: =1572.5+1188.2+7757.8+940.2 -> 11458.7 | AQ24: =1644.9+1149.5+7930.8+921.4 -> 11646.6 | AT24: =9562.5+11269.7 -> 20832.2 | AU24: =9003.4+11520.5 -> 20523.9 | AV24: =10034.3+11747.1 -> 21781.4 | AW24: =10024.5+12118.7 -> 22143.2 | AX24: =10195.4+12685.2 -> 22880.6 | AY24: =11017.1+13302 -> 24319.1 | AZ24: =11115.8+13552.3 -> 24668.1 | BA24: =10775.5+13990.6 -> 24766.1 | BB24: =13009.5+16056.5 -> 29066 | BC24: =15212+17882.6 -> 33094.6 | BD24: =13966.4+17859.9 -> 31826.3 | BE24: =14527.1+18074.5 -> 32601.6 | BF24: =14480.9+18712.8 -> 33193.7
A25: Minnesota | B25: MN | C25: 9013 | D25: 9660 | E25: 10403 | F25: 10739 | G25: 10931 | H25: 11841 | I25: 12444 | J25: 12135 | K25: 14233 | L25: 16873 | M25: 15777.561 | N25: 14873.104 | O25: 16656 | Q25: 1281 | R25: 1278 | S25: 1455 | T25: 1473 | U25: 1205 | V25: 1257 | W25: 1621 | X25: 1539 | Y25: 2258 | Z25: 2823 | AA25: 2928.921 | AB25: 3171 | AC25: 3192 | AE25: 4760 | AF25: 5043 | AG25: 5131 | AH25: 5233 | AI25: 5405 | AJ25: 5453 | AK25: 5762 | AL25: 5746 | AM25: 6169 | AN25: 6644 | AO25: 7446.443 | AP25: 7546 | AQ25: 7436 | AT25: =17147+798 -> 17945 | AU25: =18554+721 -> 19275 | AV25: =19587+753 -> 20340 | AW25: =20110+779 -> 20889 | AX25: =20233+819 -> 21052 | AY25: =21248+814 -> 22062 | AZ25: =22600+879 -> 23479 | BA25: =22077+817 -> 22894 | BB25: =25660+922 -> 26582 | BC25: =29390+927 -> 30317 | BD25: =29139+1346 -> 30485 | BE25: =28562+1747 -> 30309 | BF25: =30365+1616 -> 31981
A26: Mississippi | B26: MS | C26: 1650.1 | D26: 1666.8 | E26: 1743.4 | F26: 1769.4 | G26: 1781.7 | H26: 1826.6 | I26: 1898.0593 | J26: 1819.6103 | K26: 2226.2 | L26: 2499.6 | M26: 2388.3697 | N26: 2246.5463 | O26: 2281.2244 | Q26: 524.1 | R26: 677 | S26: 714.1 | T26: 596.3 | U26: 564 | V26: 572.3 | W26: 643.65377 | X26: 548.72883 | Y26: 845.1 | Z26: 854.6 | AA26: 1037.2239 | AB26: 967.75673 | AC26: 735.24867 | AE26: 2144.6 | AF26: 2201.4 | AG26: 2260.8 | AH26: 2300.4 | AI26: 2289.3 | AJ26: 2340.4 | AK26: =(2138037754+326412860)/1000000 -> 2464.4506 | AL26: =2156.1+339.9 -> 2496 | AM26: =2244.4+408.8 -> 2653.2 | AN26: =2553.65323+428.957748 -> 2982.611 | AO26: =2734.066955+388.99789 -> 3123.0648 | AP26: =2815.901977+407.942563 -> 3223.8445 | AQ26: =2865.863821+439.92553 -> 3305.7894 | AT26: 5118.6 | AU26: 5403 | AV26: 5536.5 | AW26: 5686.7 | AX26: 5653.9 | AY26: 5691.8 | AZ26: 5967.8 | BA26: 5817.1 | BB26: 6741.3 | BC26: 7386.7 | BD26: 7694.1021 | BE26: 7707.1054 | BF26: 7642.7386
A27: Missouri | B27: MO | C27: 6367.9711 | D27: 6352.5192 | E27: 6890.8156 | F27: 7158.2409 | G27: 7320.5998 | H27: 7728.4791 | I27: 7646.9414 | J27: 6952.2002 | K27: 8916.2318 | L27: 9971.4964 | M27: 9984.7431 | N27: =9048.94027599+746.4212 -> 9795.3615 | O27: =(9165090388+718611242)/1000000 -> 9883.7016 | Q27: 525.67899 | R27: 540.71551 | S27: 558.62913 | T27: 468.28902 | U27: 435.09775 | V27: 461.7124 | W27: 526.56631 | X27: 463.1309 | Y27: 797.10995 | Z27: 909.67161 | AA27: 1058.8398 | AB27: 1050.7103 | AC27: 994.17233 | AE27: 1897.5434 | AF27: 1969.3863 | AG27: 2014.3631 | AH27: 2102.6337 | AI27: 2147.1411 | AJ27: 2196.6737 | AK27: 2237.1496 | AL27: 2276.3901 | AM27: 2428.8572 | AN27: 2746.8829 | AO27: 2943.6498 | AP27: 3184.1043 | AQ27: 3223.3634 | AT27: 8082.6866 | AU27: 8003.2897 | AV27: 8709.1671 | AW27: 8786.7731 | AX27: 9016.2418 | AY27: 9468.5807 | AZ27: 9567.3559 | BA27: 8933.5196 | BB27: 11239.918 | BC27: 12881.027 | BD27: 13234.563 | BE27: 13429.144 | BF27: 13430.979
A28: Montana | B28: MT | C28: 1047.79 | D28: 1063.284 | E28: 1175.745 | F28: 1184.8278 | G28: 1168.225 | H28: 1297.777 | I28: 1429.01 | J28: 1435.24 | K28: 1765.4 | L28: 2393.807 | M28: 2254.3051 | N28: 2243.9463 | O28: 2329.58 | Q28: 177.497 | R28: 147.548 | S28: 172.729 | T28: 118.387 | U28: 133.992 | V28: 167.1 | W28: 186.536 | X28: 187.358 | Y28: 266.5 | Z28: 293.683 | AA28: 309.88362 | AB28: 312.27636 | AC28: 321.208 | AE28: N/A | AF28: N/A | AG28: N/A | AH28: N/A | AI28: N/A | AJ28: N/A | AK28: N/A | AL28: N/A | AM28: N/A | AN28: N/A | AO28: N/A | AP28: N/A | AQ28: N/A | AT28: 2078 | AU28: 2077.044 | AV28: 2200 | AW28: 2121 | AX28: 2141 | AY28: 2405.447 | AZ28: 2572.629 | BA28: 2533.321 | BB28: 2963.8467 | BC28: 3891.6402 | BD28: 3687.7434 | BE28: 3916.9224 | BF28: 4034.369
A29: Nebraska | B29: NE | C29: 2101.912 | D29: 2060.7589 | E29: 2205.4639 | F29: 2221.0888 | G29: 2224.8401 | H29: 2360.5959 | I29: 2545.68 | J29: 2445.6475 | K29: 3130.5993 | L29: 3243.2376 | M29: 3005.9521 | N29: 2479.0542 | O29: 2179.9339 | Q29: 275.56299 | R29: 306.59103 | S29: 346.47738 | T29: 307.66969 | U29: 264.43971 | V29: 313.68952 | W29: 423.73757 | X29: 391.16375 | Y29: 571.22032 | Z29: 715.15274 | AA29: 692.96473 | AB29: 1724.9081 | AC29: 1075.0851 | AE29: 1474.9426 | AF29: 1524.7938 | AG29: 1535.4195 | AH29: 1528.0233 | AI29: 1548.3888 | AJ29: 1602.7374 | AK29: 1658.1071 | AL29: 1848.236 | AM29: 2009.7483 | AN29: 2133.1521 | AO29: 2335.8999 | AP29: 2458.8341 | AQ29: 2516.7442 | AT29: 4052.3586 | AU29: 4117.4082 | AV29: 4305.0993 | AW29: 4307.9813 | AX29: 4265.7719 | AY29: 4566.9958 | AZ29: 4896.3785 | BA29: 4939.7626 | BB29: 5959.0424 | BC29: 6348.9947 | BD29: 6367.9825 | BE29: 7155.8106 | BF29: 6159.0417
A30: Nevada | B30: NV | C30: N/A | D30: N/A | E30: N/A | F30: N/A | G30: N/A | H30: N/A | I30: N/A | J30: N/A | K30: N/A | L30: N/A | M30: N/A | N30: N/A | Q30: N/A | R30: N/A | S30: N/A | T30: N/A | U30: N/A | V30: N/A | W30: N/A | X30: N/A | Y30: N/A | Z30: N/A | AA30: N/A | AB30: N/A | AE30: 888.65896 | AF30: 931.31969 | AG30: 994.76497 | AH30: 1036.5492 | AI30: 1090.6954 | AJ30: 1142.7998 | AK30: 1235.1243 | AL30: 1214.7013 | AM30: 1325.814 | AN30: 1613.3418 | AO30: 1721.5439 | AP30: 1790.4336 | AT30: 3132.6018 | AU30: 3066.9464 | AV30: 3284.4827 | AW30: 3693.8428 | AX30: 3880.5062 | AY30: 4018.7115 | AZ30: 4287.5042 | BA30: 4077.2473 | BB30: 4474.3 | BC30: 5439.3351 | BD30: 5762.4808 | BE30: 6009.7865
A31: New Hampshire | B31: NH | C31: 92.974 | D31: 79.811 | E31: 96.861 | F31: 89.265 | G31: 94.287 | H31: 105.826 | I31: 114.68 | J31: 125.7 | K31: 120.7 | L31: 157.5 | M31: 147.3 | N31: 184.6 | O31: 72.7 | Q31: 551.8 | R31: 549.6 | S31: 561.7 | T31: 699.3 | U31: 637.8 | V31: 781.1 | W31: 805.6 | X31: 709.8 | Y31: 1003.2 | Z31: 1224 | AA31: 1258.9 | AB31: 1225.7 | AC31: 1095.6 | AE31: N/A | AF31: N/A | AG31: N/A | AH31: N/A | AI31: N/A | AJ31: N/A | AK31: N/A | AL31: N/A | AM31: N/A | AN31: N/A | AO31: N/A | AP31: N/A | AQ31: N/A | AT31: 2275.6 | AU31: 2173.2 | AV31: 2266.7 | AW31: 2457.6 | AX31: 2407.5 | AY31: 2577.2 | AZ31: 2644.6 | BA31: 2520.2 | BB31: 2979.7 | BC31: 3234.4 | BD31: 3218.5 | BE31: 3332 | BF31: 3101.1
A32: New Jersey | B32: NJ | C32: 12108.6 | D32: 12311.7 | E32: 13250 | F32: 13355.992 | G32: 13958.119 | H32: 15037.844 | I32: 15903.3 | J32: 16253.7 | K32: 17469.9 | L32: 20737.5 | M32: 18798.701 | N32: 18880.484 | Q32: 2364 | R32: 2101 | S32: 2655 | T32: 2295.378 | U32: 2141.508 | V32: 2315.529 | W32: 4029 | X32: 3807.9344 | Y32: 4884.5 | Z32: 5705.2811 | AA32: 5512.7339 | AB32: 4703.4641 | AE32: 8235 | AF32: 8640 | AG32: 8875 | AH32: 9203.341 | AI32: 9448.39 | AJ32: 9619.151 | AK32: 9939 | AL32: 9772.1042 | AM32: 11275.5 | AN32: 12525.219 | AO32: 13079.431 | AP32: 13292.492 | AT32: 30924.1 | AU32: 31347.7 | AV32: 33097.2 | AW32: 32872.6 | AX32: 34120.9 | AY32: 35785.9 | AZ32: 38316.2 | BA32: 38013.2 | BB32: 48553 | BC32: 52653 | BD32: 52099.5 | BE32: 53087
A33: New Mexico | B33: NM | C33: 1240.9453 | D33: 1254.9396 | E33: 1339.7115 | F33: 1327.2075 | G33: 1380.6752 | H33: 1519 | I33: 1672 | J33: 1691.9 | K33: 1904.1 | L33: 2327.6 | M33: 2514.7 | N33: 2207.6 | O33: 2143.1 | Q33: 267.15697 | R33: 196.76188 | S33: 254.47678 | T33: 118.50192 | U33: 70.155693 | V33: 106.6 | W33: 122.8 | X33: 63.2 | Y33: 149.7 | Z33: 343.9 | AA33: 439.1 | AB33: 627.2 | AC33: 782.5 | AE33: 1968.5711 | AF33: 2070.4043 | AG33: 2166.9929 | AH33: 2022.2974 | AI33: 2062.0775 | AJ33: 2437.2 | AK33: 2737.7 | AL33: 3005.7 | AM33: 2914.2 | AN33: 3491 | AO33: 4045.2 | AP33: 4131.8 | AQ33: 4383.5 | AT33: 5708.6 | AU33: 6040.5 | AV33: 6235.9 | AW33: 5712.1 | AX33: 6461.6 | AY33: 6881.3 | AZ33: 7910.3 | BA33: 8182.2 | BB33: 8051 | BC33: 8772.5 | BD33: 10890.1 | BE33: 13190 | BF33: 13624.1
A34: New York | B34: NY | C34: 40227 | D34: 42961 | E34: 43709 | F34: 47055 | G34: 47565 | H34: 51501 | I34: 48088 | J34: 53660 | K34: 54967 | L34: 70737 | M34: 58776 | N34: 53839 | O34: 61201 | Q34: 8465 | R34: 8259 | S34: 8504 | T34: 7884 | U34: 6979 | V34: 7164 | W34: 7912 | X34: 8995 | Y34: 8792 | Z34: 27725 | AA34: 28617 | AB34: 27695 | AC34: 31373 | AE34: 14615 | AF34: 15099 | AG34: 15384 | AH34: 15725 | AI34: 16212 | AJ34: 16711 | AK34: 17357 | AL34: 18023 | AM34: 16117 | AN34: 19621 | AO34: 20585 | AP34: 21865 | AQ34: 22352 | AT34: =66302+24036 -> 90338 | AU34: =69690+24234 -> 93924 | AV34: =71034+29438 -> 100472 | AW34: =74673+27268 -> 101941 | AX34: =74372+26594 -> 100966 | AY34: =79266+27262 -> 106528 | AZ34: =75578+31184 -> 106762 | BA34: =82889+29466 -> 112355 | BB34: =191300-78152 -> 113148 | BC34: =244375-95307 -> 149068 | BD34: =233062-89563 -> 143499 | BE34: =234478-94276 -> 140202 | BF34: =248986-96713 -> 152273
A35: North Carolina | B35: NC | C35: 10953.14 | D35: 10272.4 | E35: 11078.5 | F35: 11905.2 | G35: 11969.7 | H35: 12517.5 | I35: 13166 | J35: 12414.7 | K35: 15822.6 | L35: 17567.6 | M35: 16762.5 | N35: 16562.9 | O35: 17012.2 | Q35: =1191.7+660.1 -> 1851.8 | R35: =1356.9+697 -> 2053.9 | S35: =1327.7+544.1 -> 1871.8 | T35: =1058.2+524.4 -> 1582.6 | U35: =752.2+748.1 -> 1500.3 | V35: =739+669 -> 1408 | W35: =830.5+749.6 -> 1580.1 | X35: =657.8+646 -> 1303.8 | Y35: =1511.5+869.8 -> 2381.3 | Z35: =1625.8+888.3 -> 2514.1 | AA35: =1635+848 -> 2483 | AB35: =1552.2+741.4 -> 2293.6 | AC35: =1569.7+ 775 -> 2344.7 | AE35: 5294.2 | AF35: 5566.5 | AG35: 6252 | AH35: 6559.5 | AI35: 7004 | AJ35: 7337.4 | AK35: 7751.3 | AL35: 7820.6 | AM35: 9023.6 | AN35: 10200.7 | AO35: 10801.2 | AP35: 10905.8 | AQ35: 11006.2 | AT35: 20540.5 | AU35: 20152.7 | AV35: 21448 | AW35: 22150.7 | AX35: 22614.1 | AY35: 23565.2 | AZ35: 24826.7 | BA35: 23939.3 | BB35: 29698.9 | BC35: 33208.6 | BD35: 33535.4 | BE35: 33693.8 | BF35: 34559
A36: North Dakota | B36: ND | C36: 616.16522 | D36: 514.4322 | E36: 535.63037 | F36: 353.93775 | G36: 312.72192 | H36: 364.25412 | I36: 413.80077 | J36: 352.0966 | K36: 465.45726 | L36: 455.99017 | M36: 482.78239 | N36: 355.00178 | O36: 453.20509 | Q36: 187.06748 | R36: 239.40425 | S36: 195.83881 | T36: 97.5808 | U36: 69.225591 | V36: 92.34817 | W36: 147.75845 | X36: 91.564033 | Y36: 146.84595 | Z36: 213.43463 | AA36: 308.26094 | AB36: 276.65747 | AC36: 330.59823 | AE36: 1165.5358 | AF36: 1212.4601 | AG36: 1265.7867 | AH36: 925.36957 | AI36: 792.49826 | AJ36: 829.12021 | AK36: 957.35951 | AL36: 970.55956 | AM36: 853.43221 | AN36: 976.11374 | AO36: 1154.5302 | AP36: 1200.1614 | AQ36: 1253.7592 | AT36: 2635.5788 | AU36: 2927.3514 | AV36: 2874.4461 | AW36: 2540.2247 | AX36: 2408.9807 | AY36: 2348.6378 | AZ36: 2564.8109 | BA36: 2549.8917 | BB36: 3202.0126 | BC36: 2595.2889 | BD36: 2724.553 | BE36: 3012.5148 | BF36: 2625.7071
A37: Ohio | B37: OH | C37: 9507.83 | D37: 8064.9 | E37: 8506.7 | F37: 7799.3 | G37: 7606.5 | H37: 8411 | I37: 8910.2 | J37: 7881.3 | K37: 10201.3 | L37: 10752.2 | M37: 10797.208 | N37: 9519.3 | O37: 10461.519 | Q37: 261.9 | R37: 197.8 | S37: 182.1 | T37: 213.5 | U37: 187.3 | V37: 201.1 | W37: 202.4 | X37: 214.9 | Y37: 226.4 | Z37: 202.8 | AA37: 239.236 | AB37: 204.9 | AC37: 200.586 | AE37: 8444.85 | AF37: 9165.8 | AG37: 9960.2 | AH37: 10348 | AI37: 10614.6 | AJ37: 10148.1 | AK37: 10573.4 | AL37: 10685.7 | AM37: 12190.6 | AN37: 13029.6 | AO37: 13483.137 | AP37: 13700.5 | AQ37: 14144.774 | AT37: 21015.71 | AU37: 20134.7 | AV37: 21405.8 | AW37: 21821.6 | AX37: 21885.8 | AY37: 22423.2 | AZ37: 23489.6 | BA37: 22623 | BB37: 26467 | BC37: 28152.5 | BD37: 28915.687 | BE37: 27944.5 | BF37: 29220.222
A38: Oklahoma | B38: OK | C38: 2056.7675 | D38: 2027.9756 | E38: 2160.7781 | F38: 1989.6995 | G38: 1881.4768 | H38: 2083.7582 | I38: 2272.8898 | J38: 2434.1341 | K38: 2816.6953 | L38: 3149.1817 | M38: 3372.6309 | N38: 3253.4388 | O38: 3518.7149 | Q38: 451.63982 | R38: 306.53686 | S38: 303.45696 | T38: 259.88297 | U38: 130.621 | V38: 192.84089 | W38: 241.89665 | X38: 238.25998 | Y38: 452.13785 | Z38: 527.11497 | AA38: 598.49755 | AB38: 331.79365 | AC38: 481.65537 | AE38: =1900.847138+186.590009 -> 2087.4371 | AF38: =1959.396264+196.693829 -> 2156.0901 | AG38: =2019.725448+204.233847 -> 2223.9593 | AH38: =1893.58564+169.697019 -> 2063.2827 | AI38: =1850.145427+188.02528 -> 2038.1707 | AJ38: =2136.000056+232.925511 -> 2368.9256 | AK38: =2136.539388+306.40179 -> 2442.9412 | AL38: =2019.904805+329.163434 -> 2349.0682 | AM38: =2196.722155+369.967042 -> 2566.6892 | AN38: =2495.226162+437.992983 -> 2933.2191 | AO38: =2629.188327+483.83612 -> 3113.0244 | AP38: =2610.353375+517.902143 -> 3128.2555 | AQ38: =2296.300534+541.472159 -> 2837.7727 | AT38: 5604.0609 | AU38: 5627.4497 | AV38: 5726.5112 | AW38: 5202.1672 | AX38: 5042.9175 | AY38: 5854.2306 | AZ38: 6859.7413 | BA38: 6266.1012 | BB38: 7006.7353 | BC38: 8493.6733 | BD38: 9104.3013 | BE38: 8466.2585 | BF38: 8745.416
A39: Oregon | B39: OR | C39: 6255.646 | D39: 6628.0213 | E39: 7292.1572 | F39: 7598.557 | G39: 8457.274 | H39: 8872.479 | I39: 9908.589 | J39: 7192.048 | K39: 12772.597 | L39: 12436.649 | M39: 13246.856 | N39: 9128.408 | O39: 13041.019 | Q39: 452.88819 | R39: 494.75937 | S39: 621.76976 | T39: 603.078 | U39: 607.658 | V39: 754.98 | W39: 926.66919 | X39: 488.294 | Y39: 1478.618 | Z39: 1538.497 | AA39: 1618.518 | AB39: 1623.083 | AC39: 1527.687 | AE39: N/A | AF39: N/A | AG39: N/A | AH39: N/A | AI39: N/A | AJ39: N/A | AK39: N/A | AL39: N/A | AM39: N/A | AN39: N/A | AO39: N/A | AP39: N/A | AQ39: N/A | AT39: 7213.0734 | AU39: 7612.1 | AV39: 8418.3 | AW39: 8713.1 | AX39: 9810 | AY39: 10244.3 | AZ39: 11541.5 | BA39: 8319.2849 | BB39: 15218.9 | BC39: 14837.7 | BD39: 15759.2 | BE39: 11878.415 | BF39: 15505.895
A40: Pennsylvania | B40: PA | C40: 11371.2 | D40: 11437.3 | E40: 12107.4 | F40: 12506 | G40: 12664.4 | H40: 13399 | I40: 14095.5 | J40: 12835 | K40: 16283.4 | L40: 18125.7 | M40: 17628.1 | N40: 17856.8 | O40: 18956.5 | Q40: 2423.4 | R40: 2501.6 | S40: 2811.5 | T40: 2842.4 | U40: 2751.5 | V40: 2879 | W40: 3397.5 | X40: 2826.9 | Y40: 4423.8 | Z40: 5323.1 | AA40: 6142.9 | AB40: 5651.5 | AC40: 4719.9 | AE40: 8893.7 | AF40: 9129.6 | AG40: 9493.1 | AH40: 9795.2 | AI40: 10005.2 | AJ40: 10381.4 | AK40: 11099.6 | AL40: 10817.8 | AM40: 12834.9 | AN40: 13915.2 | AO40: 14024.4 | AP40: 14255.9 | AQ40: 14693.2 | AT40: 28646.9 | AU40: 28607.2 | AV40: 30592.5 | AW40: 30901.7 | AX40: 31669.7 | AY40: 34566.9 | AZ40: 34857.9 | BA40: 32275.8 | BB40: 40389.4 | BC40: 48134.2 | BD40: 44917.1 | BE40: 45473.5 | BF40: 46408.4
A41: Rhode Island | B41: RI | C41: 1085.7653 | D41: 1115.5125 | E41: 1227.582 | F41: 1217.4296 | G41: 1243.8071 | H41: 1345.2721 | I41: 1396.9626 | J41: 1405.5085 | K41: 1615.5123 | L41: 1985.9234 | M41: 1813.6051 | N41: 1819.193 | O41: 1975.2903 | Q41: 144.42283 | R41: 130.82605 | S41: 170.72237 | T41: 156.00489 | U41: =(119289609+22188601)/1000000 -> 141.47821 | V41: =(127674418+29176929)/1000000 -> 156.85135 | W41: =(155110673+21145195)/1000000 -> 176.25587 | X41: =148.605498+44.612483 -> 193.21798 | Y41: =201.788847+34.85603 -> 236.64488 | Z41: =288.450198+36.263375 -> 324.71357 | AA41: =272.572015+31.6535 -> 304.22552 | AB41: =367.504982+47.67806 -> 415.18304 | AC41: =(332787290+7603962)/1000000 -> 340.39125 | AE41: 878.86607 | AF41: 916.08325 | AG41: 963.44637 | AH41: 971.87292 | AI41: 998.19657 | AJ41: 1057.1899 | AK41: 1125.6983 | AL41: 1167.4235 | AM41: 1341.4722 | AN41: 1511.4527 | AO41: 1564.768 | AP41: 1635.4276 | AQ41: 1672.7087 | AT41: 3323.9988 | AU41: 3430.2624 | AV41: 3641.1086 | AW41: 3663.5926 | AX41: 3684.3576 | AY41: 3908.3844 | AZ41: 4024.5796 | BA41: 4063.7134 | BB41: 4437.4786 | BC41: 5204.2441 | BD41: 5211.7294 | BE41: 5418.7038 | BF41: 5610.0136 | BG41: PRELIMINARY
A42: South Carolina | B42: SC | C42: 3357.5177 | D42: 3422.6043 | E42: 3661.1946 | F42: 3832.8465 | G42: 4107.647 | H42: 4398.4237 | I42: 4714.9982 | J42: 5019.42 | K42: 5421.2805 | L42: 6827.5601 | M42: 5758.2119 | N42: 6113.1849 | O42: 6722.1869 | Q42: 386.66859 | R42: 331.14805 | S42: 377.66926 | T42: 411.14812 | U42: 320.4155 | V42: 375.18959 | W42: 494.21444 | X42: 423.05219 | Y42: 669.22111 | Z42: 1129.3751 | AA42: 1262.2218 | AB42: 1293.0637 | AC42: 1321.6285 | AE42: 2428.9942 | AF42: 2504.9148 | AG42: 2643.7401 | AH42: 2818.6056 | AI42: 2896.2713 | AJ42: 3034.4152 | AK42: 3186.4255 | AL42: 3286.7717 | AM42: 3825.9203 | AN42: 4401.9932 | AO42: 4660.0788 | AP42: 4786.3799 | AQ42: 5027.4404 | AT42: 6924.8402 | AU42: 7033.2486 | AV42: 7513.4535 | AW42: 7839.424 | AX42: 8158.5095 | AY42: 8706.0174 | AZ42: 9402.1268 | BA42: 9793.2775 | BB42: 11089.127 | BC42: 13654.415 | BD42: 13094.202 | BE42: 13707.681 | BF42: 14858.559
A43: South Dakota | B43: SD | C43: N/A | D43: N/A | E43: N/A | F43: N/A | G43: N/A | H43: N/A | I43: N/A | J43: N/A | K43: N/A | L43: N/A | M43: N/A | N43: N/A | O43: N/A | Q43: 17.537046 | R43: 10.782035 | S43: 8.583099 | T43: 10.512754 | U43: 14.688771 | V43: 13.49494 | W43: 17.25612 | X43: 12.060604 | Y43: 18.702022 | Z43: 22.51185 | AA43: 20.425082 | AB43: 28.659255 | AC43: 26.180028 | AE43: 776.09554 | AF43: 823.40159 | AG43: 836.58711 | AH43: 860.90571 | AI43: 951.22308 | AJ43: 988.8236 | AK43: 1025.4012 | AL43: 1072.8306 | AM43: 1209.3423 | AN43: 1356.8448 | AO43: 1480.5729 | AP43: 1441.6788 | AQ43: 1432.6311 | AT43: 1258.1772 | AU43: 1353.7972 | AV43: 1381.3849 | AW43: 1438.3868 | AX43: 1540.794 | AY43: 1593.4059 | AZ43: 1641.2033 | BA43: 1699.623 | BB43: 1936.1985 | BC43: 2126.4094 | BD43: 2298.2901 | BE43: 2413.3093 | BF43: 2380.5491
A44: Tennessee | B44: TN | C44: 233.4188 | D44: 239.3163 | E44: 303.3535 | F44: 322.356 | G44: 250.1262 | H44: 245.9796 | I44: 203.8178 | J44: 150.7089 | K44: 86.0254 | L44: 6.6186 | M44: 2.6623 | N44: 1.9803 | O44: 0 | Q44: 2020.5047 | R44: 1858.6383 | S44: 2164.486 | T44: 2311.7051 | U44: =(1729020100+891185100)/1000000 -> 2620.2052 | V44: =928.0281+1642.743 -> 2570.7711 | W44: =1036.8685+1715.1553 -> 2752.0238 | X44: =1004.2635+1849.1662 -> 2853.4297 | Y44: =1222.4804+2272.7676 -> 3495.248 | Z44: =1514.9712+3029.6181 -> 4544.5893 | AA44: =1453.9371+3332.636 -> 4786.5731 | AB44: =1564.055+3036.4099 -> 4600.4649 | AC44: =(1096661800+2630540200)/1000000 -> 3727.202 | AE44: 7012.0287 | AF44: 7286.1645 | AG44: 7706.0595 | AH44: 8267.2244 | AI44: 8556.7736 | AJ44: 8835.1871 | AK44: 9337.8177 | AL44: 9619.2152 | AM44: 11083.12 | AN44: 12809.892 | AO44: 13677.873 | AP44: 13802.144 | AQ44: 14502.001 | AT44: 13395.559 | AU44: 13546.23 | AV44: 14552.134 | AW44: 15457.645 | AX44: 16069.079 | AY44: 16752.378 | AZ44: 17411.217 | BA44: 18216.957 | BB44: 20400.163 | BC44: 23619.571 | BD44: 25350.991 | BE44: 26269.941 | BF44: 26897.39
A45: Texas | B45: TX | C45: N/A | D45: N/A | E45: N/A | F45: N/A | G45: N/A | H45: N/A | I45: N/A | J45: N/A | K45: N/A | L45: N/A | M45: N/A | N45: N/A | O45: N/A | Q45: N/A | R45: N/A | S45: N/A | T45: N/A | U45: N/A | V45: N/A | W45: N/A | X45: N/A | Y45: N/A | Z45: N/A | AA45: N/A | AB45: N/A | AC45: N/A | AE45: 25943.807 | AF45: 27385.709 | AG45: 28910.857 | AH45: 28245.801 | AI45: 28900.035 | AJ45: 31937.235 | AK45: 34023.916 | AL45: 34099.115 | AM45: 36019.605 | AN45: 42971.904 | AO45: 46581.072 | AP45: 47159.947 | AQ45: 49058.907 | AT45: 66506.056 | AU45: 70676.247 | AV45: 72727.268 | AW45: 71807.036 | AX45: 72829.591 | AY45: 80547.051 | AZ45: 86036.928 | BA45: 83459.569 | BB45: 88556.355 | BC45: =(183344840-72738692)/1000 -> 110606.15 | BD45: =(187788970-68707041)/1000 -> 119081.93 | BE45: =(181117486-58866331)/1000 -> 122251.15 | BF45: =(183048999.98595-59101909.27355)/1000 -> 123947.09
A46: Utah | B46: UT | C46: 2852.0222 | D46: 2889.792 | E46: 3157.669 | F46: 3370.322 | G46: 3609.454 | H46: 3998.996 | I46: 4320.042 | J46: 3985.4 | K46: 6110.511 | L46: 6771.926 | M46: 6432.142 | N46: 6214.529 | O46: 6607.356 | Q46: 338.173 | R46: 313.537 | S46: 373.938 | T46: 338.334 | U46: 328.468 | V46: 447.934 | W46: 520.918 | X46: 355.875 | Y46: 742.697 | Z46: 937.045 | AA46: 869.903 | AB46: 883.39 | AC46: 948.52 | AE46: 1615.9365 | AF46: 1656.806 | AG46: 1714.954 | AH46: 1778.524 | AI46: 1856.754 | AJ46: 2018.747 | AK46: 2116.255 | AL46: 2265.293 | AM46: 2625.318 | AN46: 3098.477 | AO46: 3262.812 | AP46: 3315.555 | AQ46: 3412.47 | AT46: 5768.4295 | AU46: 5860.239 | AV46: 6252.367 | AW46: 6500.786 | AX46: 6894.912 | AY46: 7622.964 | AZ46: 8162.9 | BA46: 7858.348 | BB46: 10733.28 | BC46: 12218.982 | BD46: 12260.541 | BE46: 12291.518 | BF46: 12844.638
A47: Vermont | B47: VT | C47: 660.6 | D47: 671.1 | E47: 705.9 | F47: 747 | G47: 756.5 | H47: 831.97077 | I47: 875.42552 | J47: 925.8 | K47: 1069.8 | L47: 1267.777 | M47: 1209.9712 | N47: 1243.0692 | O47: 1362.9 | Q47: 95 | R47: 94.8 | S47: 121.9 | T47: 117 | U47: 95.8 | V47: 96.363559 | W47: 134.1908 | X47: 147.9 | Y47: 133.4 | Z47: 223.26148 | AA47: 281.36932 | AB47: 238.81253 | AC47: 272.6 | AE47: 346.8 | AF47: 353.6 | AG47: 364.6 | AH47: 370.7 | AI47: 376.7 | AJ47: 397.78506 | AK47: 412.50923 | AL47: 432.5 | AM47: 507.6 | AN47: 545.18198 | AO47: 584.04754 | AP47: 595.17829 | AQ47: 618.1 | AT47: 1520.9 | AU47: 1567.7 | AV47: 1625.7 | AW47: 1673.7 | AX47: 1717.5 | AY47: =1667.2+87+71.1 -> 1825.3 | AZ47: =1763+93.9+68.4 -> 1925.3 | BA47: =1829.7+84.8+71.4 -> 1985.9 | BB47: =2068.5+84.1+77.5 -> 2230.1 | BC47: =2468.2+83.9+76 -> 2628.1 | BD47: =2536.1+143.1+74.8 -> 2754 | BE47: =2560.1+181.7+70 -> 2811.8 | BF47: =2805.3+153.3+67.4 -> 3026
A48: Virginia | B48: VA | C48: 11340 | D48: 11253.3 | E48: 12328.7 | F48: 12555.6 | G48: 13052.9 | H48: 14105.776 | I48: 15226.471 | J48: 15351.6 | K48: 17303.7 | L48: 20410.2 | M48: 18983.556 | N48: 20310.406 | O48: 21892.442 | Q48: 796.7 | R48: 757.5 | S48: 831.9 | T48: 764.9 | U48: 827 | V48: 861.897 | W48: 943.391 | X48: 1011.7 | Y48: 1515.7 | Z48: 1978.7 | AA48: 2031.1 | AB48: 1907.065 | AC48: 1878.586 | AE48: =3219.8+521.2 -> 3741 | AF48: =3066.5+822.6 -> 3889.1 | AG48: =3235.4+994.9 -> 4230.3 | AH48: =3295.9+1000.5 -> 4296.4 | AI48: =3357.1+1020.4 -> 4377.5 | AJ48: =3461.772+1043.805 -> 4505.577 | AK48: =3580.355+1087.842 -> 4668.197 | AL48: =3706.8+1124.2 -> 4831 | AM48: =4166.2+1264.1 -> 5430.3 | AN48: =4558.1+1368.3 -> 5926.4 | AO48: =4734.549+1416.7 -> 6151.249 | AP48: =4709.661+1377.114 -> 6086.775 | AQ48: =4812.737+1412.43 -> 6225.167 | AT48: =16684.6+2493.6 -> 19178.2 | AU48: =16411.4+2806.3 -> 19217.7 | AV48: =17735.6+3137.2 -> 20872.8 | AW48: =18040.1+3355.6 -> 21395.7 | AX48: =18695.1+3452.2 -> 22147.3 | AY48: =19880.8+3457.1 -> 23337.9 | AZ48: =21307.5+3555.2 -> 24862.7 | BA48: =21737.8+3605.4 -> 25343.2 | BB48: =24878.5+4133.6 -> 29012.1 | BC48: =28934.9+4594.1 -> 33529 | BD48: =27909.9+4817.7 -> 32727.6 | BE48: =29448.224+4872.417 -> 34320.641 | BF48: =31233.034+5111.407 -> 36344.441
A49: Washington | B49: WA | C49: N/A | D49: N/A | E49: N/A | F49: N/A | G49: N/A | H49: N/A | I49: N/A | J49: N/A | K49: N/A | L49: N/A | M49: N/A | N49: N/A | O49: N/A | Q49: N/A | R49: N/A | S49: N/A | T49: N/A | U49: N/A | V49: N/A | W49: N/A | X49: N/A | Y49: N/A | Z49: N/A | AA49: N/A | AB49: N/A | AC49: N/A | AE49: 7686.859 | AF49: 8236.839 | AG49: 8793.24 | AH49: 9563.093 | AI49: 10132.787 | AJ49: 10924.744 | AK49: 11872.905 | AL49: =11296.2+719.2 -> 12015.4 | AM49: =12454.9+835.3 -> 13290.2 | AN49: =14001+897 -> 14898 | AO49: =14795.6+1010.1 -> 15805.7 | AP49: =14769.9+984.4 -> 15754.3 | AQ49: =15071.1+1043 -> 16114.1 | AT49: 15783 | AU49: 16383 | AV49: 17283 | AW49: 18579 | AX49: 19739 | AY49: 21712 | AZ49: 22430 | BA49: 23817 | BB49: 26986.1 | BC49: 30029.7 | BD49: 30971.9 | BE49: 31093.5 | BF49: 32298.8
A50: West Virginia | B50: WV | C50: 1700.547 | D50: 1664.066 | E50: 1840.056 | F50: 1803.311 | G50: 1813.867 | H50: 1919.57 | I50: 2096.807 | J50: 1947.946 | K50: 2253.788 | L50: 2502.828 | M50: 2663.568 | N50: 2239.859 | O50: 2126.396 | Q50: 238.13 | R50: 203.508 | S50: 186.101 | T50: 143.605 | U50: 116.306 | V50: 110.068 | W50: 198.032 | X50: 151.988 | Y50: 320.487 | Z50: 366.316 | AA50: 419.965 | AB50: 465.463 | AC50: 376.219 | AE50: 1193.29 | AF50: 1173.097 | AG50: 1228.221 | AH50: 1231.044 | AI50: 1222.283 | AJ50: 1247.031 | AK50: 1370.157 | AL50: 1386.571 | AM50: 1537.245 | AN50: 1655.483 | AO50: 1750.434 | AP50: 1816.544 | AQ50: 1821.247 | AT50: 4059.121 | AU50: 4106.106 | AV50: 4203.81 | AW50: 4102.679 | AX50: 4166.51 | AY50: 4245.258 | AZ50: 4756.336 | BA50: 4494.857 | BB50: 4987.577 | BC50: 5887.899 | BD50: 6483.291 | BE50: 5710.575 | BF50: 5519.363
A51: Wisconsin | B51: WI | C51: 7496.9 | D51: 7061.4 | E51: 7325.8 | F51: 7740.8 | G51: 8039.4539 | H51: 8479.0532 | I51: 8994.0962 | J51: 8742.2663 | K51: 9283.4 | L51: 9214.4 | M51: 9414.7 | N51: 9717.592 | O51: 10451.1 | Q51: 925.4 | R51: 967.2 | S51: 1004.9 | T51: 963 | U51: 921.00102 | V51: 893.98872 | W51: 1338.0633 | X51: 1607.8727 | Y51: 2560.1 | Z51: 2960 | AA51: 2748.5 | AB51: 2702.1 | AC51: 2761.7 | AE51: 4410.1 | AF51: 4628.3 | AG51: 4892.1 | AH51: 5065.8 | AI51: 5223.9 | AJ51: 5448.117 | AK51: 5695.5484 | AL51: 5836.215 | AM51: 6373.5 | AN51: 6978.3 | AO51: 7456.1 | AP51: 7587.5 | AQ51: 7831.6 | AT51: 14085.6 | AU51: 13948.1 | AV51: 14541.2 | AW51: 15097.5 | AX51: 15517.6 | AY51: 16144.2 | AZ51: 17341.4 | BA51: 17532.172 | BB51: 19572.8 | BC51: 20548.4 | BD51: 20974 | BE51: 21329.6 | BF51: 22362.9
A52: Wyoming | B52: WY | C52: N/A | D52: N/A | E52: N/A | F52: N/A | G52: N/A | H52: N/A | I52: N/A | J52: N/A | K52: N/A | L52: N/A | M52: N/A | N52: N/A | O52: N/A | Q52: N/A | R52: N/A | S52: N/A | T52: N/A | U52: N/A | V52: N/A | W52: N/A | X52: N/A | Y52: N/A | Z52: N/A | AA52: N/A | AB52: N/A | AC52: N/A | AE52: 481.43139 | AF52: 521.10261 | AG52: 544.03017 | AH52: 432.00856 | AI52: 407.31582 | AJ52: 480.04428 | AK52: 518.52162 | AL52: 487.23253 | AM52: 493.10191 | AN52: 562.54959 | AO52: 635.93381 | AP52: 646.9233 | AQ52: 635.79614 | AT52: 1381.2048 | AU52: 1382.3767 | AV52: 1509.0885 | AW52: 1001.2522 | AX52: 1173.0461 | AY52: 1393.5513 | AZ52: 1394.2852 | BA52: 1201.3163 | BB52: 1407.9873 | BC52: 1491.7299 | BD52: 1394.5026 | BE52: 1664.0441 | BF52: 2026.7114
A53: United States | B53: US | C53: =SUM(C3:C52) -> 309889.84 | D53: =SUM(D3:D52) -> 313514.13 | E53: =SUM(E3:E52) -> 337138.26 | F53: =SUM(F3:F52) -> 345512.72 | G53: =SUM(G3:G52) -> 356051.39 | H53: =SUM(H3:H52) -> 393322.43 | I53: =SUM(I3:I52) -> 408518.86 | J53: =SUM(J3:J52) -> 407037.93 | ... O53: =SUM(O3:O52) -> 519912.1 | Q53: =SUM(Q3:Q52) -> 48867.191 | R53: =SUM(R3:R52) -> 50153.46 | S53: =SUM(S3:S52) -> 53022.062 | T53: =SUM(T3:T52) -> 50896.76 | U53: =SUM(U3:U52) -> 49304.677 | V53: =SUM(V3:V52) -> 52866.41 | W53: =SUM(W3:W52) -> 64769.585 | X53: =SUM(X3:X52) -> 61366.892 | ... AC53: =SUM(AC3:AC52) -> 141613.62 | AE53: =SUM(AE3:AE52) -> 223438.39 | AF53: =SUM(AF3:AF52) -> 234180.28 | AG53: =SUM(AG3:AG52) -> 245882.7 | AH53: =SUM(AH3:AH52) -> 252413.76 | AI53: =SUM(AI3:AI52) -> 259657.88 | AJ53: =SUM(AJ3:AJ52) -> 270991.62 | AK53: =SUM(AK3:AK52) -> 284487.75 | AL53: =SUM(AL3:AL52) -> 285496.73 | ... AQ53: =SUM(AQ3:AQ52) -> 378516.23 | AT53: =SUM(AT3:AT52) -> 765394.24 | AU53: =SUM(AU3:AU52) -> 784227.65 | AV53: =SUM(AV3:AV52) -> 822369.1 | AW53: =SUM(AW3:AW52) -> 830716.94 | AX53: =SUM(AX3:AX52) -> 857649.96 | AY53: =SUM(AY3:AY52) -> 920553.97 | AZ53: =SUM(AZ3:AZ52) -> 967286.35 | BA53: =SUM(BA3:BA52) -> 956128.51 | ... BF53: =SUM(BF3:BF52) -> 1316125

Sheet Forecasts
A1: $ millions | C1: PIT | D1: PIT | E1: PIT | F1: PIT | G1: PIT | H1: PIT | I1: PIT | J1: PIT | K1: PIT | L1: PIT | M1: PIT | N1: PIT | O1: PIT | P1: PIT | Q1: PIT | S1: CIT | T1: CIT | U1: CIT | V1: CIT | W1: CIT | X1: CIT | Y1: CIT | Z1: CIT | AA1: CIT | AB1: CIT | AC1: CIT | AD1: CIT | AE1: CIT | AF1: CIT | AG1: CIT | AI1: Sales | AJ1: Sales | AK1: Sales | AL1: Sales | AM1: Sales | AN1: Sales | AO1: Sales | AP1: Sales | AQ1: Sales | AR1: Sales | AS1: Sales | AT1: Sales | AU1: Sales | AV1: Sales | AW1: Sales | AY1: Total | AZ1: Total | BA1: Total | BB1: Total | BC1: Total | BD1: Total | BE1: Total | BF1: Total | BG1: Total | BH1: Total | BI1: Total | BJ1: Total | BK1: Total | BL1: Total | BM1: Total | BO1: Forecast Date
A2: State | B2: Abbr | C2: FY 2013 | D2: FY 2014 | E2: FY 2015 | F2: FY 2016 | G2: FY 2017 | H2: FY 2018 | I2: FY 2019 | J2: FY 2020 | K2: FY 2021 | L2: FY 2022 | M2: FY 2023 | N2: FY 2024 | O2: FY 2025 | P2: FY 2026 | Q2: FY 2027 | S2: FY 2013 | T2: FY 2014 | U2: FY 2015 | V2: FY 2016 | W2: FY 2017 | X2: FY 2018 | Y2: FY 2019 | Z2: FY 2020 | AA2: FY 2021 | AB2: FY 2022 | AC2: FY 2023 | AD2: FY 2024 | AE2: FY 2025 | AF2: FY 2026 | AG2: FY 2027 | AI2: FY 2013 | AJ2: FY 2014 | AK2: FY 2015 | AL2: FY 2016 | AM2: FY 2017 | AN2: FY 2018 | AO2: FY 2019 | AP2: FY 2020 | AQ2: FY 2021 | AR2: FY 2022 | AS2: FY 2023 | AT2: FY 2024 | AU2: FY 2025 | AV2: FY 2026 | AW2: FY 2027 | AY2: FY 2013 | AZ2: FY 2014 | BA2: FY 2015 | BB2: FY 2016 | BC2: FY 2017 | BD2: FY 2018 | BE2: FY 2019 | BF2: FY 2020 | BG2: FY 2021 | BH2: FY 2022 | BI2: FY 2023 | BJ2: FY 2024 | BK2: FY 2025 | BL2: FY 2026 | BM2: FY 2027 | BO2: FY 2013 | BP2: FY 2014 | BQ2: FY 2015 | BR2: FY 2016 | BS2: FY 2017 | BT2: FY 2018 | BU2: FY 2019 | BV2: FY 2020 | BW2: FY 2021 | BX2: FY 2022 | BY2: FY 2023 | BZ2: FY 2024 | CA2: FY 2025 | CB2: FY 2026 | CC2: FY 2027 | CD2: Budget cycle
A3: Alabama | B3: AL | C3: 3281.81 | D3: 3473 | E3: 3681 | F3: 3746 | G3: 3843 | H3: 3976 | I3: 4158 | J3: 4437.1114 | K3: 4877.3017 | L3: 4777.4046 | M3: 5129.8835 | N3: 7500 | O3: 6750 | P3: 7569.7972 | S3: 44.36 | T3: 52.5 | U3: 115 | V3: 58 | W3: 75.5 | X3: 96.5 | Y3: 96 | Z3: 96 | AA3: 96 | AB3: 96 | AC3: 103 | AD3: 104.8 | AE3: 103.96488 | AF3: 108.9046 | AI3: 2089.4494 | AJ3: 2066.3 | AK3: 2094.4 | AL3: 2378.8 | AM3: 2271.6 | AN3: 2392 | AO3: 2407 | AP3: 2610.4492 | AQ3: 2749.7442 | AR3: 2839.1024 | AS3: 3182.9369 | AT3: 3474.2661 | AU3: 3465.0259 | AV3: 3585.7088 | AY3: =5719.45+1371.744 -> 7091.194 | AZ3: =(1663043840+5824593296)/1000000 -> 7487.6371 | BA3: 7841.7174 | BB3: 8298.4463 | BC3: 8041.5834 | BD3: 8364.6494 | BE3: 8599.0709 | BF3: 9215.8394 | BG3: 9927.265 | BH3: 9980.8064 | BI3: 10859.205 | BJ3: =(2823184399+10904087198)/1000000 -> 13727.272 | BK3: 13182.237 | BL3: 14404.785 | BO3: 40909 | BP3: 41275 | BQ3: 41640 | BR3: 42005 | BS3: 42370 | BT3: 42736 | BU3: 43101 | BV3: 43466 | BW3: 43831 | BX3: 44197 | BY3: 44562 | BZ3: 44927 | CA3: 45292 | CB3: 45658 | CD3: Annual
A4: Alaska | B4: AK | C4: N/A | D4: N/A | E4: N/A | F4: N/A | G4: N/A | H4: N/A | I4: N/A | J4: N/A | K4: N/A | L4: N/A | M4: N/A | N4: N/A | O4: N/A | P4: N/A | S4: 167.6 | T4: 100.5 | U4: 127.1 | V4: 125.9 | W4: 99.3 | X4: 154.9 | Y4: 145 | Z4: 135 | AA4: 75 | AB4: 10 | AC4: 125 | AD4: 125 | AE4: 160 | AF4: 235 | AI4: N/A | AJ4: N/A | AK4: N/A | AL4: N/A | AM4: N/A | AN4: N/A | AO4: N/A | AP4: N/A | AQ4: N/A | AR4: N/A | AS4: N/A | AT4: N/A | AU4: N/A | AV4: N/A | AY4: =16492.4-2862.2 -> 13630.2 | AZ4: =14622.9-2965 -> 11657.9 | BA4: =12567.5-3116.4 -> 9451.1 | BB4: =9957.6-3401.8 -> 6555.8 | BC4: =8219-3401.8 -> 4817.2 | BD4: =10188.7-3466.7 -> 6722 | BE4: =11172.3-3678.4 -> 7493.9 | BF4: =10970.6-3257.9 -> 7712.7 | BG4: =10569.9-4314 -> 6255.9 | BH4: =11040.8-4070.3 -> 6970.5 | BI4: =16435.4-5183.8 -> 11251.6 | BJ4: =14904-5433.7 -> 9470.3 | BK4: =16515.8-6472.5 -> 10043.3 | BL4: =15900.8-6080.7 -> 9820.1 | BO4: 40969 | BP4: 41334 | BQ4: 41699 | BR4: 42064 | BS4: 42430 | BT4: 42795 | BU4: 43160 | BV4: 43525 | BW4: 43891 | BX4: 44270 | BY4: 44621 | BZ4: 45006 | CA4: 45352 | CB4: 45717 | CD4: Annual
A5: Arizona | B5: AZ | C5: 3280 | D5: 3531.2579 | E5: 3868.06 | F5: 3741.4672 | G5: 4147.14 | H5: 4282.79 | I5: 4507.9 | J5: 5008.63 | K5: 5311.765 | L5: 5555.8199 | M5: 5590 | N5: 5662.2761 | O5: 5185.639 | P5: 5481.7877 | S5: 630 | T5: 714.91 | U5: 573.868 | V5: 465.0621 | W5: 563.325 | X5: 389.3901 | Y5: 299.06 | Z5: 427 | AA5: 533.98 | AB5: 533.5182 | AC5: 815.5695 | AD5: 1305.7 | AE5: 1795.146 | AF5: 1933.857 | AI5: 3900 | AJ5: 4029.02 | AK5: 4290.6 | AL5: 4343.8893 | AM5: 4502.5448 | AN5: 4676.87 | AO5: 4838.4 | AP5: 5289.43 | AQ5: 5669.9034 | AR5: 6091.9181 | AS5: 6918.59 | AT5: 7943.3568 | AU5: 8280.3115 | AV5: 8484.4251 | AY5: 8262.8 | AZ5: 8742.6405 | BA5: 9246.5752 | BB5: 9116.9486 | BC5: 9763.3108 | BD5: 9945.7321 | BE5: 10261.598 | BF5: 11330.919 | BG5: 12178.302 | BH5: 12829.764 | BI5: 14054.549 | BJ5: 15805.054 | BK5: 16126.318 | BL5: 16948.879 | BO5: 40909 | BP5: 41275 | BQ5: 41640 | BR5: 42005 | BS5: 42370 | BT5: 42736 | BU5: 43101 | BV5: 43466 | BW5: 43831 | BX5: 44197 | BY5: 44562 | BZ5: 44927 | CA5: 45292 | CB5: 45658 | CD5: Annual
A6: Arkansas | B6: AR | C6: =2888.2-507.2 -> 2381 | D6: =3101.2-541.4 -> 2559.8 | E6: =3173.4-553.5 -> 2619.9 | F6: =3092-431.3 -> 2660.7 | G6: =3220.5-479.4 -> 2741.1 | H6: =3319-522.1 -> 2796.9 | I6: =3428.8-504.6 -> 2924.2 | J6: =3578.8-581.1 -> 2997.7 | K6: =3359.1-455 -> 2904.1 | L6: =3189.7-370 -> 2819.7 | M6: =3907.1-486.4 -> 3420.7 | N6: =3586.8-558.5 -> 3028.3 | O6: =3753.6-629.1 -> 3124.5 | P6: 2947.4 | S6: =406.9-45.4 -> 361.5 | T6: =429-61.6 -> 367.4 | U6: =450.2-60.5 -> 389.7 | V6: =476.2-48 -> 428.2 | W6: =462.3-54 -> 408.3 | X6: =474.9-64.8 -> 410.1 | Y6: =482.3-70.4 -> 411.9 | Z6: =404.6-52.4 -> 352.2 | AA6: =449.4-63.1 -> 386.3 | AB6: =478.7-68.8 -> 409.9 | AC6: =642.2-71.9 -> 570.3 | AD6: =519.2-72.7 -> 446.5 | AE6: =718.3-74.3 -> 644 | AF6: 434.8 | AI6: 2174.1 | AJ6: 2207.7 | AK6: 2208 | AL6: 2273 | AM6: 2396 | AN6: 2444.9 | AO6: 2487.7 | AP6: 2572.4 | AQ6: 2569.4 | AR6: 2815.3 | AS6: 3166.8 | AT6: 3405.1 | AU6: 3547.9 | AV6: 3575.6 | AY6: 4727.5 | AZ6: 4957.6 | BA6: 5040.7 | BB6: 5186.2 | BC6: 5333.1 | BD6: 5453.2 | BE6: 5690.2 | BF6: 5737.1 | BG6: 5687.3 | BH6: 5866.2 | BI6: 6938.3 | BJ6: 6625.4 | BK6: 7075.2 | BL6: 6679.1 | BO6: 41030 | BP6: 41395 | BQ6: 41760 | BR6: 42125 | BS6: 42491 | BT6: 42856 | BU6: 43221 | BV6: 43586 | BW6: 43923 | BX6: 44335 | BY6: 44682 | BZ6: 45047 | CA6: 45413 | CB6: 45778 | CD6: Biennial (odd)
A7: California | B7: CA | C7: 60268 | D7: 60827 | E7: 70238 | F7: 77700 | G7: 83393 | H7: 88961 | I7: 95009 | J7: 102333 | K7: 76619.63 | L7: 123298 | M7: 137454 | N7: 118136 | O7: 116176 | P7: 126107 | S7: 8488 | T7: 8508 | U7: 8910 | V7: 10342 | W7: 10993 | X7: 10894 | Y7: 12248 | Z7: 13233 | AA7: 12367.49 | AB7: 18106 | AC7: 38464 | AD7: 42081 | AE7: 36778 | AF7: 35293 | AI7: 20605 | AJ7: 22983 | AK7: 23823 | AL7: 25240 | AM7: 25727 | AN7: 24470 | AO7: 26674 | AP7: 27241 | AQ7: 20570.8 | AR7: 28986 | AS7: 33991 | AT7: 33366 | AU7: 34043 | AV7: 34866 | AY7: 95689 | AZ7: 97235 | BA7: 106951 | BB7: 118031 | BC7: 124160 | BD7: 128316 | BE7: 138317 | BF7: 147833 | BG7: 119244 | BH7: 181745 | BI7: 222966 | BJ7: 206640 | BK7: 199128 | BL7: 206736 | BO7: 41030 | BP7: 41395 | BQ7: 41760 | BR7: 42125 | BS7: 42491 | BT7: 42856 | BU7: 43221 | BV7: 43586 | BW7: 43952 | BX7: 44317 | BY7: 44682 | BZ7: 45047 | CA7: 45413 | CB7: 45778 | CD7: Annual
A8: Colorado | B8: CO | C8: 5131.1 | D8: 5687.3 | E8: 6002.5 | F8: 6493.3 | G8: 6803.3 | H8: 7275.7 | I8: 7978.4 | J8: 8617.1 | K8: 6957.8 | L8: 9877.5 | M8: 11620.5 | N8: 11139 | O8: 10138.9 | P8: 10744.8 | S8: 448.5 | T8: 760.9 | U8: 804.2 | V8: 656.8 | W8: 606.8 | X8: 632.8 | Y8: 778.8 | Z8: 857.1 | AA8: 443.6 | AB8: 982.6 | AC8: 1192.5 | AD8: 1930.8 | AE8: 2226.1 | AF8: 2124.8 | AI8: =2083.2+208.8 -> 2292 | AJ8: =2320.6+244.1 -> 2564.7 | AK8: =2497+263.5 -> 2760.5 | AL8: =2807.8+288.6 -> 3096.4 | AM8: =2792.7+270.7 -> 3063.4 | AN8: =3022.3+277.5 -> 3299.8 | AO8: =3084.7+338.5 -> 3423.2 | AP8: =3223.8+314.9 -> 3538.7 | AQ8: =3089.6+202 -> 3291.6 | AR8: =3492.8+216.1 -> 3708.9 | AS8: =4221+258.3 -> 4479.3 | AT8: =4487.6+263.7 -> 4751.3 | AU8: =4508.1+240.7 -> 4748.8 | AV8: =4585.3+232.9 -> 4818.2 | AY8: 7847.3 | AZ8: 8897.6 | BA8: 9448.2 | BB8: 10089.6 | BC8: 10360.2 | BD8: 11087.5 | BE8: 12192.5 | BF8: 13029.9 | BG8: 10832.8 | BH8: 14868.4 | BI8: 17427.1 | BJ8: 17763.7 | BK8: 17010 | BL8: 17573.1 | BO8: 41061 | BP8: 41426 | BQ8: 41791 | BR8: 42156 | BS8: 42522 | BT8: 42887 | BU8: 43252 | BV8: 43617 | BW8: 43983 | BX8: 44365 | BY8: 44713 | BZ8: 45078 | CA8: 45444 | CB8: 45809 | CD8: Annual
A9: Connecticut | B9: CT | C9: 8551.3 | D9: 8796.9 | E9: 9267.5 | F9: 9665.1 | G9: 9522 | H9: 9096.7 | I9: 9707.6 | J9: =6808.6+2767.5 -> 9576.1 | K9: =6408.3+1822.3 -> 8230.6 | L9: =7321.9+2689.1 -> 10011 | M9: =8227.3+3522.7 -> 11750 | N9: =8547.5+2666.4 -> 11213.9 | O9: =8759.1+3123.5 -> 11882.6 | P9: =9287.2+3343.7 -> 12630.9 | S9: 792 | T9: 668.6 | U9: 704.3 | V9: 644.1 | W9: 839.3 | X9: 872.1 | Y9: 920.2 | Z9: =1005.4+850 -> 1855.4 | AA9: =808.6+850.7 -> 1659.3 | AB9: =1021.2+1485.8 -> 2507 | AC9: =1303.6+1957.3 -> 3260.9 | AD9: =1443.8+1815.6 -> 3259.4 | AE9: =1560.7+1969.3 -> 3530 | AF9: =1470.1+2115.3 -> 3585.4 | AI9: 4039.2 | AJ9: 3953 | AK9: 4173.4 | AL9: 4374 | AM9: 4314 | AN9: 4169.3 | AO9: 4512 | AP9: =4299.1+468.9 -> 4768 | AQ9: =3985.7+395.8 -> 4381.5 | AR9: =4234.9+665 -> 4899.9 | AS9: =4787.3+794.4 -> 5581.7 | AT9: =5301.7+860.2 -> 6161.9 | AU9: =5103.5+879.2 -> 5982.7 | AV9: =5103.5+879.2 -> 5982.7 | AY9: =19067.8+1303.8-3654.8 -> 16716.8 | AZ9: =19396.5+1333.6-4248.3 -> 16481.8 | BA9: =17403.6+1330.5-1292.1 -> 17442 | BB9: =17360.3+1500.5-1305.6 -> 17555.2 | BC9: =17750.4+1513.6-1262.7 -> 18001.3 | BD9: =17085.1+1593.5-1282.5 -> 17396.1 | BE9: =19056.6+1591.5-2167.1 -> 18481 | BF9: =18400.5+1808-1401.8 -> 18806.7 | BG9: =18088.4+1676.9-1922.8 -> 17842.5 | BH9: =19757.6+1884.7-1755.1 -> 19887.2 | BI9: =23384.2+2242.7-1962.7 -> 23664.2 | BJ9: =22790.8+2401-1827.5 -> 23364.3 | BK9: =23129.5+2410.5-1893.7 -> 23646.3 | BL9: =23782.9-1825.4+2292.1 -> 24249.6 | BO9: 41000 | BP9: 41365 | BQ9: 41730 | BR9: 42095 | BS9: 42461 | BT9: 42826 | BU9: 43191 | BV9: 43556 | BW9: 43922 | BX9: 44316 | BY9: 44652 | BZ9: 45031 | CA9: 45383 | CB9: 45748 | CD9: Biennial (odd)
A10: Delaware | B10: DE | C10: 1086.2 | D10: 1172.5 | E10: 1226.3 | F10: 1297 | G10: 1334.3 | H10: 1373.4 | I10: 1486.3 | J10: 1590.2 | K10: 1562.1 | L10: 1788.2 | M10: 2061.6 | N10: 2089.1 | O10: 2313.2 | P10: 2531.2 | S10: 176.1 | T10: 203.4 | U10: 212.4 | V10: 154 | W10: 157.4 | X10: 108.4 | Y10: 92.8 | Z10: 112.2 | AA10: 76.8 | AB10: 144.9 | AC10: 199.3 | AD10: 282.7 | AE10: 270 | AF10: 330.3 | AI10: N/A | AJ10: N/A | AK10: N/A | AL10: N/A | AM10: N/A | AN10: N/A | AO10: N/A | AP10: N/A | AQ10: N/A | AR10: N/A | AS10: N/A | AT10: N/A | AU10: N/A | AV10: N/A | AY10: 3697.1 | AZ10: 3740.6 | BA10: 3890 | BB10: 3867.8 | BC10: 4025.9 | BD10: 3997.4 | BE10: 4383.4 | BF10: 4617.3 | BG10: 4535.4 | BH10: 5124.9 | BI10: 5814.5 | BJ10: 6039.4 | BK10: 6418.3 | BL10: 6777.7 | BO10: 41061 | BP10: 41426 | BQ10: 41791 | BR10: 42156 | BS10: 42522 | BT10: 42887 | BU10: 43252 | BV10: 43617 | BW10: 43983 | BX10: 44364 | BY10: 44713 | BZ10: 45078 | CA10: 45413 | CB10: 45778 | CD10: Annual
A11: Florida | B11: FL | C11: N/A | D11: N/A | E11: N/A | F11: N/A | G11: N/A | H11: N/A | I11: N/A | J11: N/A | K11: N/A | L11: N/A | M11: N/A | N11: N/A | O11: N/A | P11: N/A | S11: 2159.1 | T11: 2283.6 | U11: 2254.8 | V11: 2208.3 | W11: 2147.4 | X11: 2339.5 | Y11: 2376.2 | Z11: 2694.6 | AA11: 2843 | AB11: 2876.3 | AC11: 3822.2 | AD11: 5482.1 | AE11: 5774.4 | AF11: 5960.9 | AI11: 18101.4 | AJ11: 19158.7 | AK11: 20463.6 | AL11: 21773 | AM11: 23217.3 | AN11: 24091.4 | AO11: 25070.2 | AP11: 26058.5 | AQ11: 27022.9 | AR11: 27134.6 | AS11: 29797.4 | AT11: 34577 | AU11: 36244.5 | AV11: 37738.9 | AY11: 24506.9 | AZ11: 26006.4 | BA11: 27140.2 | BB11: 28126.8 | BC11: 29464.7 | BD11: 30793.8 | BE11: 32256.9 | BF11: 33506.5 | BG11: 34449.3 | BH11: 34864.9 | BI11: 39041.1 | BJ11: 45300.6 | BK11: 48009.7 | BL11: 50200.6 | BO11: 40909 | BP11: 41334 | BQ11: 41710 | BR11: 42073 | BS11: 42388 | BT11: 42811 | BU11: 43140 | BV11: 43525 | BW11: 43831 | BX11: 44292 | BY11: 44562 | BZ11: 44998 | CA11: 45292 | CB11: 45717 | CD11: Annual
A12: Georgia | B12: GA | C12: 8604.798 | D12: 8895.846 | E12: 9536.657 | F12: 9839.041 | G12: 10715.557 | H12: 11454.618 | I12: 12025.913 | J12: 12754.221 | K12: 12653.107 | L12: 12738.708 | M12: 14101.898 | N12: 14706.897 | O12: 15808.929 | P12: 15693.797 | S12: 735.41372 | T12: 775.314 | U12: 846.667 | V12: 995.534 | W12: 1023.3514 | X12: 1042.83 | Y12: 1067.9791 | Z12: 1259.624 | AA12: 1536.1181 | AB12: 880.77726 | AC12: 1396.9884 | AD12: 1401.7095 | AE12: 3062.908 | AF12: 3254.3608 | AI12: 5560.6527 | AJ12: 5094.297 | AK12: 5258.817 | AL12: 5593.609 | AM12: 5658.9 | AN12: 5848.547 | AO12: 6092.7808 | AP12: 6525.181 | AQ12: 6722.1413 | AR12: 6649.0841 | AS12: 7402.3142 | AT12: 8365.6576 | AU12: 8369.25 | AV12: 9434.9741 | AY12: 18156.467 | AZ12: 18798.349 | BA12: 19726.831 | BB12: 20647.628 | BC12: 22523.214 | BD12: 23713.413 | BE12: 24679.053 | BF12: 26143.818 | BG12: 26631.766 | BH12: 25775.587 | BI12: 28634.939 | BJ12: 30784.469 | BK12: 34425.232 | BL12: 35897.957 | BO12: 40878 | BP12: 41244 | BQ12: 41609 | BR12: 41974 | BS12: 42339 | BT12: 42705 | BU12: 43070 | BV12: 43435 | BW12: 43800 | BX12: 44166 | BY12: 44531 | BZ12: 44896 | CA12: 45261 | CB12: 45627 | CD12: Annual
A13: Hawaii | B13: HI | C13: 1528.684 | D13: 1789.785 | E13: 1912.378 | F13: 1915.067 | G13: 2130.32 | H13: 2196.838 | I13: 2537.392 | J13: 2659.251 | K13: 2058.28 | L13: 2497.695 | M13: 3861.257 | N13: 3504.931 | O13: 2910.104 | P13: 3024.052 | S13: 58.943 | T13: 82.275 | U13: 69.034 | V13: 99.534 | W13: 80.713 | X13: 83.305 | Y13: 105.421 | Z13: 127.677 | AA13: 111.188 | AB13: 148.986 | AC13: 460.66 | AD13: 162.178 | AE13: 368.917 | AF13: 413.072 | AI13: 2850.462 | AJ13: 3142.442 | AK13: 3057.202 | AL13: 3180.489 | AM13: 3372.902 | AN13: 3459.629 | AO13: 3562.313 | AP13: 3642.53 | AQ13: 3044.802 | AR13: 3747.609 | AS13: 4328.94 | AT13: 4363.137 | AU13: 5256.148 | AV13: 4767.259 | AY13: 5105.816 | AZ13: 5736.273 | BA13: 5744.533 | BB13: 5928.91 | BC13: 6389.234 | BD13: 6603.184 | BE13: 7115.037 | BF13: 7400.068 | BG13: 5844.841 | BH13: 7240.434 | BI13: 9744.351 | BJ13: 9635.87 | BK13: 9960.103 | BL13: 9639.693 | BO13: 41030 | BP13: 41395 | BQ13: 41760 | BR13: 42125 | BS13: 42491 | BT13: 42856 | BU13: 43221 | BV13: 43586 | BW13: 43952 | BX13: 44317 | BY13: 44682 | BZ13: 45061 | CA13: 45413 | CB13: 45778 | CD13: Biennial (odd)
A14: Idaho | B14: ID | C14: 1295 | D14: 1313.41 | E14: 1403.03 | F14: 1488.58 | G14: 1606.15 | H14: 1666.778 | I14: 1853.19 | J14: 1954.259 | K14: 1875.391 | L14: 2089.445 | M14: 2553.109 | N14: 2162.795 | O14: 2601.192 | P14: 2689.056 | S14: 182.84 | T14: 194.06 | U14: 206.51 | V14: 212.48 | W14: 222.06 | X14: 215.894 | Y14: 234.96 | Z14: 256.323 | AA14: 293.003 | AB14: 260.889 | AC14: 324.08 | AD14: 872.563 | AE14: 751.932 | AF14: 979.247 | AI14: 1082.72 | AJ14: 1151.57 | AK14: 1233.41 | AL14: 1269.99 | AM14: 1345.13 | AN14: 1447.141 | AO14: 1546.05 | AP14: 1667.036 | AQ14: 1789.171 | AR14: 1866.354 | AS14: 2272.077 | AT14: 2077.893 | AU14: 1942.999 | AV14: 1940.004 | AY14: 2700.26 | AZ14: 2799.11 | BA14: 2987.77 | BB14: 3127.64 | BC14: 3340.37 | BD14: 3507.437 | BE14: 3823.13 | BF14: 4057.43 | BG14: 4148.572 | BH14: 4403.998 | BI14: 5464.071 | BJ14: 5547.111 | BK14: 5698.242 | BL14: 6077.619 | BO14: 40909 | BP14: 41275 | BQ14: 41640 | BR14: 42005 | BS14: 42370 | BT14: 42736 | BU14: 43101 | BV14: 43466 | BW14: 43831 | BX14: 44197 | BY14: 44562 | BZ14: 44927 | CA14: 45292 | CB14: 45658 | CD14: Annual
A15: Illinois | B15: IL | C15: =16879-1646 -> 15233 | D15: =17713-1727 -> 15986 | E15: =16717-1672 -> 15045 | F15: =14766-1477 -> 13289 | G15: =15354-1535 -> 13819 | H15: =15688-1569 -> 14119 | I15: =21071-2044 -> 19027 | J15: =22128-2157 -> 19971 | K15: =23643-2187 -> 21456 | L15: =23584-2181 -> 21403 | M15: =26687-2469 -> 24218 | N15: =29235-2704 -> 26531 | O15: =31254-2860 -> 28394 | P15: =33241-3042 -> 30199 | S15: =3070-430 -> 2640 | T15: =3391-475 -> 2916 | U15: =3267-457 -> 2810 | V15: =2700-446 -> 2254 | W15: =2648-410 -> 2238 | X15: =1900-333 -> 1567 | Y15: =2618-406 -> 2212 | Z15: =2890-426 -> 2464 | AA15: =3201-448 -> 2753 | AB15: =3240-486 -> 2754 | AC15: =5471-793 -> 4678 | AD15: =6832-956 -> 5876 | AE15: =6040-846 -> 5194 | AF15: =5969-836 -> 5133 | AI15: 7340 | AJ15: 7348 | AK15: 7842 | AL15: 8280 | AM15: 8203 | AN15: 8380 | AO15: 8491 | AP15: 9022 | AQ15: 9503 | AR15: 9486 | AS15: 10919 | AT15: 11897 | AU15: 11987 | AV15: 12039 | AY15: 32131 | AZ15: 33283 | BA15: 32747 | BB15: 30540 | BC15: 31012 | BD15: 30880 | BE15: 37593 | BF15: 39162 | BG15: 41634 | BH15: 41046 | BI15: 48245 | BJ15: 53397 | BK15: 55482 | BL15: 57718 | BO15: 40969 | BP15: 41306 | BQ15: 41699 | BR15: 42064 | BS15: 42430 | BT15: 42795 | BU15: 43160 | BV15: 43525 | BW15: 43891 | BX15: 44256 | BY15: 44621 | BZ15: 44986 | CA15: 45383 | CB15: 45717 | CD15: Annual
A16: Indiana | B16: IN | C16: 5084 | D16: 5162.7 | E16: 5279.6 | F16: 5121.8 | G16: 5372.1 | H16: 5661 | I16: 5922.9 | J16: 6174.1 | K16: 6395.5 | L16: 6710.6 | M16: 7578.9 | N16: 7907.4 | O16: 8283.6 | P16: 8861.5 | S16: 784.9 | T16: 900.3 | U16: 920.5 | V16: 984.7 | W16: 966.3 | X16: 949.2 | Y16: 870.7 | Z16: 850.9 | AA16: 872.4 | AB16: 883.8 | AC16: 1281.7 | AD16: 1358.4 | AE16: 1202.5 | AF16: 1304.2 | AI16: 6864.6 | AJ16: 7088.4 | AK16: 7242.9 | AL16: 7504.7 | AM16: 7665.3 | AN16: 7630.2 | AO16: 7837.9 | AP16: 8075.8 | AQ16: 8459.8 | AR16: 9074.4 | AS16: 9940.3 | AT16: 10815.2 | AU16: 10916.9 | AV16: 11092.6 | AY16: 14432 | AZ16: 14728.2 | BA16: 14858.7 | BB16: 14971.1 | BC16: 15343.3 | BD16: 15588.2 | BE16: 15961.6 | BF16: 16552 | BG16: 17259.9 | BH16: 18076.9 | BI16: 20279.7 | BJ16: 21854.1 | BK16: 22313.3 | BL16: 23192.4 | BO16: 40878 | BP16: 41365 | BQ16: 41609 | BR16: 42095 | BS16: 42339 | BT16: 42826 | BU16: 43070 | BV16: 43556 | BW16: 43800 | BX16: 44287 | BY16: 44531 | BZ16: 45017 | CA16: 45261 | CB16: 45627 | CD16: Biennial (odd)
A17: Iowa | B17: IA | C17: 3786.7 | D17: 4133.5 | E17: 4291.4 | F17: 4493.5 | G17: 4742.4 | H17: 4743.4 | I17: 4985.4 | J17: 4830.8 | K17: 5050.6 | L17: 5129.2 | M17: 5392.1 | N17: 5136.2 | O17: 5523.4 | P17: 4753.7 | S17: 511.3 | T17: 556.6 | U17: 610 | V17: 560.3 | W17: 531.8 | X17: 525.7 | Y17: 649 | Z17: 653 | AA17: 692.2 | AB17: 742.9 | AC17: 828.7 | AD17: 893.3 | AE17: 945.4 | AF17: 815.8 | AI17: 2538.3 | AJ17: 2676.1 | AK17: 2753 | AL17: 2891 | AM17: 2849.8 | AN17: 2980.8 | AO17: 3039.3 | AP17: 3316.1 | AQ17: 3342.1 | AR17: 3398.8 | AS17: 4002.6 | AT17: 3924.7 | AU17: 4361.3 | AV17: 4430.4 | AY17: 6280.6 | AZ17: 6870.6 | BA17: 6983.2 | BB17: 7175.5 | BC17: 7357.4 | BD17: 7364.5 | BE17: 7733.8 | BF17: 7848.4 | BG17: 8236.7 | BH17: 8385.6 | BI17: 9156.3 | BJ17: 9650.3 | BK17: 9697.8 | BL17: 8507.9 | BO17: 40969 | BP17: 41334 | BQ17: 41699 | BR17: 42064 | BS17: 42430 | BT17: 42795 | BU17: 43160 | BV17: 43525 | BW17: 43891 | BX17: 44274 | BY17: 44621 | BZ17: 44995 | CA17: 45352 | CB17: 45717 | CD17: Annual
A18: Kansas | B18: KS | C18: 2870.8 | D18: 2524.685 | E18: 2519.288 | F18: 2461.8 | G18: 2377 | H18: 2927 | I18: 3334.17 | J18: 3750 | K18: 3770 | L18: 3688.63 | M18: 4661.6 | N18: 4798.8 | O18: 4186.2 | P18: 4670.38 | S18: =270+26 -> 296 | T18: =370+31 -> 401 | U18: =425+37.45 -> 462.45 | V18: 489 | W18: 436 | X18: 316 | Y18: 394 | Z18: =450+42 -> 492 | AA18: =370+48 -> 418 | AB18: =282.52+48.7 -> 331.22 | AC18: =650+46 -> 696 | AD18: =1295.255+50 -> 1345.255 | AE18: =1561.5+45.2 -> 1606.7 | AF18: =1325+45 -> 1370 | AI18: =2225+350 -> 2575 | AJ18: =2087.5+320.7 -> 2408.2 | AK18: =2168.188+358.984 -> 2527.172 | AL18: 2786.2 | AM18: 2754.912 | AN18: 2667.317 | AO18: 2766.427 | AP18: =2344.993+440 -> 2784.993 | AQ18: =2320+450 -> 2770 | AR18: =2466.1+665.5 -> 3131.6 | AS18: 3413.9 | AT18: 3619.685 | AU18: 3417.9 | AV18: 3435 | AY18: 6174.32 | AZ18: 5885.526 | BA18: 5974.575 | BB18: 6325.033 | BC18: 6303.872 | BD18: 6705.497 | BE18: 7003.346 | BF18: 7431.693 | BG18: 7230.5 | BH18: 7561.94 | BI18: 8907 | BJ18: 10351.24 | BK18: 9791.6 | BL18: 10060.88 | BO18: 41061 | BP18: 41426 | BQ18: 41791 | BR18: 42186 | BS18: 42522 | BT18: 42887 | BU18: 43221 | BV18: 43586 | BW18: 43983 | BX18: 44348 | BY18: 44713 | BZ18: 45070 | CA18: 45444 | CB18: 45809 | CD18: Annual
A19: Kentucky | B19: KY | C19: 3563.5 | D19: 3689.4 | E19: 3977.3 | F19: 4135.8 | G19: 4411.1 | H19: 4588.6 | I19: 4649.5 | J19: 4793.2 | K19: 4813 | L19: 5004.1 | M19: 5342.26 | N19: 5249.29 | O19: 5548.1 | P19: 5742.1 | S19: 359.50547 | T19: 365.30454 | U19: 697.1 | V19: 687.5 | W19: =579.4+223.7 -> 803.1 | X19: =553.1+221.6 -> 774.7 | Y19: =600.6+200.2 -> 800.8 | Z19: =632.3+210.8 -> 843.1 | AA19: 547.5 | AB19: 469.1 | AC19: 909.75 | AD19: 963.75 | AE19: 1283.3 | AF19: 1313.4 | AI19: 3075.2 | AJ19: 3172.7 | AK19: 3149.6 | AL19: 3216.8 | AM19: 3539.8 | AN19: 3638.4 | AO19: 3699.4 | AP19: 3791.7 | AQ19: 4232.8 | AR19: 4336 | AS19: 5283.22 | AT19: 5625.42 | AU19: 6082.1 | AV19: 6315.9 | AY19: 9220.6 | AZ19: 9500.3 | BA19: 9794.3 | BB19: 10046.6 | BC19: 10617.2 | BD19: 10875.5 | BE19: 11005.9 | BF19: 11290 | BG19: 11704 | BH19: 11849.8 | BI19: 13758.988 | BJ19: 14154.399 | BK19: 15549.5 | BL19: 15654.9 | BO19: 40878 | BP19: 40878 | BQ19: 41609 | BR19: 41609 | BS19: 42339 | BT19: 42339 | BU19: 43070 | BV19: 43070 | BW19: 43800 | BX19: 43800 | BY19: 44531 | BZ19: 44531 | CA19: 45261 | CB19: 45261 | CD19: Biennial (even)
A20: Louisiana | B20: LA | C20: 2627.1 | D20: 2786.1 | E20: 2932.4 | F20: 2976.6 | G20: 3088.3 | H20: 3016.5 | I20: 3379.6 | J20: 3512.9 | K20: 3646.3 | L20: 3793.1 | M20: 4325.1 | N20: 4486.1 | O20: 4631.7 | P20: 3704.1 | S20: 155.9 | T20: 340 | U20: 350.8 | V20: 385 | W20: 510.4 | X20: 338.5 | Y20: 300 | Z20: 400 | AA20: 422.7 | AB20: 500 | AC20: 650 | AD20: 812.7 | AE20: 900 | AF20: 1152.6 | AI20: 2767.5 | AJ20: 2656.8 | AK20: 2695.7 | AL20: 2827.9 | AM20: 3774.5 | AN20: 3800.8 | AO20: 3108.4 | AP20: 3470.5 | AQ20: 3197.2 | AR20: 3404.5 | AS20: 4002.7 | AT20: 4432.8 | AU20: 4429.9 | AV20: 5405.1 | AY20: 9957.8 | AZ20: 10213.8 | BA20: 10640.4 | BB20: 10545.8 | BC20: 12032.1 | BD20: 11981 | BE20: 11467.5 | BF20: 12354.4 | BG20: 11518.2 | BH20: 12296.3 | BI20: 13837.2 | BJ20: 15277.4 | BK20: 15778.8 | BL20: 15841.5 | BO20: 41030 | BP20: 41395 | BQ20: 41760 | BR20: 42125 | BS20: 42522 | BT20: 42856 | BU20: 43191 | BV20: 43556 | BW20: 43952 | BX20: 44317 | BY20: 44682 | BZ20: 45064 | CA20: 45413 | CB20: 45778 | CD20: Annual
A21: Maine | B21: ME | C21: 1436.3997 | D21: 1392.994 | E21: 1447.229 | F21: 1548.7766 | G21: 1480.1952 | H21: 1684.3423 | I21: 1663.0552 | J21: 1769.7065 | K21: 1851.6813 | L21: 1888.055 | M21: 2184.9402 | N21: 2395.3567 | O21: 2454.4707 | P21: 2666.3213 | S21: 216.25421 | T21: 185.55858 | U21: 177.65123 | V21: 150.0846 | W21: 156.10047 | X21: 165.72424 | Y21: 183.5592 | Z21: 204.6 | AA21: 211.99 | AB21: 217.23374 | AC21: 335.8482 | AD21: 355.903 | AE21: 428 | AF21: 376 | AI21: 994.36419 | AJ21: 1022.3382 | AK21: 1189.5923 | AL21: 1127.459 | AM21: 1321.3537 | AN21: 1400.1483 | AO21: 1466.0326 | AP21: 1570.8098 | AQ21: 1695.0717 | AR21: 1806.2924 | AS21: 2114.5213 | AT21: 2190.0292 | AU21: 2286.0125 | AV21: 2336.1192 | AY21: 3022.2261 | AZ21: 2880.5192 | BA21: 3278.3014 | BB21: 3142.5189 | BC21: 3376.4597 | BD21: 3550.7131 | BE21: 3689.166 | BF21: 3816.1755 | BG21: 4073.7205 | BH21: 4248.4249 | BI21: 4881.3003 | BJ21: 5206.2143 | BK21: 5305.5644 | BL21: 5539.2852 | BO21: 40969 | BP21: 41395 | BQ21: 41699 | BR21: 42125 | BS21: 42430 | BT21: 42856 | BU21: 43160 | BV21: 43586 | BW21: 43891 | BX21: 44317 | BY21: 44621 | BZ21: 45047 | CA21: 45352 | CB21: 45778 | CD21: Biennial (odd)
A22: Maryland | B22: MD | C22: 7304.285 | D22: 7961.33 | E22: 8470.31 | F22: 8628.707 | G22: 9273.211 | H22: 9405.788 | I22: 10156.89 | J22: 10395.608 | K22: 11030.082 | L22: 11662.601 | M22: 13426.304 | N22: 14339.006 | O22: 14286.423 | P22: 14659.748 | S22: 733.792 | T22: 844.736 | U22: 783.185 | V22: 822.141 | W22: 876.224 | X22: 830.074 | Y22: 929.887 | Z22: 965.267 | AA22: 1101.278 | AB22: 1252.187 | AC22: 1685.554 | AD22: 1673.174 | AE22: 1746.7 | AF22: 1931.942 | AI22: 4087.088 | AJ22: 4223.686 | AK22: 4344.294 | AL22: 4529.455 | AM22: 4601.71 | AN22: 4727.251 | AO22: 4750.875 | AP22: 5026.412 | AQ22: 5040.583 | AR22: 4996.895 | AS22: 5807.079 | AT22: 6047.564 | AU22: 6095.909 | AV22: 6124.298 | AY22: 14372.265 | AZ22: 15312.663 | BA22: 15819.177 | BB22: 16167.545 | BC22: 16938.496 | BD22: 17136.584 | BE22: 18058.553 | BF22: 18584.695 | BG22: 19366.545 | BH22: 20361.49 | BI22: 23525.896 | BJ22: 24689.602 | BK22: 24783.784 | BL22: 25179.237 | BO22: 40969 | BP22: 41334 | BQ22: 41699 | BR22: 42064 | BS22: 42430 | BT22: 42795 | BU22: 43160 | BV22: 43525 | BW22: 43891 | BX22: 44256 | BY22: 44621 | BZ22: 44994 | CA22: 45352 | CB22: 45717 | CD22: Annual
A23: Massachusetts | B23: MA | C23: 12827 | D23: 13130.5 | E23: 13911 | F23: 14793.5 | G23: 15544 | H23: 15549 | I23: 16027 | J23: 17164 | K23: 17933 | L23: =(17614+16103)/2 -> 16858.5 | M23: =(21344+20758)/2 -> 21051 | N23: =(24880+23943)/2 -> 24411.5 | O23: =(25305+24274)/2 -> 24789.5 | P23: =(26613+25588)/2 -> 26100.5 | Q23: =(29091+27928)/2 -> 28509.5 | S23: 1989 | T23: 2017 | U23: 2346 | V23: 2496 | W23: 2491.5 | X23: 2671.5 | Y23: 2627.5 | Z23: 2757 | AA23: 3142.5 | AB23: =(3157+2920)/2 -> 3038.5 | AC23: =(4705+4365)/2 -> 4535 | AD23: =(5191+4911)/2 -> 5051 | AE23: =(5018+4739)/2 -> 4878.5 | AF23: =(4684+4555)/2 -> 4619.5 | AG23: =(3940+3802)/2 -> 3871 | AI23: 5116 | AJ23: 5326 | AK23: 5775.5 | AL23: 6005.5 | AM23: 6515.5 | AN23: 6418 | AO23: 6576.5 | AP23: 7013 | AQ23: 7376 | AR23: =(7596+6747)/2 -> 7171.5 | AS23: =(8733+8508)/2 -> 8620.5 | AT23: =(9796+9606)/2 -> 9701 | AU23: =(9990+9668)/2 -> 9829 | AV23: =(9990+9766)/2 -> 9878 | AW23: =(10001+9803)/2 -> 9902 | AY23: 21687.5 | AZ23: 22308.5 | BA23: 24171 | BB23: 25481 | BC23: 26757.5 | BD23: 26957 | BE23: 27478 | BF23: 29300.5 | BG23: 30805.5 | BH23: =(30610+27828)/2 -> 29219 | BI23: =(37684+36484)/2 -> 37084 | BJ23: =(42783+41282)/2 -> 42032.5 | BK23: =(43025+41281)/2 -> 42153 | BL23: =(43847+42392)/2 -> 43119.5 | BM23: =(45840+44265)/2 -> 45052.5 | BO23: 40878 | BP23: 41244 | BQ23: 41609 | BR23: 42005 | BS23: 42339 | BT23: 42705 | BU23: 43070 | BV23: 43435 | BW23: 43800 | BX23: 44166 | BY23: 44531 | BZ23: 44950 | CA23: 45261 | CB23: 45627 | CC23: 45992 | CD23: Annual
A24: Michigan | B24: MI | C24: =5665.1+2255.1 -> 7920.2 | D24: =5836.3+2390.7 -> 8227 | E24: =6055.3+2441.3 -> 8496.6 | F24: =6364.8+2560.1 -> 8924.9 | G24: =6901.4+2730.8 -> 9632.2 | H24: =7132.8+2833.4 -> 9966.2 | I24: =7043+2955.7 -> 9998.7 | J24: =7029.8+2827.4 -> 9857.2 | K24: =6233.9+2843.4 -> 9077.3 | L24: =7299.7+3261.9 -> 10561.6 | M24: =9067.3+3763.1 -> 12830.4 | N24: =7631.1+3855.8 -> 11486.9 | O24: =8318.1+3889.5 -> 12207.6 | P24: =8711.8+4346.8 -> 13058.6 | S24: 833.7 | T24: 960.5 | U24: 884 | V24: 983.3 | W24: 1002 | X24: 960 | Y24: 955 | Z24: 1133.9 | AA24: 889.3 | AB24: 1184.2 | AC24: 1732.4 | AD24: 1425 | AE24: 1610 | AF24: 2075 | AI24: =1141.9+831.3+5247.3+415.7 -> 7636.2 | AJ24: =1158.8+877.3+5359.2+438.7 -> 7834 | AK24: =1169.8+945.2+5477.7+472.6 -> 8065.3 | AL24: =1240.9+901.9+5743.6+499 -> 8385.4 | AM24: =1190.5+653.1+5523+517 -> 7883.6 | AN24: =1261+577.6+5799.6+557.8 -> 8196 | AO24: =1314.7+570.8+6028.4+568.7 -> 8482.6 | AP24: =1361.9+746.8+6300.9+615.3 -> 9024.9 | AQ24: =1235+669+5729.7+583.3 -> 8217 | AR24: =1411+1212.9+6601.2+869.3 -> 10094.4 | AS24: =1514.3+1222.8+7333.4+888.2 -> 10958.7 | AT24: =1747.1+1157+8064.2+862.1 -> 11830.4 | AU24: =1614.9+1295.2+7819+984.8 -> 11713.9 | AV24: =1658.1+1344+7966.5+1010.3 -> 11978.9 | AY24: =11206.8+8967.6 -> 20174.4 | AZ24: =11530.2+9332.7 -> 20862.9 | BA24: =9719.8+11807.4 -> 21527.2 | BB24: =9789.6+12245.8 -> 22035.4 | BC24: =10113.4+12409.6 -> 22523 | BD24: =10369.7+12992.4 -> 23362.1 | BE24: =10433.2+13513.9 -> 23947.1 | BF24: =10766.2+13881.2 -> 24647.4 | BG24: =9574.2+13205.6 -> 22779.8 | BH24: =11755.8+15132.7 -> 26888.5 | BI24: =14304.5+17072.3 -> 31376.8 | BJ24: =13129.2+18050.7 -> 31179.9 | BK24: =14132.7+18224.5 -> 32357.2 | BL24: =14990.5+19002.8 -> 33993.3 | BO24: 41030 | BP24: 41395 | BQ24: 41760 | BR24: 42125 | BS24: 42491 | BT24: 42856 | BU24: 43221 | BV24: 43586 | BW24: 43952 | BX24: 44317 | BY24: 44682 | BZ24: 45061 | CA24: 45413 | CB24: 45778 | CD24: Annual
A25: Minnesota | B25: MN | C25: 8385 | D25: 9138 | E25: 10041 | F25: 10731 | G25: 11146 | H25: 11839 | I25: 12263 | J25: 12523 | K25: 13495 | L25: 13279 | M25: 15697 | N25: 15979 | O25: 15986 | P25: 16332 | S25: 853 | T25: 958 | U25: 1372 | V25: 1299 | W25: 1227 | X25: 1280 | Y25: 1295 | Z25: 1479 | AA25: 1525 | AB25: 1677 | AC25: 2051 | AD25: 2318 | AE25: 3162 | AF25: 3183 | AI25: 4738 | AJ25: 5113 | AK25: 5282 | AL25: 5320 | AM25: 5485 | AN25: 5592 | AO25: 5775 | AP25: 5806 | AQ25: 6116 | AR25: 6251 | AS25: 7220 | AT25: 7441 | AU25: 7790 | AV25: 7881 | AY25: =15916+700 -> 16616 | AZ25: =17351+705 -> 18056 | BA25: =19308+707 -> 20015 | BB25: =19938+703 -> 20641 | BC25: =20522+711 -> 21233 | BD25: =21394+704 -> 22098 | BE25: =22036+711 -> 22747 | BF25: =22581+759 -> 23340 | BG25: =23899+776 -> 24675 | BH25: =24059+712 -> 24771 | BI25: =28042+776 -> 28818 | BJ25: =28676+1322 -> 29998 | BK25: =30002+982 -> 30984 | BL25: =30527+1219 -> 31746 | BO25: 40940 | BP25: 41306 | BQ25: 41671 | BR25: 42036 | BS25: 42401 | BT25: 42767 | BU25: 43132 | BV25: 43497 | BW25: 43862 | BX25: 44228 | BY25: 44593 | BZ25: 44972 | CA25: 45346 | CB25: 45689 | CD25: Biennial (odd)
A26: Mississippi | B26: MS | C26: 1427 | D26: 1600.1 | E26: 1726.8 | F26: 1813.9 | G26: 1903.2 | H26: 1895.8 | I26: 1807.3 | J26: 1900 | K26: 1942.6 | L26: 1850 | M26: 2082.5 | N26: 2431.4 | O26: 2110.2 | P26: 2117.8 | S26: 456 | T26: 480 | U26: 562.6 | V26: 678 | W26: 635 | X26: 586.7 | Y26: 550.9 | Z26: 517.5 | AA26: 563 | AB26: 488 | AC26: 675 | AD26: 897.5 | AE26: 970 | AF26: 951.1 | AI26: =1840+202.2 -> 2042.2 | AJ26: =1929.6+223.4 -> 2153 | AK26: =2040+247.9 -> 2287.9 | AL26: 2367.8 | AM26: 2415.1 | AN26: 2387.6 | AO26: 2333.6 | AP26: =2185+292.2 -> 2477.2 | AQ26: =2228.1+292.3 -> 2520.4 | AR26: =2144+329 -> 2473 | AS26: =2380+378.7 -> 2758.7 | AT26: =2722.8+404 -> 3126.8 | AU26: =2911.9+422.8 -> 3334.7 | AV26: =2921.6+433 -> 3354.6 | AY26: 4693.3 | AZ26: 5018.1 | BA26: 5362.1 | BB26: 5630.1 | BC26: 5703.2 | BD26: 5776.1 | BE26: 5600 | BF26: 5802.2 | BG26: 5965.5 | BH26: 5754.3 | BI26: 6493.5 | BJ26: 7523.8 | BK26: 7600.1 | BL26: 7627 | BO26: 40848 | BP26: 41214 | BQ26: 41548 | BR26: 41944 | BS26: 42278 | BT26: 42675 | BU26: 43040 | BV26: 43405 | BW26: 43770 | BX26: 44136 | BY26: 44501 | BZ26: 44866 | CA26: 45231 | CB26: 45597 | CD26: Annual
A27: Missouri | B27: MO | C27: 6084.7 | D27: 6370 | E27: 6981 | F27: 7058.2 | G27: 7566.1 | H27: 7849.2 | I27: 7789.2 | J27: 7797.9 | K27: 7949.1 | L27: 7766.7 | M27: 8933.6 | N27: 10079.3 | O27: 9633.6 | P27: =9249.4+910 -> 10159.4 | S27: 520 | T27: 477 | U27: 580 | V27: 495.7 | W27: 520 | X27: 377.5 | Y27: 490.3 | Z27: 487.4 | AA27: 493 | AB27: 551.6 | AC27: 702.7 | AD27: 920.1 | AE27: 1055.5 | AF27: 1099.3 | AI27: 1940.6 | AJ27: 1966 | AK27: 2064 | AL27: 2077 | AM27: 2137.1 | AN27: 2187.9 | AO27: 2240.9 | AP27: 2342.1 | AQ27: 2405.3 | AR27: 2285.1 | AS27: 2829.8 | AT27: 2910.8 | AU27: 3200.9 | AV27: 3166.1 | AY27: 7585.6 | AZ27: 7928.5 | BA27: 8738.5 | BB27: 8672.8 | BC27: 9322.8 | BD27: 9398 | BE27: 9418.2 | BF27: 9821.7 | BG27: 9983.9 | BH27: 9784.5 | BI27: 11418.6 | BJ27: 13152.7 | BK27: 13162.1 | BL27: 13562.1 | BO27: 40878 | BP27: 41244 | BQ27: 41609 | BR27: 41974 | BS27: 42339 | BT27: 42705 | BU27: 43070 | BV27: 43435 | BW27: 43800 | BX27: 44166 | BY27: 44531 | BZ27: 44896 | CA27: 45261 | CB27: 45627 | CD27: Annual
A28: Montana | B28: MT | C28: 859.47 | D28: 1039.16 | E28: 1104.898 | F28: 1229.127 | G28: 1311.185 | H28: 1320.815 | I28: 1404.438 | J28: 1410.943 | K28: 1469.746 | L28: 1549.25 | M28: 1623.128 | N28: 2086.756 | O28: 2178.325 | P28: 2284.365 | S28: 127.975 | T28: 154.096 | U28: 155.022 | V28: 179.829 | W28: 156.851 | X28: 168.763 | Y28: 171.748 | Z28: 165.898 | AA28: 167.214 | AB28: 159.088 | AC28: 170.783 | AD28: 277.207 | AE28: 271.356 | AF28: 326.217 | AI28: N/A | AJ28: N/A | AK28: N/A | AL28: N/A | AM28: N/A | AN28: N/A | AO28: N/A | AP28: N/A | AQ28: N/A | AR28: N/A | AS28: N/A | AT28: N/A | AU28: N/A | AV28: N/A | AY28: 1852.134 | AZ28: 2056.252 | BA28: 2137.41 | BB28: 2251.181 | BC28: 2357.877 | BD28: 2359.345 | BE28: 2476.395 | BF28: 2498.558 | BG28: 2570.361 | BH28: 2644.011 | BI28: 2748.874 | BJ28: 3710.034 | BK28: 3782.68 | BL28: 4043.071 | BO28: 40603 | BP28: 41365 | BQ28: 41365 | BR28: 42064 | BS28: 42064 | BT28: 42795 | BU28: 42795 | BV28: 43556 | BW28: 43556 | BX28: 44256 | BY28: 44256 | BZ28: 44986 | CA28: 44986 | CB28: 45748 | CD28: Biennial (odd)
A29: Nebraska | B29: NE | C29: 1870 | D29: 2039.395 | E29: 2216 | F29: 2285 | G29: 2440 | H29: 2425 | I29: 2470 | J29: 2625.1 | K29: 2765 | L29: 2480 | M29: 2900 | N29: 3150 | O29: 2230 | P29: 3050 | S29: 230 | T29: 265 | U29: 263 | V29: 330 | W29: 310 | X29: 265 | Y29: 300 | Z29: 325 | AA29: 370 | AB29: 400 | AC29: 475 | AD29: 575 | AE29: 740 | AF29: 900 | AI29: 1485 | AJ29: 1499.996 | AK29: 1560 | AL29: 1615 | AM29: 1610 | AN29: 1625 | AO29: 1685 | AP29: 1750 | AQ29: 1820 | AR29: 2005 | AS29: 2350 | AT29: 2500 | AU29: 2600 | AV29: 2600 | AY29: 3767.0656 | AZ29: 4020.687 | BA29: 4220.4504 | BB29: 4473.856 | BC29: 4575 | BD29: 4605.427 | BE29: 4730.7339 | BF29: 4929.107 | BG29: 5175 | BH29: 5080 | BI29: 5960 | BJ29: 6500 | BK29: 5840 | BL29: 6865 | BO29: 40940 | BP29: 41365 | BQ29: 41671 | BR29: 42095 | BS29: 42401 | BT29: 42826 | BU29: 43132 | BV29: 43556 | BW29: 43862 | BX29: 44287 | BY29: 44593 | BZ29: 45017 | CA29: 45323 | CB29: 45748 | CD29: Biennial (odd)
A30: Nevada | B30: NV | C30: N/A | D30: N/A | E30: N/A | F30: N/A | G30: N/A | H30: N/A | I30: N/A | J30: N/A | K30: N/A | L30: N/A | M30: N/A | N30: N/A | O30: N/A | P30: N/A | S30: N/A | T30: N/A | U30: N/A | V30: N/A | W30: N/A | X30: N/A | Y30: N/A | Z30: N/A | AA30: N/A | AB30: N/A | AC30: N/A | AD30: N/A | AE30: N/A | AF30: N/A | AI30: 826.134 | AJ30: 934.536 | AK30: 985.935 | AL30: 1057 | AM30: 1114.995 | AN30: 1154.724 | AO30: 1214.518 | AP30: 1294.51 | AQ30: 1334.223 | AR30: 1301.969 | AS30: 1385.023 | AT30: 1843.322 | AU30: 1925.377 | AV30: 1814.039 | AY30: 2990.3308 | AZ30: 3125.7216 | BA30: 3292.3808 | BB30: 3654.6737 | BC30: 3691.2995 | BD30: 3915.5095 | BE30: 4076.5283 | BF30: 4350.1602 | BG30: 4496.5807 | BH30: 4397.3932 | BI30: 4696.2785 | BJ30: 5739.843 | BK30: 5895.1707 | BL30: 6036.338 | BO30: 40664 | BP30: 41395 | BQ30: 41395 | BR30: 42125 | BS30: 42125 | BT30: 42856 | BU30: 42856 | BV30: 43586 | BW30: 43586 | BX30: 44317 | BY30: 44317 | BZ30: 45047 | CA30: 45047 | CB30: 45778 | CD30: Biennial (odd)
A31: New Hampshire | B31: NH | C31: 97.7 | D31: 93 | E31: 97 | F31: 84.2 | G31: 85.5 | H31: 96 | I31: 98.9 | J31: 105 | K31: 106.5 | L31: 138.1 | M31: 134.6 | N31: 112.8 | O31: 89.4 | P31: 8.7 | S31: 578.1 | T31: 509.2 | U31: 520.2 | V31: 561.5 | W31: 574.2 | X31: 673.2 | Y31: 685.2 | Z31: 795.5 | AA31: 779.2 | AB31: 821.1 | AC31: 861.3 | AD31: 1232 | AE31: 1228.2 | AF31: 1209.2 | AI31: N/A | AJ31: N/A | AK31: N/A | AL31: N/A | AM31: N/A | AN31: N/A | AO31: N/A | AP31: N/A | AQ31: N/A | AR31: N/A | AS31: N/A | AT31: N/A | AU31: N/A | AV31: N/A | AY31: 2401 | AZ31: 2161.5 | BA31: 2202 | BB31: 2280.4 | BC31: 2324.2 | BD31: 2464.1 | BE31: 2507 | BF31: 2524.4 | BG31: 2518 | BH31: 2725.4 | BI31: 2770.2 | BJ31: 3162 | BK31: 3138 | BL31: 3117.9 | BO31: 40575 | BP31: 41306 | BQ31: 41306 | BR31: 42036 | BS31: 42036 | BT31: 42767 | BU31: 42767 | BV31: 43497 | BW31: 43497 | BX31: 44228 | BY31: 44228 | BZ31: 44971 | CA31: 44971 | CB31: 45689 | CD31: Biennial (odd)
A32: New Jersey | B32: NJ | C32: 11584.4 | D32: 13039 | E32: 12627 | F32: 13880 | G32: 13982.3 | H32: 14382.2 | I32: 16421.7 | J32: 17058.8 | K32: 14525.6 | L32: 17221.74 | M32: 20085 | N32: 19653.7 | O32: 19400.4 | P32: 21313 | S32: 2566 | T32: 2413 | U32: 2590 | V32: 2575 | W32: 2471 | X32: 2375.4 | Y32: 2266.1 | Z32: 3142 | AA32: 2861.6 | AB32: 3675.96 | AC32: 5225 | AD32: 5273.9 | AE32: 4489.1 | AF32: 4063.1 | AI32: 8422.8 | AJ32: 8676 | AK32: 9138 | AL32: 9090 | AM32: 9597.4 | AN32: 9509.9 | AO32: 10336.4 | AP32: 10252.5 | AQ32: 9794.1 | AR32: 11350.4 | AS32: 12580.6 | AT32: 13376.5 | AU32: 13717.6 | AV32: 14464.3 | AY32: 31696 | AZ32: 32813 | BA32: 32737.8 | BB32: 33812.66 | BC32: 34592.1 | BD32: 35786 | BE32: 37472.8 | BF32: 39072.6 | BG32: 35528.3 | BH32: 41967.81 | BI32: 50554.9 | BJ32: 52802.3 | BK32: 54248.8 | BL32: 57130.9 | BO32: 41030 | BP32: 41395 | BQ32: 41760 | BR32: 42125 | BS32: 42491 | BT32: 42856 | BU32: 43221 | BV32: 43586 | BW32: 44044 | BX32: 44348 | BY32: 44682 | BZ32: 45069 | CA32: 45413 | CB32: 45778 | CD32: Annual
A33: New Mexico | B33: NM | C33: 1115 | D33: 1217.3 | E33: 1280 | F33: 1360 | G33: 1455 | H33: 1346 | I33: 1408.8 | J33: 1605 | K33: 1660.6 | L33: 1667.2 | M33: 2038.5 | N33: 2321.7 | O33: 2537.1 | P33: 2114.6 | S33: 375 | T33: 342 | U33: 289 | V33: 225 | W33: 220 | X33: 100 | Y33: 110 | Z33: 115.5 | AA33: 17.1 | AB33: 42.3 | AC33: 68.1 | AD33: 264.5 | AE33: 323.7 | AF33: 730.7 | AI33: 2009 | AJ33: 2105.5 | AK33: 2145.1 | AL33: 2305 | AM33: 2280.1 | AN33: 2061.4 | AO33: 2217.1 | AP33: 2715.7 | AQ33: 3055.9 | AR33: 2616.6 | AS33: 3047 | AT33: 3771.4 | AU33: 4157.6 | AV33: 4505.9 | AY33: 5684.9 | AZ33: 5931.8 | BA33: 6186 | BB33: 6234.1 | BC33: 6264.6 | BD33: 5929.1 | BE33: 6374.6 | BF33: 7433.1 | BG33: 7882.5 | BH33: 7548.1 | BI33: 9049.1 | BJ33: 11994.9 | BK33: 13047.8 | BL33: 13614.4 | BO33: 40878 | BP33: 41244 | BQ33: 41609 | BR33: 42036 | BS33: 42370 | BT33: 42705 | BU33: 43101 | BV33: 43435 | BW33: 43800 | BX33: 44228 | BY33: 44531 | BZ33: 44907 | CA33: 45261 | CB33: 45627 | CD33: Annual
A34: New York | B34: NY | C34: 40256 | D34: 42543 | E34: 43735 | F34: 47075 | G34: 49464 | H34: 49382 | I34: 50410 | J34: 52150 | K34: 49046 | L34: 61049 | M34: 46975 | N34: 52819 | O34: 61201 | P34: 61531 | S34: 8229 | T34: 8638 | U34: 7671 | V34: 8137 | W34: 7994 | X34: 7969 | Y34: 7981 | Z34: 8585 | AA34: 8957 | AB34: 9601 | AC34: 27980 | AD34: 25533 | AE34: 28792 | AF34: 28911 | AI34: 14921 | AJ34: 15116 | AK34: 15364 | AL34: 15850 | AM34: 16134 | AN34: 16861 | AO34: 17303 | AP34: 18308 | AQ34: 15474 | AR34: 18155 | AS34: 19585 | AT34: 21715 | AU34: 22446 | AV34: 22953 | AY34: =66370+24269 -> 90639 | AZ34: =69351+23621 -> 92972 | BA34: =70188+25672 -> 95860 | BB34: =74562+25410 -> 99972 | BC34: =77128+23567 -> 100695 | BD34: =77926+26509 -> 104435 | BE34: =77923+28005 -> 105928 | BF34: =81305+29013 -> 110318 | BG34: =75543+30669 -> 106212 | BH34: =91093+26052 -> 117145 | BI34: =97368+27107 -> 124475 | BJ34: =102947+26837 -> 129784 | BK34: =110784+31685 -> 142469 | BL34: =249227-94090 -> 155137 | BO34: 41000 | BP34: 41365 | BQ34: 41730 | BR34: 42095 | BS34: 42461 | BT34: 42826 | BU34: 43191 | BV34: 43556 | BW34: 43922 | BX34: 44287 | BY34: 44652 | BZ34: 45017 | CA34: 45383 | CB34: 45748 | CD34: Annual
A35: North Carolina | B35: NC | C35: 10517.1 | D35: 11211.2 | E35: 10885.4 | F35: 10859.3 | G35: 11718.7 | H35: 12314.3 | I35: 12799.6 | J35: 12891.5 | K35: 14821.6 | L35: 14090.8 | M35: 15472.5 | N35: 16679.1 | O35: 17048.5 | P35: 16857.5 | S35: =1075+615.2 -> 1690.2 | T35: =1099.1+677.9 -> 1777 | U35: =1095.2+543.1 -> 1638.3 | V35: =1134.5+524.5 -> 1659 | W35: =916.8+554.1 -> 1470.9 | X35: =743.6+583.7 -> 1327.3 | Y35: =720.9+684.1 -> 1405 | Z35: =687+685.8 -> 1372.8 | AA35: =1037.2+808.2 -> 1845.4 | AB35: =867.5+733.4 -> 1600.9 | AC35: 1846.4 | AD35: =1680.7+726.5 -> 2407.2 | AE35: 2396.6 | AF35: =1552+785.8 -> 2337.8 | AI35: 6218.9 | AJ35: 5491 | AK35: 6285.5 | AL35: 6715.8 | AM35: 6918.4 | AN35: 7393.5 | AO35: 7624.9 | AP35: 8155.6 | AQ35: 8623.7 | AR35: 8890.5 | AS35: 10382.8 | AT35: 10874.6 | AU35: 11273.3 | AV35: 11553.5 | AY35: 20701.5 | AZ35: 20732.6 | BA35: 21006.8 | BB35: 21428.7 | BC35: 22174.1 | BD35: 23166.7 | BE35: 24016.6 | BF35: 24830.1 | BG35: 27602.6 | BH35: 26985.1 | BI35: 30709.6 | BJ35: 34147.8 | BK35: 34764.1 | BL35: 34779.7 | BO35: 41030 | BP35: 41334 | BQ35: 41760 | BR35: 42064 | BS35: 42461 | BT35: 42795 | BU35: 43221 | BV35: 43525 | BW35: 44256 | BX35: 44256 | BY35: 44682 | BZ35: 45000 | CA35: 45383 | CB35: 45717 | CD35: Biennial (odd)
A36: North Dakota | B36: ND | C36: 265.797 | D36: 278.86867 | E36: 382.875 | F36: 414.77936 | G36: 370.708 | H36: 392.568 | I36: 340.672 | J36: 358.056 | K36: 396.53146 | L36: 385.49108 | M36: 297.20891 | N36: 387.97875 | O36: 483.32404 | P36: 439.43868 | S36: 61.734 | T36: 64.509667 | U36: 185.092 | V36: 192.64765 | W36: 185.583 | X36: 185.839 | Y36: 54.592 | Z36: 47.496415 | AA36: 65.429683 | AB36: 99.520664 | AC36: 107.47934 | AD36: 194.50837 | AE36: 190.89163 | AF36: 256.37956 | AI36: 666.735 | AJ36: 715.49966 | AK36: 1149.083 | AL36: 1323.8645 | AM36: 1377.926 | AN36: 1490.1006 | AO36: 818.947 | AP36: 882.80029 | AQ36: 928.02729 | AR36: 845.15392 | AS36: 920.18007 | AT36: 1080.647 | AU36: 1126.5473 | AV36: 1259.4396 | AY36: 1736.5364 | AZ36: 1721.2098 | BA36: 2682.0371 | BB36: 2794.796 | BC36: 3123.1472 | BD36: 2515.361 | BE36: 2272.2898 | BF36: 2057.5261 | BG36: 2496.2547 | BH36: 2191.0518 | BI36: 2041.6695 | BJ36: 2708.1152 | BK36: 2261.4501 | BL36: 2668.0721 | BO36: 40634 | BP36: 41395 | BQ36: 41395 | BR36: 42125 | BS36: 42125 | BT36: 42856 | BU36: 42856 | BV36: 43586 | BW36: 43586 | BX36: 44317 | BY36: 44501 | BZ36: 45047 | CA36: 45047 | CB36: 45778 | CD36: Biennial (odd)
A37: Ohio | B37: OH | C37: 8891.2 | D37: 9444.1 | E37: 10098.6 | F37: 9171.6 | G37: 9624.8 | H37: 7972.9 | I37: 8377.5 | J37: 9179 | K37: 9472 | L37: 9857.4 | M37: 10349.8 | N37: 11115 | O37: 11506 | P37: 10621 | S37: 230 | T37: 205 | U37: 210 | V37: 190 | W37: 190 | X37: 189 | Y37: 191 | Z37: 200 | AA37: 200 | AB37: 215 | AC37: 215 | AD37: 236 | AE37: 241 | AF37: 212 | AI37: 8437.4 | AJ37: 8856.3 | AK37: 9438.3 | AL37: 10377.9 | AM37: 10869.9 | AN37: 10040.6 | AO37: 10227.6 | AP37: 10872 | AQ37: 10966 | AR37: 12410.8 | AS37: 12607 | AT37: 13799 | AU37: 14210 | AV37: 14450 | AY37: 20339.1 | AZ37: 21155.4 | BA37: 22414.7 | BB37: 22506.7 | BC37: 23485.3 | BD37: 21851.2 | BE37: 22486.7 | BF37: 23988.9 | BG37: 24391.8 | BH37: 26467.1 | BI37: 27244 | BJ37: 29454.2 | BK37: 30291.2 | BL37: 29600 | BO37: 40695 | BP37: 41426 | BQ37: 41426 | BR37: 42156 | BS37: 42156 | BT37: 42887 | BU37: 42887 | BV37: 43525 | BW37: 43525 | BX37: 44348 | BY37: 44348 | BZ37: 45078 | CA37: 45078 | CB37: 45809 | CD37: Biennial (odd)
A38: Oklahoma | B38: OK | C38: 1999.6259 | D38: 2103.4346 | E38: 2129.1023 | F38: 2076.2803 | G38: 1886.8805 | H38: 1901.75 | I38: 2257.8654 | J38: 2729.0899 | K38: 2693.2079 | L38: 2646.8637 | M38: 2820.6651 | N38: 3312.5819 | O38: 3291.0437 | P38: 3455.1847 | S38: 320.88488 | T38: 481.8702 | U38: 375.1186 | V38: 249.80343 | W38: 296.33053 | X38: 102.04348 | Y38: 136.71232 | Z38: 195.9727 | AA38: 245.58045 | AB38: 208.92605 | AC38: 278.89645 | AD38: 356.78319 | AE38: 443.83378 | AF38: 466.34821 | AI38: =1924.254051+187.025537 -> 2111.2796 | AJ38: =(2030.782388+204.49083) -> 2235.2732 | AK38: =2033.692016+212.693807 -> 2246.3858 | AL38: =2134.072436+191.112394 -> 2325.1848 | AM38: =1935.85243+164.542808 -> 2100.3952 | AN38: =2047.331315+217.950368 -> 2265.2817 | AO38: =2167.308584+261.599804 -> 2428.9084 | AP38: =2215.559022+350.807912 -> 2566.3669 | AQ38: =2164.036661+339.056944 -> 2503.0936 | AR38: =2164.060907+385.053314 -> 2549.1142 | AS38: =2489.375293+490.671022 -> 2980.0463 | AT38: =2636.497114+517.425523 -> 3153.9226 | AU38: =2478.086+566.572912 -> 3044.6589 | AV38: =2151.559878+567.720779 -> 2719.2807 | AY38: 5600.3437 | AZ38: 5888.3407 | BA38: 5855.636 | BB38: 5745.1303 | BC38: 5219.3392 | BD38: 5423.9926 | BE38: 6504.3347 | BF38: 6988.2465 | BG38: 6724.7294 | BH38: 6641.2983 | BI38: 7665.4292 | BJ38: 8288.5806 | BK38: 8520.7071 | BL38: 8275.7535 | BO38: 41061 | BP38: 41426 | BQ38: 41791 | BR38: 42156 | BS38: 42522 | BT38: 42887 | BU38: 43252 | BV38: 43617 | BW38: 43983 | BX38: 44348 | BY38: 44713 | BZ38: 45096 | CA38: 45444 | CB38: 45809 | CD38: Annual
A39: Oregon | B39: OR | C39: 6116.037 | D39: =6515.713-24.142 -> 6491.571 | E39: =7182.959-38.111 -> 7144.848 | F39: 7558.328 | G39: 8038.499 | H39: 8210.669 | I39: 8898.108 | J39: 8709.138 | K39: 8769.849 | L39: 9742.412 | M39: 11360.845 | N39: 8695.12 | O39: 12601.408 | P39: 14302.926 | S39: 395.906 | T39: =500.306-27.296 -> 473.01 | U39: =535.471-4.587 -> 530.884 | V39: 536.701 | W39: 525.402 | X39: 510.613 | Y39: 497.885 | Z39: 513.371 | AA39: 247.959 | AB39: 681.242 | AC39: 773.905 | AD39: 1136.036 | AE39: 1254.008 | AF39: 1602.278 | AI39: N/A | AJ39: N/A | AK39: N/A | AL39: N/A | AM39: N/A | AN39: N/A | AO39: N/A | AP39: N/A | AQ39: N/A | AR39: N/A | AS39: N/A | AT39: N/A | AU39: N/A | AV39: N/A | AY39: 7007.379 | AZ39: 7454.381 | BA39: 8166.896 | BB39: 8598.652 | BC39: 9225.591 | BD39: 9311.028 | BE39: 10128.049 | BF39: 9896.365 | BG39: 9796.533 | BH39: 11105.589 | BI39: 12765.795 | BJ39: 10919.866 | BK39: 14764.35 | BL39: 16887.838 | BO39: 41061 | BP39: 41395 | BQ39: 41791 | BR39: 42125 | BS39: 42522 | BT39: 42856 | BU39: 43252 | BV39: 43586 | BW39: 43983 | BX39: 44317 | BY39: 44713 | BZ39: 45063 | CA39: 45444 | CB39: 45778 | CD39: Biennial (odd)
A40: Pennsylvania | B40: PA | C40: 10800.527 | D40: 11727.5 | E40: 12032.8 | F40: 12707.9 | G40: 13052 | H40: 13304.8 | I40: 14174.1 | J40: 14570.1 | K40: 15438.2 | L40: 15768.8 | M40: 18163.7 | N40: 18124.7 | O40: 18770.3 | P40: 19631.8 | S40: 2022.401 | T40: 2482.1 | U40: 2501.2 | V40: 2831.7 | W40: 2982.4 | X40: 3118.7 | Y40: 2926.3 | Z40: 3558 | AA40: 3252.6 | AB40: 3776.5 | AC40: 4900.2 | AD40: 5651.3 | AE40: 5354.9 | AF40: 4741.2 | AI40: 8772.266 | AJ40: 9228.7 | AK40: 9477.3 | AL40: 9824.7 | AM40: 10204.5 | AN40: 10340.9 | AO40: 10752.6 | AP40: 11454.4 | AQ40: 11904 | AR40: 12801.1 | AS40: 13814.9 | AT40: 14012.6 | AU40: 14535.6 | AV40: 15317.5 | AY40: 27677.999 | AZ40: 29115.9 | BA40: 30180.555 | BB40: 30871.7 | BC40: 32776.4 | BD40: 34704.1 | BE40: 33974.8 | BF40: 35496.8 | BG40: 36954.7 | BH40: 42536.2 | BI40: 43579.7 | BJ40: 44881.1 | BK40: 46087.4 | BL40: 47787.6 | BO40: 41061 | BP40: 41426 | BQ40: 41791 | BR40: 42156 | BS40: 42522 | BT40: 42887 | BU40: 43252 | BV40: 43617 | BW40: 43983 | BX40: 44348 | BY40: 44713 | BZ40: 45078 | CA40: 45444 | CB40: 45962 | CD40: Annual
A41: Rhode Island | B41: RI | C41: 1076.5 | D41: 1107.8 | E41: 1148.1 | F41: 1228.2 | G41: 1257.4 | H41: 1297.3 | I41: 1381.2 | J41: 1426.8 | K41: 1295.8 | L41: 1535 | M41: 1827.1 | N41: 1886.9 | O41: 1856.6 | P41: 1999.2 | S41: =132.9+1.7 -> 134.6 | T41: =141.3+4.3 -> 145.6 | U41: =115.4+11.5 -> 126.9 | V41: =138+16.5 -> 154.5 | W41: =158.4+20.3 -> 178.7 | X41: =158+20.1 -> 178.1 | Y41: =176+21.8 -> 197.8 | Z41: =164+24.4 -> 188.4 | AA41: =132.3+21.2 -> 153.5 | AB41: =147.2+26.9 -> 174.1 | AC41: =214.9+31 -> 245.9 | AD41: =276+34.5 -> 310.5 | AE41: =345+36.7 -> 381.7 | AF41: =351+21.2 -> 372.2 | AI41: 873.4 | AJ41: 895 | AK41: 937 | AL41: 1000 | AM41: 1015 | AN41: 1035 | AO41: 1082 | AP41: 1172.9 | AQ41: 1109.1 | AR41: 1305.2 | AS41: 1506 | AT41: 1607 | AU41: 1701.3 | AV41: 1723.3 | AY41: 3146.84 | AZ41: 3236.945 | BA41: 3343.275 | BB41: 3416.797 | BC41: 3501.665 | BD41: 3572.147 | BE41: 3740.95 | BF41: 3952.45 | BG41: 3725.85 | BH41: 4191.7 | BI41: 4776.2 | BJ41: 5101.9 | BK41: 5463.9 | BL41: 5486.3 | BO41: 41030 | BP41: 41395 | BQ41: 41760 | BR41: 42125 | BS41: 42491 | BT41: 42856 | BU41: 43221 | BV41: 43586 | BW41: 43952 | BX41: 44317 | BY41: 44682 | BZ41: 45063 | CA41: 45413 | CB41: 45778 | CD41: Annual
A42: South Carolina | B42: SC | C42: 3285.699 | D42: 3354.6321 | E42: 3514.8454 | F42: 3777.156 | G42: 4066.887 | H42: 4296.4 | I42: 4417.417 | J42: 4661.029 | K42: 4707.916 | L42: 5064.667 | M42: 6252.2624 | N42: 5923.626 | O42: 6108.481 | P42: 6519.82 | S42: 228.3 | T42: 288.08524 | U42: 355 | V42: 357.131 | W42: 393.154 | X42: 329.486 | Y42: 358.914 | Z42: 400.997 | AA42: 375.56 | AB42: 465.9 | AC42: 560.448 | AD42: 762.083 | AE42: 927.68 | AF42: 1204.382 | AI42: 2446.4146 | AJ42: 2491.501 | AK42: 2569.3301 | AL42: 2751.186 | AM42: 2925.788 | AN42: 3041.207 | AO42: 3147.685 | AP42: 3399.926 | AQ42: 3419.654 | AR42: 3419.654 | AS42: 3852.456 | AT42: 4504.725 | AU42: 4845.676 | AV42: 5098.774 | AY42: 6674.1424 | AZ42: 6889.9544 | BA42: 7213.1592 | BB42: 7670.473 | BC42: 8235.752 | BD42: 8518.393 | BE42: 8838.458 | BF42: 9330.674 | BG42: 9552.233 | BH42: 9925.428 | BI42: 11876.877 | BJ42: 12558.634 | BK42: 13350.347 | BL42: 14491.93 | BO42: 41030 | BP42: 41306 | BQ42: 41760 | BR42: 42125 | BS42: 42491 | BT42: 42767 | BU42: 43191 | BV42: 43497 | BW42: 43952 | BX42: 44287 | BY42: 44682 | BZ42: 45055 | CA42: 45413 | CB42: 45778 | CD42: Annual
A43: South Dakota | B43: SD | C43: N/A | D43: N/A | E43: N/A | F43: N/A | G43: N/A | H43: N/A | I43: N/A | J43: N/A | K43: N/A | L43: N/A | M43: N/A | N43: N/A | O43: N/A | P43: N/A | S43: 24.38904 | T43: 23.245655 | U43: 8.711612 | V43: 10.809812 | W43: 11.424177 | X43: 10.777309 | Y43: 11.872042 | Z43: 14.47164 | AA43: 14.889195 | AB43: 15.659821 | AC43: 17.151487 | AD43: 19.169875 | AE43: 16.967424 | AF43: 26.222175 | AI43: 764.1696 | AJ43: 802.98803 | AK43: 848.43105 | AL43: 869.18326 | AM43: 901.48979 | AN43: 999.50904 | AO43: 1030.3864 | AP43: 1073.04 | AQ43: 1098.818 | AR43: 1149.2787 | AS43: 1279.133 | AT43: 1414.6852 | AU43: 1503.6204 | AV43: 1492.3276 | AY43: 1239.3434 | AZ43: 1319.5163 | BA43: 1387.6892 | BB43: 1431.8207 | BC43: 1488.8221 | BD43: 1601.2406 | BE43: 1636.2237 | BF43: 1695.4931 | BG43: 1734.1783 | BH43: 1811.9071 | BI43: 2002.4365 | BJ43: 2220.048 | BK43: 2412.7113 | BL43: 2446.1392 | BO43: 40940 | BP43: 41306 | BQ43: 41699 | BR43: 42064 | BS43: 42401 | BT43: 42767 | BU43: 43132 | BV43: 43497 | BW43: 43862 | BX43: 44228 | BY43: 44593 | BZ43: 44971 | CA43: 45323 | CB43: 45689 | CD43: Annual
A44: Tennessee | B44: TN | C44: 215 | D44: 204.1 | E44: 264.1 | F44: 269.1 | G44: 341 | H44: 272 | I44: 157.9 | J44: 103.2 | K44: 75.3 | L44: 3.9 | M44: 0 | N44: 0 | O44: 0 | P44: 0 | S44: =1031.6+689.1 -> 1720.7 | T44: =1387.7+747.3 -> 2135 | U44: =1338.5+720.7 -> 2059.2 | V44: =1241+668.2 -> 1909.2 | W44: =1398.6+753.1 -> 2151.7 | X44: =1613.9+869 -> 2482.9 | Y44: =1640.5+883.4 -> 2523.9 | Z44: =1700.8+915.8 -> 2616.6 | AA44: =1047.7+1945.7 -> 2993.4 | AB44: =991.8+1842 -> 2833.8 | AC44: =1390.7+2582.6 -> 3973.3 | AD44: =1750.7+3251.2 -> 5001.9 | AE44: =1327+2953.6 -> 4280.6 | AF44: =1216.3+2707.1 -> 3923.4 | AI44: 7069.1 | AJ44: 7302.6 | AK44: 7515.1 | AL44: 7878.2 | AM44: 8280.1 | AN44: 8861.1 | AO44: 9023.8 | AP44: 9463.9 | AQ44: 10028.9 | AR44: 10325.5 | AS44: 12357.7 | AT44: 14260.2 | AU44: 14387.8 | AV44: 14890 | AY44: 13026.1 | AZ44: 13827.2 | BA44: 14063.2 | BB44: 14330.4 | BC44: 15153.4 | BD44: 16125.5 | BE44: 16643.9 | BF44: 17346.7 | BG44: 18495.7 | BH44: 18660.7 | BI44: 22182.7 | BJ44: 25423.7 | BK44: 24872.4 | BL44: 26471.5 | BO44: 40848 | BP44: 41214 | BQ44: 41579 | BR44: 41944 | BS44: 42309 | BT44: 42675 | BU44: 43040 | BV44: 43405 | BW44: 43770 | BX44: 44136 | BY44: 44501 | BZ44: 44866 | CA44: 45231 | CB44: 45597 | CD44: Annual
A45: Texas | B45: TX | C45: N/A | D45: N/A | E45: N/A | F45: N/A | G45: N/A | H45: N/A | I45: N/A | J45: N/A | K45: N/A | L45: N/A | M45: N/A | N45: N/A | O45: N/A | P45: N/A | S45: N/A | T45: N/A | U45: N/A | V45: N/A | W45: N/A | X45: N/A | Y45: N/A | Z45: N/A | AA45: N/A | AB45: N/A | AC45: N/A | AD45: N/A | AE45: N/A | AF45: N/A | AI45: 22704.457 | AJ45: 26840.354 | AK45: 27724.696 | AL45: 29258.665 | AM45: 30663.502 | AN45: 30490.044 | AO45: 33506.194 | AP45: 35650.87 | AQ45: 32247.302 | AR45: 38625.332 | AS45: 43422.292 | AT45: 47862.082 | AU45: 49327.182 | AV45: 51090.782 | AY45: =(91620462-35540809)/1000 -> 56079.653 | AZ45: =(102510324-35902617)/1000 -> 66607.707 | BA45: =(105642392-38013459)/1000 -> 67628.933 | BB45: =(108053259-37751547)/1000 -> 70301.712 | BC45: =(105944086-35047132)/1000 -> 70896.954 | BD45: =(111468208-37470349)/1000 -> 73997.859 | BE45: =(127293632-44271751)/1000 -> 83021.881 | BF45: =(128814195-44123392)/1000 -> 84690.803 | BG45: =(127569079-49355025)/1000 -> 78214.054 | BH45: =165730.355-73739.033 -> 91991.322 | BI45: =183762.55-74271.189 -> 109491.36 | BJ45: =(182016590-63966876)/1000 -> 118049.71 | BK45: =(177398678-57121536)/1000 -> 120277.14 | BL45: =176613.536-56453.621 -> 120159.91 | BO45: 40848 | BP45: 41579 | BQ45: 41579 | BR45: 42290 | BS45: 42290 | BT45: 43018 | BU45: 43292 | BV45: 43748 | BW45: 44032 | BX45: 44470 | BY45: 44756 | BZ45: 45200 | CA45: 45474 | CB45: 45931 | CD45: Biennial (odd)
A46: Utah | B46: UT | C46: 2596.327 | D46: 2748.709 | E46: 2913.051 | F46: 3162.691 | G46: 3534.109 | H46: 3804.753 | I46: 4128.42 | J46: 4409.53 | K46: 5168.146 | L46: 5113.866 | M46: 5730.92 | N46: 6274.613 | O46: 6450.318 | P46: 6656.091 | S46: 248.286 | T46: 276.325 | U46: 310.916 | V46: 374.566 | W46: 365.555 | X46: 338.848 | Y46: 359.151 | Z46: 521.634 | AA46: 379.544 | AB46: 434.346 | AC46: 526.255 | AD46: 698.571 | AE46: 827.648 | AF46: 796.774 | AI46: 1610.577 | AJ46: 1683.229 | AK46: 1708.612 | AL46: 1800.212 | AM46: 1858.001 | AN46: 1944.401 | AO46: 2101.634 | AP46: 2246.587 | AQ46: 2295.662 | AR46: 2579.866 | AS46: 2832.961 | AT46: 3402.945 | AU46: 3380.526 | AV46: 3187.751 | AY46: 5422.451 | AZ46: 5675.139 | BA46: 5930.748 | BB46: 6366.587 | BC46: 6797.402 | BD46: 7208.987 | BE46: 7778.685 | BF46: 8423.834 | BG46: 9078.319 | BH46: 9374.23 | BI46: 10452.161 | BJ46: =11270.215+764.113 -> 12034.328 | BK46: =11620.618+868.864 -> 12489.482 | BL46: =(11546835+927469)/1000 -> 12474.304 | BO46: 40940 | BP46: 41306 | BQ46: 41671 | BR46: 42036 | BS46: 42430 | BT46: 42795 | BU46: 43160 | BV46: 43525 | BW46: 43983 | BX46: 44317 | BY46: 44682 | BZ46: 45047 | CA46: 45413 | CB46: 45778 | CD46: Annual
A47: Vermont | B47: VT | C47: 642.1 | D47: 667.7 | E47: 738.5 | F47: 740.3 | G47: 793.7 | H47: 803.6 | I47: 846.9 | J47: 853.2 | K47: 909.1 | L47: 961.7 | M47: 1102.6 | N47: 1137.5 | O47: 1134.7 | P47: 1333.5 | S47: 81 | T47: 96.3 | U47: 92.6 | V47: 82.4 | W47: 92.6 | X47: 98.1 | Y47: 89.6 | Z47: 97.5 | AA47: 95.1 | AB47: 120.6 | AC47: 187.4 | AD47: 181.3 | AE47: 229.2 | AF47: 248.5 | AI47: 352.7 | AJ47: 359.6 | AK47: 367.3 | AL47: 377.8 | AM47: 392.1 | AN47: 394 | AO47: 400.9 | AP47: 429.5 | AQ47: 454.6 | AR47: 507.9 | AS47: 553.7 | AT47: 576 | AU47: 606.9 | AV47: 619 | AY47: 1492 | AZ47: 1562.7 | BA47: 1644 | BB47: 1643.8 | BC47: 1737.6 | BD47: 1784.2 | BE47: 1839.9 | BF47: 1902.06 | BG47: 1986.6 | BH47: 2115.1 | BI47: 2439.7 | BJ47: 2530.1 | BK47: 2662.9 | BL47: =2745.1+146.1+63.5 -> 2954.7 | BO47: 40909 | BP47: 41275 | BQ47: 41640 | BR47: 42005 | BS47: 42370 | BT47: 42736 | BU47: 43101 | BV47: 43466 | BW47: 43831 | BX47: 44197 | BY47: 44562 | BZ47: 44927 | CA47: 45292 | CB47: 45658 | CD47: Annual
A48: Virginia | B48: VA | C48: 10902.1 | D48: 11610.8 | E48: 12359 | F48: 12036.1 | G48: 13162.4 | H48: 13380.2 | I48: 14110.4 | J48: 15380.5 | K48: 16164.2 | L48: 16101.3 | M48: 17862.4 | N48: 18726.8 | O48: 18100.4 | P48: 21793.9 | S48: 877.6 | T48: 839.8 | U48: 816.6 | V48: 771.6 | W48: 778 | X48: 824.9 | Y48: 912 | Z48: 1043.5 | AA48: 1019.2 | AB48: 1289.6 | AC48: 1737 | AD48: 1461 | AE48: 2063.8 | AF48: 1995.4 | AI48: =3153.3+579 -> 3732.3 | AJ48: =3303.5+600.2 -> 3903.7 | AK48: =3175.7+936.6 -> 4112.3 | AL48: =3292+985.3 -> 4277.3 | AM48: =3528.9+1055.4 -> 4584.3 | AN48: =3445.5+1045.2 -> 4490.7 | AO48: =3547.1+1067.8 -> 4614.9 | AP48: =3731.1+1115.5 -> 4846.6 | AQ48: =3893+1183 -> 5076 | AR48: =3705.7+1126 -> 4831.7 | AS48: =4299+1350.3 -> 5649.3 | AT48: =4876.5+1388.2 -> 6264.7 | AU48: =5400.9+1435.9 -> 6836.8 | AV48: =4987.4+1477 -> 6464.4 | AY48: =16246.5+2541.9 -> 18788.4 | AZ48: =17037.1+2627.5 -> 19664.6 | BA48: =17686.1+3095.8 -> 20781.9 | BB48: =17459.3+3081.3 -> 20540.6 | BC48: =18860.3+3458 -> 22318.3 | BD48: =19158.5+3466.1 -> 22624.6 | BE48: =20096.5+3541.3 -> 23637.8 | BF48: =21689+3577 -> 25266 | BG48: =22689.1+3819.6 -> 26508.7 | BH48: =22729.4+3943.2 -> 26672.6 | BI48: =25786.7+4700.6 -> 30487.3 | BJ48: =26901.2+4779.7 -> 31680.9 | BK48: =28121.4+4990.2 -> 33111.6 | BL48: =31406.5+5214.2 -> 36620.7 | BO48: 40878 | BP48: 41244 | BQ48: 41609 | BR48: 41974 | BS48: 42339 | BT48: 42705 | BU48: 43070 | BV48: 43435 | BW48: 43800 | BX48: 44166 | BY48: 44531 | BZ48: 44896 | CA48: 45261 | CB48: 45627 | CD48: Biennial (even)
A49: Washington | B49: WA | C49: N/A | D49: N/A | E49: N/A | F49: N/A | G49: N/A | H49: N/A | I49: N/A | J49: N/A | K49: N/A | L49: N/A | M49: N/A | N49: N/A | O49: N/A | P49: N/A | S49: N/A | T49: N/A | U49: N/A | V49: N/A | W49: N/A | X49: N/A | Y49: N/A | Z49: N/A | AA49: N/A | AB49: N/A | AC49: N/A | AD49: N/A | AE49: N/A | AF49: N/A | AI49: =7088.5+509.5 -> 7598 | AJ49: =7453.7+532 -> 7985.7 | AK49: =7974.6+560.4 -> 8535 | AL49: =8624.8+594.4 -> 9219.2 | AM49: =9121+634.2 -> 9755.2 | AN49: =9831.1+654.1 -> 10485.2 | AO49: =10725.8+691.8 -> 11417.6 | AP49: =11629.8+721.8 -> 12351.6 | AQ49: =12189.2+743.8 -> 12933 | AR49: =12598.1+750.1 -> 13348.2 | AS49: =14280.1+848.7 -> 15128.8 | AT49: =14826.1+891.7 -> 15717.8 | AU49: =15605.3+962.4 -> 16567.7 | AV49: =15758.6+988.8 -> 16747.4 | AY49: 15512.1 | AZ49: 15891.4 | BA49: 16752.6 | BB49: 17790.6 | BC49: 18811.6 | BD49: 20012.7 | BE49: 22721.2 | BF49: 24246.8 | BG49: 25829.7 | BH49: 26798.8 | BI49: 29552 | BJ49: 30749.3 | BK49: 32352.1 | BL49: 32863.1 | BO49: 40940 | BP49: 41334 | BQ49: 41671 | BR49: 42036 | BS49: 42401 | BT49: 42795 | BU49: 43132 | BV49: 43525 | BW49: 43862 | BX49: 44256 | BY49: 44593 | BZ49: 44986 | CA49: 45323 | CB49: 45717 | CD49: Biennial (odd)
A50: West Virginia | B50: WV | C50: 1721.6 | D50: 1770 | E50: 1809.6 | F50: 1860.5 | G50: 1934.7 | H50: 1834 | I50: 1961 | J50: 2105 | K50: 2156.15 | L50: 2041.3 | M50: 2190 | N50: 2209.5 | O50: 2023.3 | P50: 2019.556 | S50: 248.7 | T50: 231.3 | U50: 205.8 | V50: 177.5 | W50: 166 | X50: 109 | Y50: 142.1 | Z50: 136.98 | AA50: 144.5 | AB50: 160.3 | AC50: 150 | AD50: 152 | AE50: 318 | AF50: 313.5 | AI50: 1197 | AJ50: 1204 | AK50: 1266.5 | AL50: 1281.3 | AM50: 1378.8 | AN50: 1259 | AO50: 1288.5 | AP50: 1384.06 | AQ50: 1422.1 | AR50: 1473.8 | AS50: 1510.488 | AT50: 1702.3 | AU50: 1841 | AV50: 1910.7 | AY50: 4149.751 | AZ50: 4140.751 | BA50: 4271.251 | BB50: 4321.576 | BC50: 4327.794 | BD50: 4055.2 | BE50: 4356.17 | BF50: 4675.82 | BG50: 4585 | BH50: 4569.616 | BI50: 4645.424 | BJ50: 4884 | BK50: 5264.536 | BL50: 5323.157 | BO50: 40848 | BP50: 41214 | BQ50: 41579 | BR50: 41944 | BS50: 42309 | BT50: 42675 | BU50: 43040 | BV50: 43405 | BW50: 43770 | BX50: 44136 | BY50: 44501 | BZ50: 44866 | CA50: 45231 | CB50: 45597 | CD50: Annual
A51: Wisconsin | B51: WI | C51: 7120 | D51: 7590 | E51: 7800 | F51: 7845 | G51: 8050 | H51: 8360 | I51: 8720 | J51: 9090 | K51: 9235 | L51: 9720 | M51: 9690 | N51: 9710 | O51: 9910 | P51: 11140 | S51: 855 | T51: 960 | U51: 1100 | V51: 970 | W51: 1045 | X51: 940 | Y51: 960 | Z51: 1165 | AA51: 1505 | AB51: 1910 | AC51: 2585 | AD51: 2720 | AE51: 2715 | AF51: 2415 | AI51: 4365 | AJ51: 4500 | AK51: 4815 | AL51: 5030 | AM51: 5217.5 | AN51: 5370 | AO51: 5650 | AP51: 5845 | AQ51: 6010 | AR51: 6640 | AS51: 7230 | AT51: 7655 | AU51: 7810 | AV51: 8140 | AY51: 13603.5 | AZ51: 14307.5 | BA51: 15017.2 | BB51: 15146.3 | BC51: 15655.7 | BD51: 16033.4 | BE51: 16678.8 | BF51: 17434.9 | BG51: 18077.5 | BH51: 19610.6 | BI51: 20884.6 | BJ51: 21393.8 | BK51: 21772.2 | BL51: 23012.4 | BO51: 40940 | BP51: 41395 | BQ51: 41640 | BR51: 42005 | BS51: 42370 | BT51: 42736 | BU51: 43101 | BV51: 43586 | BW51: 43831 | BX51: 44348 | BY51: 44562 | BZ51: 45047 | CA51: 45292 | CB51: 45658 | CD51: Biennial (odd)
A52: Wyoming | B52: WY | C52: N/A | D52: N/A | E52: N/A | F52: N/A | G52: N/A | H52: N/A | I52: N/A | J52: N/A | K52: N/A | L52: N/A | M52: N/A | N52: N/A | O52: N/A | P52: N/A | S52: N/A | T52: N/A | U52: N/A | V52: N/A | W52: N/A | X52: N/A | Y52: N/A | Z52: N/A | AA52: N/A | AB52: N/A | AC52: N/A | AD52: N/A | AE52: N/A | AF52: N/A | AI52: 489.2 | AJ52: 507.7 | AK52: 521.3 | AL52: 545.6 | AM52: 470.5 | AN52: 420 | AO52: 444.8 | AP52: 508.3 | AQ52: 553.1 | AR52: 465.1 | AS52: 530.8 | AT52: 618 | AU52: 661.8 | AV52: 672.4 | AY52: 1023.6 | AZ52: 1067.8 | BA52: 1100 | BB52: 1103.1 | BC52: 1032.1 | BD52: 1027.9 | BE52: 1011.4 | BF52: 1218 | BG52: 1124.9 | BH52: 983.5 | BI52: 1140.6 | BJ52: 1400.8 | BK52: 1507.9 | BL52: 1496.9 | BO52: 40909 | BP52: 41275 | BQ52: 41640 | BR52: 42005 | BS52: 42370 | BT52: 42736 | BU52: 43101 | BV52: 43466 | BW52: 43831 | BX52: 44197 | BY52: 44562 | BZ52: 44938 | CA52: 45292 | CB52: 45658 | CD52: Biennial (even)
A53: United States | B53: US | C53: =SUM(C3:C52) -> 295889.76 | D53: =SUM(D3:D52) -> 310430.38 | E53: =SUM(E3:E52) -> 329154.97 | F53: =SUM(F3:F52) -> 344144.3 | G53: =SUM(G3:G52) -> 363160.44 | H53: =SUM(H3:H52) -> 373422.81 | I53: =SUM(I3:I52) -> 397976.53 | J53: =SUM(J3:J52) -> 417787.97 | ... P53: =SUM(P3:P52) -> 539516.52 | S53: =SUM(S3:S52) -> 45839.484 | T53: =SUM(T3:T52) -> 48913.9 | U53: =SUM(U3:U52) -> 49774.409 | V53: =SUM(V3:V52) -> 51150.524 | W53: =SUM(W3:W52) -> 52168.674 | X53: =SUM(X3:X52) -> 50879.287 | Y53: =SUM(Y3:Y52) -> 53315.841 | Z53: =SUM(Z3:Z52) -> 59855.412 | ... AF53: =SUM(AF3:AF52) -> 137030.08 | AI53: =SUM(AI3:AI52) -> 221482.87 | AJ53: =SUM(AJ3:AJ52) -> 232674.13 | AK53: =SUM(AK3:AK52) -> 243292.06 | AL53: =SUM(AL3:AL52) -> 255615.49 | AM53: =SUM(AM3:AM52) -> 264665.35 | AN53: =SUM(AN3:AN52) -> 267838.57 | AO53: =SUM(AO3:AO52) -> 279498.95 | AP53: =SUM(AP3:AP52) -> 294258.9 | ... AV53: =SUM(AV3:AV52) -> 406304.58 | AY53: =SUM(AY3:AY52) -> 736730.12 | AZ53: =SUM(AZ3:AZ52) -> 768729.52 | BA53: =SUM(BA3:BA52) -> 800896.7 | BB53: =SUM(BB3:BB52) -> 826594.69 | BC53: =SUM(BC3:BC52) -> 855201.48 | BD53: =SUM(BD3:BD52) -> 880602.6 | BE53: =SUM(BE3:BE52) -> 929850.15 | BF53: =SUM(BF3:BF52) -> 973909.84 | ... BL53: =SUM(BL3:BL52) -> 1366491.8

Sheet Forecasts_Feb2026
A1: $ millions | C1: PIT | D1: PIT | E1: PIT | F1: PIT | G1: PIT | I1: CIT | J1: CIT | K1: CIT | L1: CIT | M1: CIT | O1: Sales | P1: Sales | Q1: Sales | R1: Sales | S1: Sales | U1: Total | V1: Total | W1: Total | X1: Total | Y1: Total | AC1: $ millions | AD1: PIT | AE1: PIT | AF1: PIT | AG1: PIT | AI1: CIT | AJ1: CIT | AK1: CIT | AL1: CIT | AN1: Sales | AO1: Sales | AP1: Sales | AQ1: Sales | AS1: Total | AT1: Total | AU1: Total | AV1: Total | BA1: Total | BD1: Total | BG1: PIT | BJ1: PIT | BM1: Sales | BP1: Sales | CE1: MEDIAN | CF1: MEDIAN | CG1: MEDIAN | CH1: MEDIAN | CK1: FY 2025 Actual | CL1: FY 2025 Actual | CN1: FY 2026 Forecast | CO1: FY 2026 Forecast | CQ1: FY 2027 Forecast | CR1: FY 2027 Forecast
A2: State | B2: Abbr | C2: FY 2023 | D2: FY 2024 | E2: FY 2025 | F2: FY 2026 estimate | G2: FY 2027 estimate | I2: FY 2023 | J2: FY 2024 | K2: FY 2025 | L2: FY 2026 estimate | M2: FY 2027 estimate | O2: FY 2023 | P2: FY 2024 | Q2: FY 2025 | R2: FY 2026 estimate | S2: FY 2027 estimate | U2: FY 2023 | V2: FY 2024 | W2: FY 2025 | X2: FY 2026 estimate | Y2: FY 2027 estimate | Z2: Forecast Date | AA2: What's included in total | AC2: State | AD2: FY 2023-24 | AE2: FY 2024-25 | AF2: FY 2025-26 | AG2: FY 2026-27 | AI2: FY 2023-24 | AJ2: FY 2024-25 | AK2: FY 2025-26 | AL2: FY 2026-27 | AN2: FY 2023-24 | AO2: FY 2024-25 | AP2: FY 2025-26 | AQ2: FY 2026-27 | AS2: FY 2023-24 | AT2: FY 2024-25 | AU2: FY 2025-26 | AV2: FY 2026-27 | AZ2: Abbr | BA2: FY 2025-26 | BC2: Abbr | BD2: FY 2026-27 | BF2: Abbr | BG2: FY 2025-26 | BI2: Abbr | BJ2: FY 2026-27 | BL2: Abbr | BM2: FY 2025-26 | BO2: Abbr | BP2: FY 2026-27 | BS2: FY 2014 | BT2: FY 2015 | BU2: FY 2016 | BV2: FY 2017 | BW2: FY 2018 | BX2: FY 2019 | BY2: FY 2020 | BZ2: FY 2021 | CA2: FY 2022 | CB2: FY 2023 | CC2: FY 2024 | CD2: FY 2025 | CE2: FY 2024 | CF2: FY 2025 | CG2: FY 2026 forecast | CH2: FY 2027 forecast | CK2: Average | CL2: Median | CN2: Average | CO2: Median | CQ2: Average | CR2: Median
A3: Alabama | B3: AL | C3: =Actual!M3 -> 7032.0939 | D3: =Actual!N3 -> 7267.1289 | E3: =Actual!O3 -> 7495.1795 | F3: 7707.0097 | G3: 7904.8091 | I3: =Actual!AA3 -> 103.45026 | J3: =Actual!AB3 -> 103.54586 | K3: =Actual!AC3 -> 103.32133 | L3: 118.22809 | M3: 118.14498 | O3: =Actual!AO3 -> 3446.0096 | P3: =Actual!AP3 -> 3422.3503 | Q3: =Actual!AQ3 -> 3519.3319 | R3: 3432.6002 | S3: 3491.612 | U3: =Actual!BD3 -> 13621.779 | V3: =Actual!BE3 -> 14050.105 | W3: =Actual!BF3 -> 14470.873 | X3: 14547.142 | Y3: 14658.051 | Z3: 46037 | AA3: GF + Education | AC3: Alabama | AD3: =(D3-C3)/C3*100 -> 3.3423187 | AE3: =(E3-D3)/D3*100 -> 3.1381116 | AF3: =(F3-E3)/E3*100 -> 2.8262183 | AG3: =(G3-F3)/F3*100 -> 2.5664867 | AI3: =(J3-I3)/I3*100 -> 0.092411563 | AJ3: =(K3-J3)/J3*100 -> -0.21683919 | AK3: =(L3-K3)/K3*100 -> 14.427578 | AL3: =(M3-L3)/L3*100 -> -0.070298012 | AN3: =(P3-O3)/O3*100 -> -0.68656957 | AO3: =(Q3-P3)/P3*100 -> 2.8337704 | AP3: =(R3-Q3)/Q3*100 -> -2.4644367 | AQ3: =(S3-R3)/R3*100 -> 1.7191599 | AS3: =(V3-U3)/U3*100 -> 3.1444209 | AT3: =(W3-V3)/V3*100 -> 2.9947643 | AU3: =(X3-W3)/W3*100 -> 0.52705133 | AV3: =(Y3-X3)/X3*100 -> 0.76241137 | AZ3: WY | BA3: -25.021391 | BC3: AK | BD3: -12.331682 | BF3: LA | BG3: -16.268193 | BI3: MS | BJ3: -4.5863636 | BL3: UT | BM3: -6.053914 | BO3: LA | BP3: 0.19611108 | BR3: Personal income tax | BS3: =(Actual!D53-Actual!C53)/Actual!C53 -> 0.011695408 | BT3: =(Actual!E53-Actual!D53)/Actual!D53 -> 0.075352694 | BU3: =(Actual!F53-Actual!E53)/Actual!E53 -> 0.024839827 | BV3: =(Actual!G53-Actual!F53)/Actual!F53 -> 0.030501531 | BW3: =(Actual!H53-Actual!G53)/Actual!G53 -> 0.10467884 | BX3: =(Actual!I53-Actual!H53)/Actual!H53 -> 0.038636065 | BY3: =(Actual!J53-Actual!I53)/Actual!I53 -> -0.0036251371 | BZ3: =(Actual!K53-Actual!J53)/Actual!J53 -> 0.19623878 | ... CC3: =(Actual!N53-Actual!M53)/Actual!M53 -> 0.012769366 | CD3: =(E53-D53)/D53 -> 0.09194173 | CE3: =AD54/100 -> 0.0030810991 | CF3: =AE54/100 -> 0.073010462 | CG3: =AF54/100 -> 0.037566953 | CH3: =AG54/100 -> 0.02616092 | CJ3: PIT | CK3: =AE53/100 -> 0.097761688 | CL3: =AE54/100 -> 0.073010462 | CN3: =AF53/100 -> 0.045482671 | CO3: =AF54/100 -> 0.037566953 | CQ3: =AG53/100 -> 0.037261505 | CR3: =AG54/100 -> 0.02616092
A4: Alaska | B4: AK | C4: =Actual!M4 -> N/A | D4: =Actual!N4 -> N/A | E4: =Actual!O4 -> N/A | F4: N/A | G4: N/A | I4: =Actual!AA4 -> 124.4 | J4: =Actual!AB4 -> 177.2 | K4: =Actual!AC4 -> 228.7 | L4: 215 | M4: 250 | O4: =Actual!AO4 -> N/A | P4: =Actual!AP4 -> N/A | Q4: =Actual!AQ4 -> N/A | R4: N/A | S4: N/A | U4: =Actual!BD4 -> 9657.3 | V4: =Actual!BE4 -> 10200.9 | W4: =Actual!BF4 -> 12213.1 | X4: =17848.9-6664.7 -> 11184.2 | Y4: =15343.6-5538.6 -> 9805 | Z4: 46002 | AA4: Total - Federal | AC4: Alaska | AD4: N/A | AE4: N/A | AF4: N/A | AG4: N/A | AI4: =(J4-I4)/I4*100 -> 42.44373 | AJ4: =(K4-J4)/J4*100 -> 29.063205 | AK4: =(L4-K4)/K4*100 -> -5.9903804 | AL4: =(M4-L4)/L4*100 -> 16.27907 | AN4: N/A | AO4: N/A | AP4: N/A | AQ4: N/A | AS4: =(V4-U4)/U4*100 -> 5.6289025 | AT4: =(W4-V4)/V4*100 -> 19.72571 | AU4: =(X4-W4)/W4*100 -> -8.4245605 | AV4: =(Y4-X4)/X4*100 -> -12.331682 | AZ4: IA | BA4: -8.7752455 | BC4: RI | BD4: -1.5390455 | BF4: HI | BG4: -12.374576 | BI4: HI | BJ4: -1.7327885 | BL4: AL | BM4: -2.4644367 | BO4: MI | BP4: 0.90101888 | BR4: CIT | BS4: =(Actual!R53-Actual!Q53)/Actual!Q53 -> 0.026321743 | BT4: =(Actual!S53-Actual!R53)/Actual!R53 -> 0.057196486 | BU4: =(Actual!T53-Actual!S53)/Actual!S53 -> -0.040083353 | BV4: =(Actual!U53-Actual!T53)/Actual!T53 -> -0.03128064 | BW4: =(Actual!V53-Actual!U53)/Actual!U53 -> 0.072239257 | BX4: =(Actual!W53-Actual!V53)/Actual!V53 -> 0.22515573 | BY4: =(Actual!X53-Actual!W53)/Actual!W53 -> -0.052535362 | BZ4: =(Actual!Y53-Actual!X53)/Actual!X53 -> 0.44029519 | ... CC4: =(Actual!AB53-Actual!AA53)/Actual!AA53 -> -0.022297948 | CD4: =(K53-J53)/J53 -> 0.041182674 | CE4: =AI54/100 -> -0.010073897 | CF4: =AJ54/100 -> -0.034266526 | CG4: =AK54/100 -> -0.042790659 | CH4: =AL54/100 -> 0.0029995197 | CJ4: CIT | CK4: =AJ53/100 -> 0.046552966 | CL4: =AJ54/100 -> -0.034266526 | CN4: =AK53/100 -> -0.034395185 | CO4: =AK54/100 -> -0.042790659 | CQ4: =AL53/100 -> -0.0056090625 | CR4: =AL54/100 -> 0.0029995197
A5: Arizona | B5: AZ | C5: =Actual!M5 -> 5239.5529 | D5: =Actual!N5 -> 4845.7665 | E5: =Actual!O5 -> 5482.9504 | F5: 5778.8012 | G5: 6089.0083 | I5: =Actual!AA5 -> 1806.3114 | J5: =Actual!AB5 -> 1744.8217 | K5: =Actual!AC5 -> 1750.5472 | L5: 1837.3452 | M5: 1903.2847 | O5: =Actual!AO5 -> 7677.7893 | P5: =Actual!AP5 -> 7933.9142 | Q5: =Actual!AQ5 -> 8151.8501 | R5: 8395.047 | S5: 8686.3951 | U5: =Actual!BD5 -> 15589.624 | V5: =Actual!BE5 -> 15452.589 | W5: =Actual!BF5 -> 16428.095 | X5: 17172.752 | Y5: 17890.902 | Z5: 46051 | AA5: Total taxes | AC5: Arizona | AD5: =(D5-C5)/C5*100 -> -7.5156481 | AE5: =(E5-D5)/D5*100 -> 13.149289 | AF5: =(F5-E5)/E5*100 -> 5.3958321 | AG5: =(G5-F5)/F5*100 -> 5.3680182 | AI5: =(J5-I5)/I5*100 -> -3.4041597 | AJ5: =(K5-J5)/J5*100 -> 0.32814385 | AK5: =(L5-K5)/K5*100 -> 4.9583353 | AL5: =(M5-L5)/L5*100 -> 3.5888466 | AN5: =(P5-O5)/O5*100 -> 3.3359199 | AO5: =(Q5-P5)/P5*100 -> 2.7468901 | AP5: =(R5-Q5)/Q5*100 -> 2.9833338 | AQ5: =(S5-R5)/R5*100 -> 3.4704761 | AS5: =(V5-U5)/U5*100 -> -0.87901606 | AT5: =(W5-V5)/V5*100 -> 6.3128949 | AU5: =(X5-W5)/W5*100 -> 4.5328263 | AV5: =(Y5-X5)/X5*100 -> 4.1819181 | AZ5: AK | BA5: -8.4245605 | BC5: KS | BD5: -0.91817577 | BF5: IA | BG5: -11.47044 | BI5: GA | BJ5: 0.25195142 | BL5: ID | BM5: -2.0336284 | BO5: FL | BP5: 1.0626382 | BR5: Sales tax | BS5: =(Actual!AF53-Actual!AE53)/Actual!AE53 -> 0.048075406 | BT5: =(Actual!AG53-Actual!AF53)/Actual!AF53 -> 0.049971815 | BU5: =(Actual!AH53-Actual!AG53)/Actual!AG53 -> 0.02656169 | BV5: =(Actual!AI53-Actual!AH53)/Actual!AH53 -> 0.028699384 | BW5: =(Actual!AJ53-Actual!AI53)/Actual!AI53 -> 0.043648741 | BX5: =(Actual!AK53-Actual!AJ53)/Actual!AJ53 -> 0.04980279 | BY5: =(Actual!AL53-Actual!AK53)/Actual!AK53 -> 0.0035466359 | BZ5: =(Actual!AM53-Actual!AL53)/Actual!AL53 -> 0.10052001 | ... CC5: =(Actual!AP53-Actual!AO53)/Actual!AO53 -> 0.012345517 | CD5: =(Q53-P53)/P53 -> 0.02393173 | CE5: =AN54/100 -> 0.011242559 | CF5: =AO54/100 -> 0.024795913 | CG5: =AP54/100 -> 0.032100826 | CH5: =AQ54/100 -> 0.028903697 | CJ5: Sales | CK5: =AO53/100 -> 0.025082354 | CL5: =AO54/100 -> 0.024795913 | CN5: =AP53/100 -> 0.032270546 | CO5: =AP54/100 -> 0.032100826 | CQ5: =AQ53/100 -> 0.028316191 | CR5: =AQ54/100 -> 0.028903697
A6: Arkansas | B6: AR | C6: =Actual!M6 -> 3147.8 | D6: =Actual!N6 -> 3066.7 | E6: =Actual!O6 -> 2939.3 | I6: =Actual!AA6 -> 782.1 | J6: =Actual!AB6 -> 608.7 | K6: =Actual!AC6 -> 395.8 | O6: =Actual!AO6 -> 3418.4 | P6: =Actual!AP6 -> 3480.4 | Q6: =Actual!AQ6 -> 3527.9 | U6: =Actual!BD6 -> 7185.4 | V6: =Actual!BE6 -> 6900.5 | W6: =Actual!BF6 -> 6679.4 | AA6: GF | AC6: Arkansas | AZ6: ID | BA6: -6.0327092 | BC6: GA | BD6: -0.43429251 | BF6: SC | BG6: -3.5636608 | BI6: OK | BJ6: 0.57777205 | BL6: MI | BM6: -1.6562774 | BO6: AL | BP6: 1.7191599 | BR6: Total revenue | BS6: =(Actual!AU53-Actual!AT53)/Actual!AT53 -> 0.024606163 | BT6: =(Actual!AV53-Actual!AU53)/Actual!AU53 -> 0.048635688 | BU6: =(Actual!AW53-Actual!AV53)/Actual!AV53 -> 0.010150965 | BV6: =(Actual!AX53-Actual!AW53)/Actual!AW53 -> 0.032421413 | BW6: =(Actual!AY53-Actual!AX53)/Actual!AX53 -> 0.073344621 | BX6: =(Actual!AZ53-Actual!AY53)/Actual!AY53 -> 0.050765499 | BY6: =(Actual!BA53-Actual!AZ53)/Actual!AZ53 -> -0.011535194 | BZ6: =(Actual!BB53-Actual!BA53)/Actual!BA53 -> 0.18087848 | ... CC6: =(Actual!BE53-Actual!BD53)/Actual!BD53 -> 0.021985105 | CD6: =(W53-V53)/V53 -> 0.052774671 | CE6: =AS54/100 -> 0.020618149 | CF6: =AT54/100 -> 0.034452807 | CG6: =AU54/100 -> 0.0070979368 | CH6: =AV54/100 -> 0.022105905 | CJ6: Total | CK6: =AT53/100 -> 0.056061616 | CL6: =AT54/100 -> 0.034452807 | CN6: =AU53/100 -> 0.020867833 | CO6: =AU54/100 -> 0.0070979368 | CQ6: =AV53/100 -> 0.018939018 | CR6: =AV54/100 -> 0.022105905
A7: California | B7: CA | C7: =Actual!M7 -> 101748.82 | D7: =Actual!N7 -> 115166 | E7: =Actual!O7 -> 130178 | F7: 137840 | G7: 142202 | I7: =Actual!AA7 -> 36337 | J7: =Actual!AB7 -> 35456 | K7: =Actual!AC7 -> 41338 | L7: 41702 | M7: 43528 | O7: =Actual!AO7 -> 33324 | P7: =Actual!AP7 -> 33339 | Q7: =Actual!AQ7 -> 33602 | R7: 34401 | S7: 35085 | U7: =Actual!BD7 -> 179214 | V7: =Actual!BE7 -> 195261 | W7: =Actual!BF7 -> 218506 | X7: 225706 | Y7: 231047 | Z7: 46037 | AA7: GF | AC7: California | AD7: =(D7-C7)/C7*100 -> 13.186572 | AE7: =(E7-D7)/D7*100 -> 13.035097 | AF7: =(F7-E7)/E7*100 -> 5.8857872 | AG7: =(G7-F7)/F7*100 -> 3.1645386 | AI7: =(J7-I7)/I7*100 -> -2.424526 | AJ7: =(K7-J7)/J7*100 -> 16.589576 | AK7: =(L7-K7)/K7*100 -> 0.88054574 | AL7: =(M7-L7)/L7*100 -> 4.3786869 | AN7: =(P7-O7)/O7*100 -> 0.045012604 | AO7: =(Q7-P7)/P7*100 -> 0.78886589 | AP7: =(R7-Q7)/Q7*100 -> 2.3778347 | AQ7: =(S7-R7)/R7*100 -> 1.9883143 | AS7: =(V7-U7)/U7*100 -> 8.9540996 | AT7: =(W7-V7)/V7*100 -> 11.904579 | AU7: =(X7-W7)/W7*100 -> 3.295104 | AV7: =(Y7-X7)/X7*100 -> 2.3663527 | AZ7: HI | BA7: -4.7000043 | BC7: NE | BD7: -0.32130859 | BF7: MS | BG7: -3.5605613 | BI7: LA | BJ7: 0.85410144 | BL7: WY | BM7: -0.42405731 | BO7: CA | BP7: 1.9883143
A8: Colorado | B8: CO | C8: =Actual!M8 -> 10952.7 | D8: =Actual!N8 -> 10044.2 | E8: =Actual!O8 -> 9997.9 | F8: 10225.8 | G8: 11593.2 | I8: =Actual!AA8 -> 2366.7 | J8: =Actual!AB8 -> 2796.6 | K8: =Actual!AC8 -> 2619.5 | L8: 1812.5 | M8: 2084.4 | O8: =Actual!AO8 -> 4552.8 | P8: =Actual!AP8 -> 4595.8 | Q8: =Actual!AQ8 -> 4657.7 | R8: =4600.1+232.3 -> 4832.4 | S8: =4798.5+248.1 -> 5046.6 | U8: =Actual!BD8 -> 17998 | V8: =Actual!BE8 -> 17251.4 | W8: =Actual!BF8 -> 17181.3 | X8: 16870.3 | Y8: 18325.5 | Z8: 46006 | AA8: GF | AC8: Colorado | AD8: =(D8-C8)/C8*100 -> -8.2947584 | AE8: =(E8-D8)/D8*100 -> -0.46096255 | AF8: =(F8-E8)/E8*100 -> 2.2794787 | AG8: =(G8-F8)/F8*100 -> 13.372059 | AI8: =(J8-I8)/I8*100 -> 18.164533 | AJ8: =(K8-J8)/J8*100 -> -6.3326897 | AK8: =(L8-K8)/K8*100 -> -30.807406 | AL8: =(M8-L8)/L8*100 -> 15.001379 | AN8: =(P8-O8)/O8*100 -> 0.94447373 | AO8: =(Q8-P8)/P8*100 -> 1.3468819 | AP8: =(R8-Q8)/Q8*100 -> 3.7507783 | AQ8: =(S8-R8)/R8*100 -> 4.4325801 | AS8: =(V8-U8)/U8*100 -> -4.1482387 | AT8: =(W8-V8)/V8*100 -> -0.40634383 | AU8: =(X8-W8)/W8*100 -> -1.8101075 | AV8: =(Y8-X8)/X8*100 -> 8.6258099 | AZ8: LA | BA8: -4.4879357 | BC8: MS | BD8: -0.2595339 | BF8: OK | BG8: -3.3305882 | BI8: CT | BJ8: 1.0226588 | BL8: KS | BM8: 0.27449604 | BO8: MA | BP8: 2.0403957
A9: Connecticut | B9: CT | C9: =Actual!M9 -> 11223.39 | D9: =Actual!N9 -> 11803.047 | E9: =Actual!O9 -> 12963.93 | F9: =9503.4+4098.4 -> 13601.8 | G9: =9864+3876.9 -> 13740.9 | I9: =Actual!AA9 -> 3564.6562 | J9: =Actual!AB9 -> 3520.2047 | K9: =Actual!AC9 -> 3769.5983 | L9: =1381.7+2440.6 -> 3822.3 | M9: =1460.5+2365.6 -> 3826.1 | O9: =Actual!AO9 -> 5782.4012 | P9: =Actual!AP9 -> 5847.4102 | Q9: =Actual!AQ9 -> 5998.3277 | R9: =5279.2+899.1 -> 6178.3 | S9: =5409.9+922.7 -> 6332.6 | U9: =Actual!BD9 -> 22894.461 | V9: =Actual!BE9 -> 23066.009 | W9: =Actual!BF9 -> 24177.124 | X9: =24465-1827.1+2325.3 -> 24963.2 | Y9: =26038.4-1940.8+2430.6 -> 26528.2 | Z9: 46037 | AA9: GF + Transportation - Federal | AC9: Connecticut | AD9: =(D9-C9)/C9*100 -> 5.1647171 | AE9: =(E9-D9)/D9*100 -> 9.8354596 | AF9: =(F9-E9)/E9*100 -> 4.9203406 | AG9: =(G9-F9)/F9*100 -> 1.0226588 | AI9: =(J9-I9)/I9*100 -> -1.2470075 | AJ9: =(K9-J9)/J9*100 -> 7.0846339 | AK9: =(L9-K9)/K9*100 -> 1.3980724 | AL9: =(M9-L9)/L9*100 -> 0.099416582 | AN9: =(P9-O9)/O9*100 -> 1.1242559 | AO9: =(Q9-P9)/P9*100 -> 2.5809287 | AP9: =(R9-Q9)/Q9*100 -> 3.0003751 | AQ9: =(S9-R9)/R9*100 -> 2.4974508 | AS9: =(V9-U9)/U9*100 -> 0.74929679 | AT9: =(W9-V9)/V9*100 -> 4.817112 | AU9: =(X9-W9)/W9*100 -> 3.2513203 | AV9: =(Y9-X9)/X9*100 -> 6.2692283 | AZ9: UT | BA9: -3.7327405 | BC9: NY | BD9: -0.17495218 | BF9: IN | BG9: -1.5183258 | BI9: ID | BJ9: 1.1556061 | BL9: MA | BM9: 1.0938639 | BO9: WI | BP9: 2.0536167
A10: Delaware | B10: DE | C10: =Actual!M10 -> 2112.9 | D10: =Actual!N10 -> 2216.8944 | E10: =Actual!O10 -> 2383.2 | F10: 2532.8 | G10: 2648.3 | I10: =Actual!AA10 -> 383.9 | J10: =Actual!AB10 -> 344.81503 | K10: =Actual!AC10 -> 371.4 | L10: 333.3 | M10: 255.2 | O10: =Actual!AO10 -> N/A | P10: =Actual!AP10 -> N/A | Q10: =Actual!AQ10 -> N/A | R10: N/A | S10: N/A | U10: =Actual!BD10 -> 6295.1 | V10: =Actual!BE10 -> 6348.925 | W10: =Actual!BF10 -> 6694.3 | X10: 6856.9 | Y10: 6948.5 | Z10: 46005 | AA10: GF | AC10: Delaware | AD10: =(D10-C10)/C10*100 -> 4.9218778 | AE10: =(E10-D10)/D10*100 -> 7.5017397 | AF10: =(F10-E10)/E10*100 -> 6.2772743 | AG10: =(G10-F10)/F10*100 -> 4.5601706 | AI10: =(J10-I10)/I10*100 -> -10.181028 | AJ10: =(K10-J10)/J10*100 -> 7.7099208 | AK10: =(L10-K10)/K10*100 -> -10.258481 | AL10: =(M10-L10)/L10*100 -> -23.432343 | AN10: N/A | AO10: N/A | AP10: N/A | AQ10: N/A | AS10: =(V10-U10)/U10*100 -> 0.85503048 | AT10: =(W10-V10)/V10*100 -> 5.4398969 | AU10: =(X10-W10)/W10*100 -> 2.4289321 | AV10: =(Y10-X10)/X10*100 -> 1.3358806 | AZ10: WV | BA10: -3.5548667 | BC10: LA | BD10: -0.11103002 | BF10: MO | BG10: -1.2394307 | BI10: MA | BJ10: 1.2087756 | BL10: OK | BM10: 1.2797591 | BO10: GA | BP10: 2.2189626
A11: Florida | B11: FL | C11: =Actual!M11 -> N/A | D11: =Actual!N11 -> N/A | E11: =Actual!O11 -> N/A | F11: N/A | G11: N/A | I11: =Actual!AA11 -> 5517.2 | J11: =Actual!AB11 -> 6015.8 | K11: =Actual!AC11 -> 5808.9 | L11: 5334.8 | M11: 5361.5 | O11: =Actual!AO11 -> 35800.2 | P11: =Actual!AP11 -> 36014 | Q11: =Actual!AQ11 -> 36907 | R11: 37406.9 | S11: 37804.4 | U11: =Actual!BD11 -> 47327.8 | V11: =Actual!BE11 -> 48342 | W11: =Actual!BF11 -> 49676 | X11: 50987.5 | Y11: 52101 | Z11: 46045 | AA11: GF | AC11: Florida | AD11: N/A | AE11: N/A | AF11: N/A | AG11: N/A | AI11: =(J11-I11)/I11*100 -> 9.0371928 | AJ11: =(K11-J11)/J11*100 -> -3.4392766 | AK11: =(L11-K11)/K11*100 -> -8.1616141 | AL11: =(M11-L11)/L11*100 -> 0.50048737 | AN11: =(P11-O11)/O11*100 -> 0.59720337 | AO11: =(Q11-P11)/P11*100 -> 2.4795913 | AP11: =(R11-Q11)/Q11*100 -> 1.3544856 | AQ11: =(S11-R11)/R11*100 -> 1.0626382 | AS11: =(V11-U11)/U11*100 -> 2.1429266 | AT11: =(W11-V11)/V11*100 -> 2.7595052 | AU11: =(X11-W11)/W11*100 -> 2.6401079 | AV11: =(Y11-X11)/X11*100 -> 2.1838686 | AZ11: TX | BA11: -3.0554777 | BC11: TN | BD11: 0.53417853 | BF11: GA | BG11: -0.95926187 | BI11: ME | BJ11: 1.791595 | BL11: FL | BM11: 1.3544856 | BO11: VA | BP11: 2.2428016
A12: Georgia | B12: GA | C12: =Actual!M12 -> 16969.072 | D12: =Actual!N12 -> 16018.875 | E12: =Actual!O12 -> 16234.724 | F12: 16078.99 | G12: 16119.502 | I12: =Actual!AA12 -> 3807.5734 | J12: =Actual!AB12 -> 3614.9529 | K12: =Actual!AC12 -> 3256.1081 | L12: 3145.9461 | M12: 3079.175 | O12: =Actual!AO12 -> 8918.9444 | P12: =Actual!AP12 -> 9004.5913 | Q12: =Actual!AQ12 -> 9344.6258 | R12: 9554.412 | S12: 9766.4209 | U12: =Actual!BD12 -> 35944.539 | V12: =Actual!BE12 -> 36441.732 | W12: =Actual!BF12 -> 37219.732 | X12: 36770.133 | Y12: 36610.443 | Z12: 46006 | AA12: GF | AC12: Georgia | AD12: =(D12-C12)/C12*100 -> -5.5995817 | AE12: =(E12-D12)/D12*100 -> 1.3474683 | AF12: =(F12-E12)/E12*100 -> -0.95926187 | AG12: =(G12-F12)/F12*100 -> 0.25195142 | AI12: =(J12-I12)/I12*100 -> -5.0588769 | AJ12: =(K12-J12)/J12*100 -> -9.9266786 | AK12: =(L12-K12)/K12*100 -> -3.3832418 | AL12: =(M12-L12)/L12*100 -> -2.1224499 | AN12: =(P12-O12)/O12*100 -> 0.96028076 | AO12: =(Q12-P12)/P12*100 -> 3.7762346 | AP12: =(R12-Q12)/Q12*100 -> 2.2449931 | AQ12: =(S12-R12)/R12*100 -> 2.2189626 | AS12: =(V12-U12)/U12*100 -> 1.3832239 | AT12: =(W12-V12)/V12*100 -> 2.1349145 | AU12: =(X12-W12)/W12*100 -> -1.2079596 | AV12: =(Y12-X12)/X12*100 -> -0.43429251 | AZ12: OK | BA12: -2.9344619 | BC12: OK | BD12: 0.75319843 | BF12: NM | BG12: 1.488498 | BI12: NE | BJ12: 1.8589445 | BL12: MS | BM12: 1.7699449 | BO12: KS | BP12: 2.2955524
A13: Hawaii | B13: HI | C13: =Actual!M13 -> 3099.886 | D13: =Actual!N13 -> 3280.416 | E13: =Actual!O13 -> 3288.541 | F13: 2881.598 | G13: 2831.666 | I13: =Actual!AA13 -> 316.831 | J13: =Actual!AB13 -> 483.676 | K13: =Actual!AC13 -> 400.097 | L13: 420.94 | M13: 429.972 | O13: =Actual!AO13 -> 4408.473 | P13: =Actual!AP13 -> 4446.125 | Q13: =Actual!AQ13 -> 4596.199 | R13: 4779.814 | S13: 4929.829 | U13: =Actual!BD13 -> 9200.308 | V13: =Actual!BE13 -> 9568.313 | W13: =Actual!BF13 -> 9974.161 | X13: 9505.375 | Y13: 9695.483 | Z13: 46029 | AA13: GF | AC13: Hawaii | AD13: =(D13-C13)/C13*100 -> 5.8237626 | AE13: =(E13-D13)/D13*100 -> 0.247682 | AF13: =(F13-E13)/E13*100 -> -12.374576 | AG13: =(G13-F13)/F13*100 -> -1.7327885 | AI13: =(J13-I13)/I13*100 -> 52.660567 | AJ13: =(K13-J13)/J13*100 -> -17.279956 | AK13: =(L13-K13)/K13*100 -> 5.2094867 | AL13: =(M13-L13)/L13*100 -> 2.145674 | AN13: =(P13-O13)/O13*100 -> 0.85408258 | AO13: =(Q13-P13)/P13*100 -> 3.3753887 | AP13: =(R13-Q13)/Q13*100 -> 3.9949315 | AQ13: =(S13-R13)/R13*100 -> 3.1385112 | AS13: =(V13-U13)/U13*100 -> 3.9999204 | AT13: =(W13-V13)/V13*100 -> 4.2415837 | AU13: =(X13-W13)/W13*100 -> -4.7000043 | AV13: =(Y13-X13)/X13*100 -> 2.0000053 | AZ13: MO | BA13: -2.0920191 | BC13: AL | BD13: 0.76241137 | BF13: UT | BG13: 1.4888255 | BI13: VT | BJ13: 2.2063503 | BL13: GA | BM13: 2.2449931 | BO13: MS | BP13: 2.3362958
A14: Idaho | B14: ID | C14: =Actual!M14 -> 2148.7127 | D14: =Actual!N14 -> 2228.701 | E14: =Actual!O14 -> 2418.855 | F14: 2514.092 | G14: 2543.145 | I14: =Actual!AA14 -> 1031.8542 | J14: =Actual!AB14 -> 867.482 | K14: =Actual!AC14 -> 890.614 | L14: 497.342 | M14: 462.353 | O14: =Actual!AO14 -> 2503.364 | P14: =Actual!AP14 -> 2341.957 | Q14: =Actual!AQ14 -> 2269.097 | R14: 2222.952 | S14: 2400.055 | U14: =Actual!BD14 -> 5948.0488 | V14: =Actual!BE14 -> 5711.262 | W14: =Actual!BF14 -> 5866.303 | X14: 5512.406 | Y14: 5680.224 | Z14: 46037 | AA14: GF | AC14: Idaho | AD14: =(D14-C14)/C14*100 -> 3.7226149 | AE14: =(E14-D14)/D14*100 -> 8.5320552 | AF14: =(F14-E14)/E14*100 -> 3.9372761 | AG14: =(G14-F14)/F14*100 -> 1.1556061 | AI14: =(J14-I14)/I14*100 -> -15.929789 | AJ14: =(K14-J14)/J14*100 -> 2.6665683 | AK14: =(L14-K14)/K14*100 -> -44.157402 | AL14: =(M14-L14)/L14*100 -> -7.0351991 | AN14: =(P14-O14)/O14*100 -> -6.4476041 | AO14: =(Q14-P14)/P14*100 -> -3.1110733 | AP14: =(R14-Q14)/Q14*100 -> -2.0336284 | AQ14: =(S14-R14)/R14*100 -> 7.9670186 | AS14: =(V14-U14)/U14*100 -> -3.9809156 | AT14: =(W14-V14)/V14*100 -> 2.714654 | AU14: =(X14-W14)/W14*100 -> -6.0327092 | AV14: =(Y14-X14)/X14*100 -> 3.0443694 | AZ14: WI | BA14: -1.8714031 | BC14: MI | BD14: 0.96095285 | BF14: MN | BG14: 2.1493756 | BI14: MI | BJ14: 2.3380987 | BL14: CA | BM14: 2.3778347 | BO14: ME | BP14: 2.4221417
A15: Illinois | B15: IL | C15: =Actual!M15 -> 25309 | D15: =Actual!N15 -> 27376 | E15: =Actual!O15 -> 30123 | I15: =Actual!AA15 -> 6256 | J15: =Actual!AB15 -> 5611 | K15: =Actual!AC15 -> 5077 | O15: =Actual!AO15 -> 11589 | P15: =Actual!AP15 -> 11710 | Q15: =Actual!AQ15 -> 11794 | U15: =Actual!BD15 -> 53672 | V15: =Actual!BE15 -> 54887 | W15: =Actual!BF15 -> 57594 | AA15: GF | AC15: Illinois | AZ15: CO | BA15: -1.8101075 | BC15: NM | BD15: 1.2185629 | BF15: ME | BG15: 2.2598252 | BI15: MD | BJ15: 2.3858872 | BL15: TN | BM15: 2.4189668 | BO15: CT | BP15: 2.4974508
A16: Indiana | B16: IN | C16: =Actual!M16 -> 7575.7 | D16: =Actual!N16 -> 8096.1 | E16: =Actual!O16 -> 8687.2 | F16: 8555.3 | G16: 8810.6 | I16: =Actual!AA16 -> 1230.6 | J16: =Actual!AB16 -> 965.1 | K16: =Actual!AC16 -> 846.8 | L16: 1022 | M16: 1048.5 | O16: =Actual!AO16 -> 10464.7 | P16: =Actual!AP16 -> 10369.9 | Q16: =Actual!AQ16 -> 10633.7 | R16: 11230 | S16: 11617.7 | U16: =Actual!BD16 -> 21058.2 | V16: =Actual!BE16 -> 21484.6 | W16: =Actual!BF16 -> 22228 | X16: 23153.1 | Y16: 23782.1 | Z16: 46009 | AA16: GF | AC16: Indiana | AD16: =(D16-C16)/C16*100 -> 6.8693322 | AE16: =(E16-D16)/D16*100 -> 7.3010462 | AF16: =(F16-E16)/E16*100 -> -1.5183258 | AG16: =(G16-F16)/F16*100 -> 2.9841151 | AI16: =(J16-I16)/I16*100 -> -21.574842 | AJ16: =(K16-J16)/J16*100 -> -12.257797 | AK16: =(L16-K16)/K16*100 -> 20.689655 | AL16: =(M16-L16)/L16*100 -> 2.592955 | AN16: =(P16-O16)/O16*100 -> -0.9059027 | AO16: =(Q16-P16)/P16*100 -> 2.5439011 | AP16: =(R16-Q16)/Q16*100 -> 5.6076436 | AQ16: =(S16-R16)/R16*100 -> 3.4523598 | AS16: =(V16-U16)/U16*100 -> 2.0248644 | AT16: =(W16-V16)/V16*100 -> 3.4601529 | AU16: =(X16-W16)/W16*100 -> 4.1618679 | AV16: =(Y16-X16)/X16*100 -> 2.7166988 | AZ16: GA | BA16: -1.2079596 | BC16: PA | BD16: 1.2541391 | BF16: CO | BG16: 2.2794787 | BI16: SC | BJ16: 2.3990722 | BL16: MO | BM16: 2.6474394 | BO16: PA | BP16: 2.557377
A17: Iowa | B17: IA | C17: =Actual!M17 -> 5599.3 | D17: =Actual!N17 -> 4993.2 | E17: =Actual!O17 -> 4947.5 | F17: 4380 | G17: 4605.2 | I17: =Actual!AA17 -> 984.1 | J17: =Actual!AB17 -> 890.5 | K17: =Actual!AC17 -> 825.1 | L17: 723 | M17: 702 | O17: =Actual!AO17 -> 3937.1 | P17: =Actual!AP17 -> 4170.4 | Q17: =Actual!AQ17 -> 4234.9 | R17: 4402 | S17: 4546.7 | U17: =Actual!BD17 -> 9845.3 | V17: =Actual!BE17 -> 9755.8 | W17: =Actual!BF17 -> 8942.2 | X17: 8157.5 | Y17: 8498.5 | Z17: 46002 | AA17: GF | AC17: Iowa | AD17: =(D17-C17)/C17*100 -> -10.824567 | AE17: =(E17-D17)/D17*100 -> -0.91524473 | AF17: =(F17-E17)/E17*100 -> -11.47044 | AG17: =(G17-F17)/F17*100 -> 5.1415525 | AI17: =(J17-I17)/I17*100 -> -9.5112285 | AJ17: =(K17-J17)/J17*100 -> -7.3441887 | AK17: =(L17-K17)/K17*100 -> -12.374258 | AL17: =(M17-L17)/L17*100 -> -2.9045643 | AN17: =(P17-O17)/O17*100 -> 5.9256813 | AO17: =(Q17-P17)/P17*100 -> 1.5466142 | AP17: =(R17-Q17)/Q17*100 -> 3.9457838 | AQ17: =(S17-R17)/R17*100 -> 3.2871422 | AS17: =(V17-U17)/U17*100 -> -0.90906321 | AT17: =(W17-V17)/V17*100 -> -8.3396544 | AU17: =(X17-W17)/W17*100 -> -8.7752455 | AV17: =(Y17-X17)/X17*100 -> 4.1802023 | AZ17: SC | BA17: -1.1922334 | BC17: MA | BD17: 1.2825413 | BF17: AL | BG17: 2.8262183 | BI17: AL | BJ17: 2.5664867 | BL17: VT | BM17: 2.6532923 | BO17: VT | BP17: 2.6162333
A18: Kansas | B18: KS | C18: =Actual!M18 -> 4507.0067 | D18: =Actual!N18 -> 4503.6154 | E18: =Actual!O18 -> 4675.736 | F18: 4945 | G18: 5105 | I18: =Actual!AA18 -> 1561.5193 | J18: =Actual!AB18 -> 1465.7801 | K18: =Actual!AC18 -> 1362.544 | L18: =1145+43 -> 1188 | M18: =1040+44 -> 1084 | O18: =Actual!AO18 -> 3579.8481 | P18: =Actual!AP18 -> 3539.4831 | Q18: =Actual!AQ18 -> 3475.46 | R18: 3485 | S18: 3565 | U18: =Actual!BD18 -> 9282.81 | V18: =Actual!BE18 -> 10139.561 | W18: =Actual!BF18 -> 10022.038 | X18: 10226.8 | Y18: 10132.9 | Z18: 45982 | AA18: GF | AC18: Kansas | AD18: =(D18-C18)/C18*100 -> -0.075243843 | AE18: =(E18-D18)/D18*100 -> 3.8218314 | AF18: =(F18-E18)/E18*100 -> 5.7587511 | AG18: =(G18-F18)/F18*100 -> 3.2355915 | AI18: =(J18-I18)/I18*100 -> -6.1311553 | AJ18: =(K18-J18)/J18*100 -> -7.0430835 | AK18: =(L18-K18)/K18*100 -> -12.810155 | AL18: =(M18-L18)/L18*100 -> -8.7542088 | AN18: =(P18-O18)/O18*100 -> -1.1275609 | AO18: =(Q18-P18)/P18*100 -> -1.8088263 | AP18: =(R18-Q18)/Q18*100 -> 0.27449604 | AQ18: =(S18-R18)/R18*100 -> 2.2955524 | AS18: =(V18-U18)/U18*100 -> 9.2294316 | AT18: =(W18-V18)/V18*100 -> -1.1590504 | AU18: =(X18-W18)/W18*100 -> 2.0431174 | AV18: =(Y18-X18)/X18*100 -> -0.91817577 | AZ18: MS | BA18: -1.1872525 | BC18: DE | BD18: 1.3358806 | BF18: VT | BG18: 3.7566953 | BI18: NM | BJ18: 2.616092 | BL18: AZ | BM18: 2.9833338 | BO18: MO | BP18: 2.6324538
A19: Kentucky | B19: KY | C19: =Actual!M19 -> 5843.9 | D19: =Actual!N19 -> 5807.4991 | E19: =Actual!O19 -> 5319.2 | I19: =Actual!AA19 -> 1221.6 | J19: =Actual!AB19 -> 1249.1 | K19: =Actual!AC19 -> 1834.5 | O19: =Actual!AO19 -> 5576.3 | P19: =Actual!AP19 -> 5802.5822 | Q19: =Actual!AQ19 -> 5821.3 | U19: =Actual!BD19 -> 15147.7 | V19: =Actual!BE19 -> 15571.259 | W19: =Actual!BF19 -> 15703.2 | AA19: GF | AC19: Kentucky | AZ19: VT | BA19: -0.32055519 | BC19: ME | BD19: 1.3709296 | BF19: ID | BG19: 3.9372761 | BI19: MN | BJ19: 2.8505936 | BL19: CT | BM19: 3.0003751 | BO19: NM | BP19: 2.6740677
A20: Louisiana | B20: LA | C20: =Actual!M20 -> 4654.6 | D20: =Actual!N20 -> 4797.9 | E20: =Actual!O20 -> 4768.2 | F20: 3992.5 | G20: 4026.6 | I20: =Actual!AA20 -> 1616.8 | J20: =Actual!AB20 -> 1636 | K20: =Actual!AC20 -> 1451.9 | L20: 900 | M20: 800 | O20: =Actual!AO20 -> 4445 | P20: =Actual!AP20 -> 4482.4 | Q20: =Actual!AQ20 -> 4869.5 | R20: 5405.1 | S20: 5415.7 | U20: =Actual!BD20 -> 16656.9 | V20: =Actual!BE20 -> 17105.3 | W20: =Actual!BF20 -> 16785 | X20: 16031.7 | Y20: 16013.9 | Z20: 46002 | AA20: GF before transfers | AC20: Louisiana | AD20: =(D20-C20)/C20*100 -> 3.0786749 | AE20: =(E20-D20)/D20*100 -> -0.61902082 | AF20: =(F20-E20)/E20*100 -> -16.268193 | AG20: =(G20-F20)/F20*100 -> 0.85410144 | AI20: =(J20-I20)/I20*100 -> 1.1875309 | AJ20: =(K20-J20)/J20*100 -> -11.253056 | AK20: =(L20-K20)/K20*100 -> -38.01226 | AL20: =(M20-L20)/L20*100 -> -11.111111 | AN20: =(P20-O20)/O20*100 -> 0.84139483 | AO20: =(Q20-P20)/P20*100 -> 8.6359986 | AP20: =(R20-Q20)/Q20*100 -> 10.999076 | AQ20: =(S20-R20)/R20*100 -> 0.19611108 | AS20: =(V20-U20)/U20*100 -> 2.6919775 | AT20: =(W20-V20)/V20*100 -> -1.872519 | AU20: =(X20-W20)/W20*100 -> -4.4879357 | AV20: =(Y20-X20)/X20*100 -> -0.11103002 | AZ20: TN | BA20: 0.29225996 | BC20: MD | BD20: 1.3976416 | BF20: PA | BG20: 3.9485137 | BI20: IN | BJ20: 2.9841151 | BL20: RI | BM20: 3.185926 | BO20: RI | BP20: 2.8041715
A21: Maine | B21: ME | C21: =Actual!M21 -> 2473.4789 | D21: =Actual!N21 -> 2388.9911 | E21: =Actual!O21 -> 2723.9713 | F21: 2785.5283 | G21: 2835.4337 | I21: =Actual!AA21 -> 451.21106 | J21: =Actual!AB21 -> 459.75287 | K21: =Actual!AC21 -> 410.11827 | L21: 372 | M21: 380 | O21: =Actual!AO21 -> 2173.0458 | P21: =Actual!AP21 -> 2262.2337 | Q21: =Actual!AQ21 -> 2313.9057 | R21: 2399.483 | S21: 2457.6018 | U21: =Actual!BD21 -> 5379.492 | V21: =Actual!BE21 -> 5352.7627 | W21: =Actual!BF21 -> 5722.4058 | X21: 5776.0528 | Y21: 5855.2385 | Z21: 45992 | AA21: GF | AC21: Maine | AD21: =(D21-C21)/C21*100 -> -3.4157498 | AE21: =(E21-D21)/D21*100 -> 14.021829 | AF21: =(F21-E21)/E21*100 -> 2.2598252 | AG21: =(G21-F21)/F21*100 -> 1.791595 | AI21: =(J21-I21)/I21*100 -> 1.8930868 | AJ21: =(K21-J21)/J21*100 -> -10.795932 | AK21: =(L21-K21)/K21*100 -> -9.2944568 | AL21: =(M21-L21)/L21*100 -> 2.1505371 | AN21: =(P21-O21)/O21*100 -> 4.1042798 | AO21: =(Q21-P21)/P21*100 -> 2.284114 | AP21: =(R21-Q21)/Q21*100 -> 3.6983913 | AQ21: =(S21-R21)/R21*100 -> 2.4221417 | AS21: =(V21-U21)/U21*100 -> -0.49687513 | AT21: =(W21-V21)/V21*100 -> 6.9056525 | AU21: =(X21-W21)/W21*100 -> 0.93749038 | AV21: =(Y21-X21)/X21*100 -> 1.3709296 | AZ21: MI | BA21: 0.41513902 | BC21: HI | BD21: 2.0000053 | BF21: RI | BG21: 4.1062164 | BI21: MO | BJ21: 3.1502274 | BL21: VA | BM21: 3.2100826 | BO21: NY | BP21: 2.8903697
A22: Maryland | B22: MD | C22: =Actual!M22 -> 13469.498 | D22: =Actual!N22 -> 13616.685 | E22: =Actual!O22 -> 14565.248 | F22: 15420.888 | G22: 15788.813 | I22: =Actual!AA22 -> 1816.002 | J22: =Actual!AB22 -> 1903.9572 | K22: =Actual!AC22 -> 1876.709 | L22: 1694.19 | M22: 1657.966 | O22: =Actual!AO22 -> 6005.249 | P22: =Actual!AP22 -> 5896.6057 | Q22: =Actual!AQ22 -> 6048.565 | R22: 6562.583 | S22: 6869.808 | U22: =Actual!BD22 -> 23672.681 | V22: =Actual!BE22 -> 24862.789 | W22: =Actual!BF22 -> 25715.684 | X22: 26762.869 | Y22: 27136.918 | Z22: 46003 | AA22: GF | AC22: Maryland | AD22: =(D22-C22)/C22*100 -> 1.0927446 | AE22: =(E22-D22)/D22*100 -> 6.9661799 | AF22: =(F22-E22)/E22*100 -> 5.8745309 | AG22: =(G22-F22)/F22*100 -> 2.3858872 | AI22: =(J22-I22)/I22*100 -> 4.8433429 | AJ22: =(K22-J22)/J22*100 -> -1.4311353 | AK22: =(L22-K22)/K22*100 -> -9.7254822 | AL22: =(M22-L22)/L22*100 -> -2.1381309 | AN22: =(P22-O22)/O22*100 -> -1.8091389 | AO22: =(Q22-P22)/P22*100 -> 2.5770639 | AP22: =(R22-Q22)/Q22*100 -> 8.498181 | AQ22: =(S22-R22)/R22*100 -> 4.6814646 | AS22: =(V22-U22)/U22*100 -> 5.0273469 | AT22: =(W22-V22)/V22*100 -> 3.4304085 | AU22: =(X22-W22)/W22*100 -> 4.0721647 | AV22: =(Y22-X22)/X22*100 -> 1.3976416 | AZ22: AL | BA22: 0.52705133 | BC22: FL | BD22: 2.1838686 | BF22: VA | BG22: 4.4648194 | BI22: CA | BJ22: 3.1645386 | BL22: WI | BM22: 3.2139027 | BO22: TN | BP22: 2.9967414
A23: Massachusetts | B23: MA | C23: =Actual!M23 -> 21781 | D23: =Actual!N23 -> 24117 | E23: =Actual!O23 -> 26712 | F23: =(28414+27924)/2 -> 28169 | G23: =(29091+27928)/2 -> 28509.5 | I23: =Actual!AA23 -> 5065 | J23: =Actual!AB23 -> 4833 | K23: =Actual!AC23 -> 4668 | L23: =(3931+3856)/2 -> 3893.5 | M23: =(3940+3802)/2 -> 3871 | O23: =Actual!AO23 -> 9396 | P23: =Actual!AP23 -> 9323 | Q23: =Actual!AQ23 -> 9599 | R23: =(9750+9658)/2 -> 9704 | S23: =(10001+9803)/2 -> 9902 | U23: =Actual!BD23 -> 39165 | V23: =Actual!BE23 -> 40800 | W23: =Actual!BF23 -> 43705 | X23: =(44841+44123)/2 -> 44482 | Y23: =(45840+44265)/2 -> 45052.5 | Z23: 46007 | AC23: Massachusetts | AD23: =(D23-C23)/C23*100 -> 10.724944 | AE23: =(E23-D23)/D23*100 -> 10.760045 | AF23: =(F23-E23)/E23*100 -> 5.4544774 | AG23: =(G23-F23)/F23*100 -> 1.2087756 | AI23: =(J23-I23)/I23*100 -> -4.5804541 | AJ23: =(K23-J23)/J23*100 -> -3.4140286 | AK23: =(L23-K23)/K23*100 -> -16.591688 | AL23: =(M23-L23)/L23*100 -> -0.57788622 | AN23: =(P23-O23)/O23*100 -> -0.77692635 | AO23: =(Q23-P23)/P23*100 -> 2.9604205 | AP23: =(R23-Q23)/Q23*100 -> 1.0938639 | AQ23: =(S23-R23)/R23*100 -> 2.0403957 | AS23: =(V23-U23)/U23*100 -> 4.1746457 | AT23: =(W23-V23)/V23*100 -> 7.120098 | AU23: =(X23-W23)/W23*100 -> 1.7778286 | AV23: =(Y23-X23)/X23*100 -> 1.2825413 | AZ23: NM | BA23: 0.89253602 | BC23: SC | BD23: 2.2373124 | BF23: CT | BG23: 4.9203406 | BI23: KS | BJ23: 3.2355915 | BL23: NE | BM23: 3.5042848 | BO23: MN | BP23: 3.0201774
A24: Michigan | B24: MI | C24: =Actual!M24 -> 11670 | D24: =Actual!N24 -> 12295.8 | E24: =Actual!O24 -> 12679.4 | F24: =9075.2+4375.9 -> 13451.1 | G24: =9251+4514.6 -> 13765.6 | I24: =Actual!AA24 -> 1609.9 | J24: =Actual!AB24 -> 1574 | K24: =Actual!AC24 -> 1501.4 | L24: 1427 | M24: 1267.5 | O24: =Actual!AO24 -> 11594.5 | P24: =Actual!AP24 -> 11458.7 | Q24: =Actual!AQ24 -> 11646.6 | R24: =1146.5+1265.8+8070.2+971.2 -> 11453.7 | S24: =996.4+1327.1+8230.8+1002.6 -> 11556.9 | U24: =Actual!BD24 -> 31826.3 | V24: =Actual!BE24 -> 32601.6 | W24: =Actual!BF24 -> 33193.7 | X24: =14131.8+19199.7 -> 33331.5 | Y24: =14001.4+19650.4 -> 33651.8 | Z24: 46037 | AA24: GF + School Aid Fund | AC24: Michigan | AD24: =(D24-C24)/C24*100 -> 5.3624679 | AE24: =(E24-D24)/D24*100 -> 3.1197645 | AF24: =(F24-E24)/E24*100 -> 6.0862501 | AG24: =(G24-F24)/F24*100 -> 2.3380987 | AI24: =(J24-I24)/I24*100 -> -2.2299522 | AJ24: =(K24-J24)/J24*100 -> -4.6124524 | AK24: =(L24-K24)/K24*100 -> -4.955375 | AL24: =(M24-L24)/L24*100 -> -11.177295 | AN24: =(P24-O24)/O24*100 -> -1.171245 | AO24: =(Q24-P24)/P24*100 -> 1.6398021 | AP24: =(R24-Q24)/Q24*100 -> -1.6562774 | AQ24: =(S24-R24)/R24*100 -> 0.90101888 | AS24: =(V24-U24)/U24*100 -> 2.4360356 | AT24: =(W24-V24)/V24*100 -> 1.8161685 | AU24: =(X24-W24)/W24*100 -> 0.41513902 | AV24: =(Y24-X24)/X24*100 -> 0.96095285 | AZ24: ME | BA24: 0.93749038 | BC24: MN | BD24: 2.3369515 | BF24: AZ | BG24: 5.3958321 | BI24: VA | BJ24: 3.5811263 | BL24: NM | BM24: 3.5679252 | BO24: WY | BP24: 3.0958774
A25: Minnesota | B25: MN | C25: =Actual!M25 -> 15777.561 | D25: =Actual!N25 -> 14873.104 | E25: =Actual!O25 -> 16656 | F25: 17014 | G25: 17499 | I25: =Actual!AA25 -> 2928.921 | J25: =Actual!AB25 -> 3171 | K25: =Actual!AC25 -> 3192 | L25: 3077 | M25: 3195 | O25: =Actual!AO25 -> 7446.443 | P25: =Actual!AP25 -> 7546 | Q25: =Actual!AQ25 -> 7436 | R25: 7781 | S25: 8016 | U25: =Actual!BD25 -> 30485 | V25: =Actual!BE25 -> 30309 | W25: =Actual!BF25 -> 31981 | X25: =31078+1443 -> 32521 | Y25: =32113+1168 -> 33281 | Z25: 45962 | AA25: GF | AC25: Minnesota | AD25: =(D25-C25)/C25*100 -> -5.7325527 | AE25: =(E25-D25)/D25*100 -> 11.987383 | AF25: =(F25-E25)/E25*100 -> 2.1493756 | AG25: =(G25-F25)/F25*100 -> 2.8505936 | AI25: =(J25-I25)/I25*100 -> 8.2651256 | AJ25: =(K25-J25)/J25*100 -> 0.66225166 | AK25: =(L25-K25)/K25*100 -> -3.6027569 | AL25: =(M25-L25)/L25*100 -> 3.8349041 | AN25: =(P25-O25)/O25*100 -> 1.3369739 | AO25: =(Q25-P25)/P25*100 -> -1.4577259 | AP25: =(R25-Q25)/Q25*100 -> 4.6395912 | AQ25: =(S25-R25)/R25*100 -> 3.0201774 | AS25: =(V25-U25)/U25*100 -> -0.57733311 | AT25: =(W25-V25)/V25*100 -> 5.5165132 | AU25: =(X25-W25)/W25*100 -> 1.6885025 | AV25: =(Y25-X25)/X25*100 -> 2.3369515 | AZ25: MN | BA25: 1.6885025 | BC25: CA | BD25: 2.3663527 | BF25: MA | BG25: 5.4544774 | BI25: RI | BJ25: 3.6179732 | BL25: ME | BM25: 3.6983913 | BO25: UT | BP25: 3.1231343
A26: Mississippi | B26: MS | C26: =Actual!M26 -> 2388.3697 | D26: =Actual!N26 -> 2246.5463 | E26: =Actual!O26 -> 2281.2244 | F26: 2200 | G26: 2099.1 | I26: =Actual!AA26 -> 1037.2239 | J26: =Actual!AB26 -> 967.75673 | K26: =Actual!AC26 -> 735.24867 | L26: 738.6 | M26: 763.8 | O26: =Actual!AO26 -> 3123.0648 | P26: =Actual!AP26 -> 3223.8445 | Q26: =Actual!AQ26 -> 3305.7894 | R26: =2921.6+442.7 -> 3364.3 | S26: =2980.9+462 -> 3442.9 | U26: =Actual!BD26 -> 7694.1021 | V26: =Actual!BE26 -> 7707.1054 | W26: =Actual!BF26 -> 7642.7386 | X26: 7552 | Y26: 7532.4 | Z26: 45976 | AA26: GF | AC26: Mississippi | AD26: =(D26-C26)/C26*100 -> -5.9380837 | AE26: =(E26-D26)/D26*100 -> 1.5436178 | AF26: =(F26-E26)/E26*100 -> -3.5605613 | AG26: =(G26-F26)/F26*100 -> -4.5863636 | AI26: =(J26-I26)/I26*100 -> -6.6974122 | AJ26: =(K26-J26)/J26*100 -> -24.025466 | AK26: =(L26-K26)/K26*100 -> 0.45580892 | AL26: =(M26-L26)/L26*100 -> 3.4118603 | AN26: =(P26-O26)/O26*100 -> 3.2269485 | AO26: =(Q26-P26)/P26*100 -> 2.5418351 | AP26: =(R26-Q26)/Q26*100 -> 1.7699449 | AQ26: =(S26-R26)/R26*100 -> 2.3362958 | AS26: =(V26-U26)/U26*100 -> 0.16900463 | AT26: =(W26-V26)/V26*100 -> -0.8351623 | AU26: =(X26-W26)/W26*100 -> -1.1872525 | AV26: =(Y26-X26)/X26*100 -> -0.2595339 | AZ26: MA | BA26: 1.7778286 | BC26: SD | BD26: 2.3819482 | BF26: KS | BG26: 5.7587511 | BI26: DE | BJ26: 4.5601706 | BL26: CO | BM26: 3.7507783 | BO26: HI | BP26: 3.1385112
A27: Missouri | B27: MO | C27: =Actual!M27 -> 9984.7431 | D27: =Actual!N27 -> 9795.3615 | E27: =Actual!O27 -> 9883.7016 | F27: =9035.3+725.9 -> 9761.2 | G27: =9331.8+736.9 -> 10068.7 | I27: =Actual!AA27 -> 1058.8398 | J27: =Actual!AB27 -> 1050.7103 | K27: =Actual!AC27 -> 994.17233 | L27: 999.7 | M27: 1059.1 | O27: =Actual!AO27 -> 2943.6498 | P27: =Actual!AP27 -> 3184.1043 | Q27: =Actual!AQ27 -> 3223.3634 | R27: 3308.7 | S27: 3395.8 | U27: =Actual!BD27 -> 13234.563 | V27: =Actual!BE27 -> 13429.144 | W27: =Actual!BF27 -> 13430.979 | X27: 13150 | Y27: 13650 | Z27: 46035 | AA27: GF | AC27: Missouri | AD27: =(D27-C27)/C27*100 -> -1.8967102 | AE27: =(E27-D27)/D27*100 -> 0.90185701 | AF27: =(F27-E27)/E27*100 -> -1.2394307 | AG27: =(G27-F27)/F27*100 -> 3.1502274 | AI27: =(J27-I27)/I27*100 -> -0.7677719 | AJ27: =(K27-J27)/J27*100 -> -5.3809266 | AK27: =(L27-K27)/K27*100 -> 0.55600672 | AL27: =(M27-L27)/L27*100 -> 5.9417825 | AN27: =(P27-O27)/O27*100 -> 8.1685843 | AO27: =(Q27-P27)/P27*100 -> 1.232972 | AP27: =(R27-Q27)/Q27*100 -> 2.6474394 | AQ27: =(S27-R27)/R27*100 -> 2.6324538 | AS27: =(V27-U27)/U27*100 -> 1.4702497 | AT27: =(W27-V27)/V27*100 -> 0.013661667 | AU27: =(X27-W27)/W27*100 -> -2.0920191 | AV27: =(Y27-X27)/X27*100 -> 3.8022814 | AZ27: KS | BA27: 2.0431174 | BC27: VT | BD27: 2.4102377 | BF27: MD | BG27: 5.8745309 | BI27: PA | BJ27: 4.69424 | BL27: PA | BM27: 3.7895081 | BO27: IA | BP27: 3.2871422
A28: Montana | B28: MT | C28: =Actual!M28 -> 2254.3051 | D28: =Actual!N28 -> 2243.9463 | E28: =Actual!O28 -> 2329.58 | I28: =Actual!AA28 -> 309.88362 | J28: =Actual!AB28 -> 312.27636 | K28: =Actual!AC28 -> 321.208 | U28: =Actual!BD28 -> 3687.7434 | V28: =Actual!BE28 -> 3916.9224 | W28: =Actual!BF28 -> 4034.369 | AA28: GF | AC28: Montana | AZ28: DE | BA28: 2.4289321 | BC28: TX | BD28: 2.5959864 | BF28: CA | BG28: 5.8857872 | BI28: UT | BJ28: 4.7756485 | BL28: IA | BM28: 3.9457838 | BO28: WA | BP28: 3.3454811
A29: Nebraska | B29: NE | C29: =Actual!M29 -> 3005.9521 | D29: =Actual!N29 -> 2479.0542 | E29: =Actual!O29 -> 2179.9339 | F29: 3054.9632 | G29: 3111.7533 | I29: =Actual!AA29 -> 692.96473 | J29: =Actual!AB29 -> 1724.9081 | K29: =Actual!AC29 -> 1075.0851 | L29: 902.98773 | M29: 830.25109 | O29: =Actual!AO29 -> 2335.8999 | P29: =Actual!AP29 -> 2458.8341 | Q29: =Actual!AQ29 -> 2516.7442 | R29: 2604.9381 | S29: 2723.2177 | U29: =Actual!BD29 -> 6367.9825 | V29: =Actual!BE29 -> 7155.8106 | W29: =Actual!BF29 -> 6159.0417 | X29: 7069.839 | Y29: 7047.123 | Z29: 45980 | AA29: GF | AC29: Nebraska | AD29: =(D29-C29)/C29*100 -> -17.528486 | AE29: =(E29-D29)/D29*100 -> -12.065904 | AF29: =(F29-E29)/E29*100 -> 40.140176 | AG29: =(G29-F29)/F29*100 -> 1.8589445 | AI29: =(J29-I29)/I29*100 -> 148.91716 | AJ29: =(K29-J29)/J29*100 -> -37.672908 | AK29: =(L29-K29)/K29*100 -> -16.007789 | AL29: =(M29-L29)/L29*100 -> -8.0551087 | AN29: =(P29-O29)/O29*100 -> 5.2628167 | AO29: =(Q29-P29)/P29*100 -> 2.3551866 | AP29: =(R29-Q29)/Q29*100 -> 3.5042848 | AQ29: =(S29-R29)/R29*100 -> 4.5405906 | AS29: =(V29-U29)/U29*100 -> 12.371706 | AT29: =(W29-V29)/V29*100 -> -13.929504 | AU29: =(X29-W29)/W29*100 -> 14.787971 | AV29: =(Y29-X29)/X29*100 -> -0.32130859 | AZ29: FL | BA29: 2.6401079 | BC29: IN | BD29: 2.7166988 | BF29: MI | BG29: 6.0862501 | BI29: IA | BJ29: 5.1415525 | BL29: HI | BM29: 3.9949315 | BO29: SC | BP29: 3.4215559
A30: Nevada | B30: NV | O30: =Actual!AO30 -> 1721.5439 | U30: =Actual!BD30 -> 5762.4808 | AA30: GF | AC30: Nevada | AZ30: VA | BA30: 3.1456227 | BC30: ID | BD30: 3.0443694 | BF30: DE | BG30: 6.2772743 | BI30: AZ | BJ30: 5.3680182 | BL30: SC | BM30: 4.0131669 | BO30: OK | BP30: 3.4316627
A31: New Hampshire | B31: NH | C31: =Actual!M31 -> 147.3 | D31: =Actual!N31 -> 184.6 | E31: =Actual!O31 -> 72.7 | I31: =Actual!AA31 -> 1258.9 | J31: =Actual!AB31 -> 1225.7 | K31: =Actual!AC31 -> 1095.6 | U31: =Actual!BD31 -> 3218.5 | V31: =Actual!BE31 -> 3332 | W31: =Actual!BF31 -> 3101.1 | AA31: GF + Education Trust fund | AC31: New Hampshire | AZ31: CT | BA31: 3.2513203 | BC31: VA | BD31: 3.0530014 | BF31: OR | BG31: 9.1075705 | BI31: NY | BJ31: 5.9307806 | BL31: TX | BM31: 4.1417052 | BO31: IN | BP31: 3.4523598
A32: New Jersey | B32: NJ | C32: =Actual!M32 -> 18798.701 | I32: =Actual!AA32 -> 5512.7339 | O32: =Actual!AO32 -> 13079.431 | U32: =Actual!BD32 -> 52099.5 | AA32: GF | AC32: New Jersey | AZ32: CA | BA32: 3.295104 | BC32: WI | BD32: 3.0636518 | BF32: NY | BG32: 10.9459 | BI32: OR | BJ32: 10.606913 | BL32: SD | BM32: 4.4334148 | BO32: AZ | BP32: 3.4704761
A33: New Mexico | B33: NM | C33: =Actual!M33 -> 2514.7 | D33: =Actual!N33 -> 2207.6 | E33: =Actual!O33 -> 2143.1 | F33: 2175 | G33: 2231.9 | I33: =Actual!AA33 -> 439.1 | J33: =Actual!AB33 -> 627.2 | K33: =Actual!AC33 -> 782.5 | L33: 253 | M33: 384.1 | O33: =Actual!AO33 -> 4045.2 | P33: =Actual!AP33 -> 4131.8 | Q33: =Actual!AQ33 -> 4383.5 | R33: 4539.9 | S33: 4661.3 | U33: =Actual!BD33 -> 10890.1 | V33: =Actual!BE33 -> 13190 | W33: =Actual!BF33 -> 13624.1 | X33: 13745.7 | Y33: 13913.2 | Z33: 45999 | AA33: GF | AC33: New Mexico | AD33: =(D33-C33)/C33*100 -> -12.212192 | AE33: =(E33-D33)/D33*100 -> -2.921725 | AF33: =(F33-E33)/E33*100 -> 1.488498 | AG33: =(G33-F33)/F33*100 -> 2.616092 | AI33: =(J33-I33)/I33*100 -> 42.837622 | AJ33: =(K33-J33)/J33*100 -> 24.760842 | AK33: =(L33-K33)/K33*100 -> -67.667732 | AL33: =(M33-L33)/L33*100 -> 51.818182 | AN33: =(P33-O33)/O33*100 -> 2.1408089 | AO33: =(Q33-P33)/P33*100 -> 6.091776 | AP33: =(R33-Q33)/Q33*100 -> 3.5679252 | AQ33: =(S33-R33)/R33*100 -> 2.6740677 | AS33: =(V33-U33)/U33*100 -> 21.119182 | AT33: =(W33-V33)/V33*100 -> 3.2911296 | AU33: =(X33-W33)/W33*100 -> 0.89253602 | AV33: =(Y33-X33)/X33*100 -> 1.2185629 | AZ33: RI | BA33: 3.3116918 | BC33: WV | BD33: 3.1975386 | BF33: NE | BG33: 40.140176 | BI33: CO | BJ33: 13.372059 | BL33: MN | BM33: 4.6395912 | BO33: SD | BP33: 4.0297715
A34: New York | B34: NY | C34: =Actual!M34 -> 58776 | D34: =Actual!N34 -> 53839 | E34: =Actual!O34 -> 61201 | F34: 67900 | G34: 71927 | I34: =Actual!AA34 -> 28617 | J34: =Actual!AB34 -> 27695 | K34: =Actual!AC34 -> 31373 | L34: 30738 | M34: 28463 | O34: =Actual!AO34 -> 20585 | P34: =Actual!AP34 -> 21865 | Q34: =Actual!AQ34 -> 22352 | R34: 23561 | S34: 24242 | U34: =Actual!BD34 -> 143499 | V34: =Actual!BE34 -> 140202 | W34: =Actual!BF34 -> 152273 | X34: =262260-97072 -> 165188 | Y34: =251384-86485 -> 164899 | Z34: 46037 | AA34: All funds | AC34: New York | AD34: =(D34-C34)/C34*100 -> -8.3996869 | AE34: =(E34-D34)/D34*100 -> 13.674102 | AF34: =(F34-E34)/E34*100 -> 10.9459 | AG34: =(G34-F34)/F34*100 -> 5.9307806 | AI34: =(J34-I34)/I34*100 -> -3.2218611 | AJ34: =(K34-J34)/J34*100 -> 13.280376 | AK34: =(L34-K34)/K34*100 -> -2.0240334 | AL34: =(M34-L34)/L34*100 -> -7.4012623 | AN34: =(P34-O34)/O34*100 -> 6.21812 | AO34: =(Q34-P34)/P34*100 -> 2.2273039 | AP34: =(R34-Q34)/Q34*100 -> 5.408912 | AQ34: =(S34-R34)/R34*100 -> 2.8903697 | AS34: =(V34-U34)/U34*100 -> -2.297577 | AT34: =(W34-V34)/V34*100 -> 8.6097203 | AU34: =(X34-W34)/W34*100 -> 8.4814773 | AV34: =(Y34-X34)/X34*100 -> -0.17495218 | AZ34: SD | BA34: 3.4541426 | BC34: UT | BD34: 3.5860777 | BL34: WV | BM34: 4.9116347 | BO34: WV | BP34: 4.2157325
A35: North Carolina | B35: NC | C35: =Actual!M35 -> 16762.5 | D35: =Actual!N35 -> 16562.9 | E35: =Actual!O35 -> 17012.2 | I35: =Actual!AA35 -> 2483 | J35: =Actual!AB35 -> 2293.6 | K35: =Actual!AC35 -> 2344.7 | O35: =Actual!AO35 -> 10801.2 | P35: =Actual!AP35 -> 10905.8 | Q35: =Actual!AQ35 -> 11006.2 | U35: =Actual!BD35 -> 33535.4 | V35: =Actual!BE35 -> 33693.8 | W35: =Actual!BF35 -> 34559 | AA35: GF | AC35: North Carolina | AZ35: MD | BA35: 4.0721647 | BC35: MO | BD35: 3.8022814 | BL35: NY | BM35: 5.408912 | BO35: CO | BP35: 4.4325801
A36: North Dakota | B36: ND | C36: =Actual!M36 -> 482.78239 | D36: =Actual!N36 -> 355.00178 | E36: =Actual!O36 -> 453.20509 | I36: =Actual!AA36 -> 308.26094 | J36: =Actual!AB36 -> 276.65747 | K36: =Actual!AC36 -> 330.59823 | O36: =Actual!AO36 -> 1154.5302 | P36: =Actual!AP36 -> 1200.1614 | Q36: =Actual!AQ36 -> 1253.7592 | U36: =Actual!BD36 -> 2724.553 | V36: =Actual!BE36 -> 3012.5148 | W36: =Actual!BF36 -> 2625.7071 | AC36: North Dakota | AZ36: PA | BA36: 4.1190819 | BC36: IA | BD36: 4.1802023 | BL36: IN | BM36: 5.6076436 | BO36: NE | BP36: 4.5405906
A37: Ohio | B37: OH | C37: =Actual!M37 -> 10797.208 | D37: =Actual!N37 -> 9519.3 | E37: =Actual!O37 -> 10461.519 | I37: =Actual!AA37 -> 239.236 | J37: =Actual!AB37 -> 204.9 | K37: =Actual!AC37 -> 200.586 | O37: =Actual!AO37 -> 13483.137 | P37: =Actual!AP37 -> 13700.5 | Q37: =Actual!AQ37 -> 14144.774 | U37: =Actual!BD37 -> 28915.687 | V37: =Actual!BE37 -> 27944.5 | W37: =Actual!BF37 -> 29220.222 | AA37: All funds total taxes only | AC37: Ohio | AZ37: IN | BA37: 4.1618679 | BC37: AZ | BD37: 4.1819181 | BL37: WA | BM37: 6.9386438 | BO37: MD | BP37: 4.6814646
A38: Oklahoma | B38: OK | C38: =Actual!M38 -> 3372.6309 | D38: =Actual!N38 -> 3253.4388 | E38: =Actual!O38 -> 3518.7149 | F38: 3401.521 | G38: 3421.1741 | I38: =Actual!AA38 -> 598.49755 | J38: =Actual!AB38 -> 331.79365 | K38: =Actual!AC38 -> 481.65537 | L38: 535.72952 | M38: 462.98629 | O38: =Actual!AO38 -> 3113.0244 | P38: =Actual!AP38 -> 3128.2555 | Q38: =Actual!AQ38 -> 2837.7727 | R38: =2309.639614+564.449733 -> 2874.0893 | S38: =2370.460738+602.257661 -> 2972.7184 | U38: =Actual!BD38 -> 9104.3013 | V38: =Actual!BE38 -> 8466.2585 | W38: =Actual!BF38 -> 8745.416 | X38: 8488.7851 | Y38: 8552.7225 | Z38: 46010 | AA38: GF | AC38: Oklahoma | AD38: =(D38-C38)/C38*100 -> -3.5340967 | AE38: =(E38-D38)/D38*100 -> 8.1537151 | AF38: =(F38-E38)/E38*100 -> -3.3305882 | AG38: =(G38-F38)/F38*100 -> 0.57777205 | AI38: =(J38-I38)/I38*100 -> -44.562238 | AJ38: =(K38-J38)/J38*100 -> 45.167148 | AK38: =(L38-K38)/K38*100 -> 11.22673 | AL38: =(M38-L38)/L38*100 -> -13.578351 | AN38: =(P38-O38)/O38*100 -> 0.48926924 | AO38: =(Q38-P38)/P38*100 -> -9.2857768 | AP38: =(R38-Q38)/Q38*100 -> 1.2797591 | AQ38: =(S38-R38)/R38*100 -> 3.4316627 | AS38: =(V38-U38)/U38*100 -> -7.0081471 | AT38: =(W38-V38)/V38*100 -> 3.2972944 | AU38: =(X38-W38)/W38*100 -> -2.9344619 | AV38: =(Y38-X38)/X38*100 -> 0.75319843 | AZ38: AZ | BA38: 4.5328263 | BC38: WA | BD38: 4.6664672 | BL38: MD | BM38: 8.498181 | BO38: TX | BP38: 4.6955026
A39: Oregon | B39: OR | C39: =Actual!M39 -> 13246.856 | D39: =Actual!N39 -> 9128.408 | E39: =Actual!O39 -> 13041.019 | F39: 14228.739 | G39: 15737.969 | I39: =Actual!AA39 -> 1618.518 | J39: =Actual!AB39 -> 1623.083 | K39: =Actual!AC39 -> 1527.687 | L39: 1771.75 | M39: 1670.44 | O39: =Actual!AO39 -> N/A | P39: =Actual!AP39 -> N/A | Q39: =Actual!AQ39 -> N/A | R39: N/A | S39: N/A | U39: =Actual!BD39 -> 15759.2 | V39: =Actual!BE39 -> 11878.415 | W39: =Actual!BF39 -> 15505.895 | X39: 17020.558 | Y39: 18326.342 | Z39: 46054 | AA39: GF | AC39: Oregon | AD39: =(D39-C39)/C39*100 -> -31.090006 | AE39: =(E39-D39)/D39*100 -> 42.861921 | AF39: =(F39-E39)/E39*100 -> 9.1075705 | AG39: =(G39-F39)/F39*100 -> 10.606913 | AI39: =(J39-I39)/I39*100 -> 0.28204616 | AJ39: =(K39-J39)/J39*100 -> -5.8774567 | AK39: =(L39-K39)/K39*100 -> 15.975982 | AL39: =(M39-L39)/L39*100 -> -5.7180753 | AN39: N/A | AO39: N/A | AP39: N/A | AQ39: N/A | AS39: =(V39-U39)/U39*100 -> -24.62552 | AT39: =(W39-V39)/V39*100 -> 30.538418 | AU39: =(X39-W39)/W39*100 -> 9.7683042 | AV39: =(Y39-X39)/X39*100 -> 7.6718049 | AZ39: WA | BA39: 5.5259019 | BC39: CT | BD39: 6.2692283 | BL39: LA | BM39: 10.999076 | BO39: ID | BP39: 7.9670186
A40: Pennsylvania | B40: PA | C40: =Actual!M40 -> 17628.1 | D40: =Actual!N40 -> 17856.8 | E40: =Actual!O40 -> 18956.5 | F40: 19705 | G40: 20630 | I40: =Actual!AA40 -> 6142.9 | J40: =Actual!AB40 -> 5651.5 | K40: =Actual!AC40 -> 4719.9 | L40: 4940 | M40: 4760 | O40: =Actual!AO40 -> 14024.4 | P40: =Actual!AP40 -> 14255.9 | Q40: =Actual!AQ40 -> 14693.2 | R40: 15250 | S40: 15640 | U40: =Actual!BD40 -> 44917.1 | V40: =Actual!BE40 -> 45473.5 | W40: =Actual!BF40 -> 46408.4 | X40: 48320 | Y40: 48926 | Z40: 45981 | AA40: GF | AC40: Pennsylvania | AD40: =(D40-C40)/C40*100 -> 1.2973605 | AE40: =(E40-D40)/D40*100 -> 6.1584382 | AF40: =(F40-E40)/E40*100 -> 3.9485137 | AG40: =(G40-F40)/F40*100 -> 4.69424 | AI40: =(J40-I40)/I40*100 -> -7.9994791 | AJ40: =(K40-J40)/J40*100 -> -16.484119 | AK40: =(L40-K40)/K40*100 -> 4.6632344 | AL40: =(M40-L40)/L40*100 -> -3.6437247 | AN40: =(P40-O40)/O40*100 -> 1.6506945 | AO40: =(Q40-P40)/P40*100 -> 3.0675019 | AP40: =(R40-Q40)/Q40*100 -> 3.7895081 | AQ40: =(S40-R40)/R40*100 -> 2.557377 | AS40: =(V40-U40)/U40*100 -> 1.2387265 | AT40: =(W40-V40)/V40*100 -> 2.0559227 | AU40: =(X40-W40)/W40*100 -> 4.1190819 | AV40: =(Y40-X40)/X40*100 -> 1.2541391 | AZ40: NY | BA40: 8.4814773 | BC40: OR | BD40: 7.6718049
A41: Rhode Island | B41: RI | C41: =Actual!M41 -> 1813.6051 | D41: =Actual!N41 -> 1819.193 | E41: =Actual!O41 -> 1975.2903 | F41: 2056.4 | G41: 2130.8 | I41: =Actual!AA41 -> 304.22552 | J41: =Actual!AB41 -> 415.18304 | K41: =Actual!AC41 -> 340.39125 | L41: =317+11.5 -> 328.5 | M41: =332+16.7 -> 348.7 | O41: =Actual!AO41 -> 1564.768 | P41: =Actual!AP41 -> 1635.4276 | Q41: =Actual!AQ41 -> 1672.7087 | R41: 1726 | S41: 1774.4 | U41: =Actual!BD41 -> 5211.7294 | V41: =Actual!BE41 -> 5418.7038 | W41: =Actual!BF41 -> 5610.0136 | X41: 5795.8 | Y41: 5706.6 | Z41: 45978 | AA41: GF | AC41: Rhode Island | AD41: =(D41-C41)/C41*100 -> 0.30810991 | AE41: =(E41-D41)/D41*100 -> 8.5805793 | AF41: =(F41-E41)/E41*100 -> 4.1062164 | AG41: =(G41-F41)/F41*100 -> 3.6179732 | AI41: =(J41-I41)/I41*100 -> 36.472131 | AJ41: =(K41-J41)/J41*100 -> -18.014173 | AK41: =(L41-K41)/K41*100 -> -3.4934071 | AL41: =(M41-L41)/L41*100 -> 6.1491629 | AN41: =(P41-O41)/O41*100 -> 4.5156555 | AO41: =(Q41-P41)/P41*100 -> 2.2795986 | AP41: =(R41-Q41)/Q41*100 -> 3.185926 | AQ41: =(S41-R41)/R41*100 -> 2.8041715 | AS41: =(V41-U41)/U41*100 -> 3.9713188 | AT41: =(W41-V41)/V41*100 -> 3.5305453 | AU41: =(X41-W41)/W41*100 -> 3.3116918 | AV41: =(Y41-X41)/X41*100 -> -1.5390455 | AZ41: OR | BA41: 9.7683042 | BC41: CO | BD41: 8.6258099
A42: South Carolina | B42: SC | C42: =Actual!M42 -> 5758.2119 | D42: =Actual!N42 -> 6113.1849 | E42: =Actual!O42 -> 6722.1869 | F42: 6482.631 | G42: 6638.154 | I42: =Actual!AA42 -> 1262.2218 | J42: =Actual!AB42 -> 1293.0637 | K42: =Actual!AC42 -> 1321.6285 | L42: 1204.382 | M42: 1204.382 | O42: =Actual!AO42 -> 4660.0788 | P42: =Actual!AP42 -> 4786.3799 | Q42: =Actual!AQ42 -> 5027.4404 | R42: 5229.2 | S42: 5408.12 | U42: =Actual!BD42 -> 13094.202 | V42: =Actual!BE42 -> 13707.681 | W42: =Actual!BF42 -> 14858.559 | X42: 14681.41 | Y42: 15009.879 | Z42: 45979 | AA42: GF | AC42: South Carolina | AD42: =(D42-C42)/C42*100 -> 6.1646396 | AE42: =(E42-D42)/D42*100 -> 9.9621078 | AF42: =(F42-E42)/E42*100 -> -3.5636608 | AG42: =(G42-F42)/F42*100 -> 2.3990722 | AI42: =(J42-I42)/I42*100 -> 2.4434604 | AJ42: =(K42-J42)/J42*100 -> 2.2090733 | AK42: =(L42-K42)/K42*100 -> -8.8713631 | AL42: =(M42-L42)/L42*100 -> 0 | AN42: =(P42-O42)/O42*100 -> 2.7102795 | AO42: =(Q42-P42)/P42*100 -> 5.0363842 | AP42: =(R42-Q42)/Q42*100 -> 4.0131669 | AQ42: =(S42-R42)/R42*100 -> 3.4215559 | AS42: =(V42-U42)/U42*100 -> 4.6851164 | AT42: =(W42-V42)/V42*100 -> 8.3958628 | AU42: =(X42-W42)/W42*100 -> -1.1922334 | AV42: =(Y42-X42)/X42*100 -> 2.2373124 | AZ42: NE | BA42: 14.787971 | BC42: WY | BD42: 22.012372
A43: South Dakota | B43: SD | C43: =Actual!M43 -> N/A | D43: =Actual!N43 -> N/A | E43: =Actual!O43 -> N/A | F43: N/A | G43: N/A | I43: =Actual!AA43 -> 20.425082 | J43: =Actual!AB43 -> 28.659255 | K43: =Actual!AC43 -> 26.180028 | L43: 29.543802 | M43: 30.044678 | O43: =Actual!AO43 -> 1480.5729 | P43: =Actual!AP43 -> 1441.6788 | Q43: =Actual!AQ43 -> 1432.6311 | R43: 1496.1456 | S43: 1556.4369 | U43: =Actual!BD43 -> 2298.2901 | V43: =Actual!BE43 -> 2413.3093 | W43: =Actual!BF43 -> 2380.5491 | X43: 2462.7766 | Y43: 2521.4387 | Z43: 45992 | AA43: GF | AC43: South Dakota | AD43: N/A | AE43: N/A | AF43: N/A | AG43: N/A | AI43: =(J43-I43)/I43*100 -> 40.314027 | AJ43: =(K43-J43)/J43*100 -> -8.6507029 | AK43: =(L43-K43)/K43*100 -> 12.848626 | AL43: =(M43-L43)/L43*100 -> 1.6953674 | AN43: =(P43-O43)/O43*100 -> -2.6269616 | AO43: =(Q43-P43)/P43*100 -> -0.62757621 | AP43: =(R43-Q43)/Q43*100 -> 4.4334148 | AQ43: =(S43-R43)/R43*100 -> 4.0297715 | AS43: =(V43-U43)/U43*100 -> 5.0045587 | AT43: =(W43-V43)/V43*100 -> -1.3574827 | AU43: =(X43-W43)/W43*100 -> 3.4541426 | AV43: =(Y43-X43)/X43*100 -> 2.3819482
A44: Tennessee | B44: TN | C44: =Actual!M44 -> 2.6623 | D44: =Actual!N44 -> 1.9803 | E44: =Actual!O44 -> 0 | F44: 0 | G44: 0 | I44: =Actual!AA44 -> 4786.5731 | J44: =Actual!AB44 -> 4600.4649 | K44: =Actual!AC44 -> 3727.202 | L44: =1216.3+2707.1 -> 3923.4 | M44: =1178+2622 -> 3800 | O44: =Actual!AO44 -> 13677.873 | P44: =Actual!AP44 -> 13802.144 | Q44: =Actual!AQ44 -> 14502.001 | R44: 14852.8 | S44: 15297.9 | U44: =Actual!BD44 -> 25350.991 | V44: =Actual!BE44 -> 26269.941 | W44: =Actual!BF44 -> 26897.39 | X44: 26976 | Y44: 27120.1 | Z44: 45976 | AA44: All funds | AC44: Tennessee | AD44: N/A | AE44: N/A | AF44: N/A | AG44: N/A | AI44: N/A | AJ44: N/A | AK44: N/A | AL44: N/A | AN44: =(P44-O44)/O44*100 -> 0.90855059 | AO44: =(Q44-P44)/P44*100 -> 5.0706434 | AP44: =(R44-Q44)/Q44*100 -> 2.4189668 | AQ44: =(S44-R44)/R44*100 -> 2.9967414 | AS44: =(V44-U44)/U44*100 -> 3.6249081 | AT44: =(W44-V44)/V44*100 -> 2.3884675 | AU44: =(X44-W44)/W44*100 -> 0.29225996 | AV44: =(Y44-X44)/X44*100 -> 0.53417853 | AZ44: Median | BA44: 0.70979368 | BC44: Median | BD44: 2.2105905 | BF44: Median | BG44: 3.7566953 | BI44: Median | BJ44: 2.616092 | BL44: Median | BM44: 3.2100826 | BO44: Median | BP44: 2.8903697
A45: Texas | B45: TX | C45: =Actual!M45 -> N/A | D45: =Actual!N45 -> N/A | E45: =Actual!O45 -> N/A | F45: N/A | G45: N/A | I45: =Actual!AA45 -> N/A | J45: =Actual!AB45 -> N/A | K45: =Actual!AC45 -> N/A | L45: N/A | M45: N/A | O45: =Actual!AO45 -> 46581.072 | P45: =Actual!AP45 -> 47159.947 | Q45: =Actual!AQ45 -> 49058.907 | R45: 51090.782 | S45: 53489.751 | U45: =Actual!BD45 -> 119081.93 | V45: =Actual!BE45 -> 122251.15 | W45: =Actual!BF45 -> 123947.09 | X45: =(176613536-56453621)/1000 -> 120159.91 | Y45: =(178309257-55030007)/1000 -> 123279.25 | Z45: 45931 | AA45: All funds | AC45: Texas | AD45: N/A | AE45: N/A | AF45: N/A | AG45: N/A | AI45: N/A | AJ45: N/A | AK45: N/A | AL45: N/A | AN45: =(P45-O45)/O45*100 -> 1.2427258 | AO45: =(Q45-P45)/P45*100 -> 4.0266367 | AP45: =(R45-Q45)/Q45*100 -> 4.1417052 | AQ45: =(S45-R45)/R45*100 -> 4.6955026 | AS45: =(V45-U45)/U45*100 -> 2.6613828 | AT45: =(W45-V45)/V45*100 -> 1.3872554 | AU45: =(X45-W45)/W45*100 -> -3.0554777 | AV45: =(Y45-X45)/X45*100 -> 2.5959864
A46: Utah | B46: UT | C46: =Actual!M46 -> 6432.142 | D46: =Actual!N46 -> 6214.529 | E46: =Actual!O46 -> 6607.356 | F46: 6705.728 | G46: 7025.97 | I46: =Actual!AA46 -> 869.903 | J46: =Actual!AB46 -> 883.39 | K46: =Actual!AC46 -> 948.52 | L46: 640.205 | M46: 717.518 | O46: =Actual!AO46 -> 3262.812 | P46: =Actual!AP46 -> 3315.555 | Q46: =Actual!AQ46 -> 3412.47 | R46: 3205.882 | S46: 3306.006 | U46: =Actual!BD46 -> 12260.541 | V46: =Actual!BE46 -> 12291.518 | W46: =Actual!BF46 -> 12844.638 | X46: 12365.181 | Y46: 12808.606 | Z46: 45962 | AA46: GF + Education Fund + Transportation Fund | AC46: Utah | AD46: =(D46-C46)/C46*100 -> -3.383212 | AE46: =(E46-D46)/D46*100 -> 6.3211066 | AF46: =(F46-E46)/E46*100 -> 1.4888255 | AG46: =(G46-F46)/F46*100 -> 4.7756485 | AI46: =(J46-I46)/I46*100 -> 1.5504027 | AJ46: =(K46-J46)/J46*100 -> 7.3727346 | AK46: =(L46-K46)/K46*100 -> -32.50485 | AL46: =(M46-L46)/L46*100 -> 12.076288 | AN46: =(P46-O46)/O46*100 -> 1.6164891 | AO46: =(Q46-P46)/P46*100 -> 2.92304 | AP46: =(R46-Q46)/Q46*100 -> -6.053914 | AQ46: =(S46-R46)/R46*100 -> 3.1231343 | AS46: =(V46-U46)/U46*100 -> 0.25265606 | AT46: =(W46-V46)/V46*100 -> 4.5000137 | AU46: =(X46-W46)/W46*100 -> -3.7327405 | AV46: =(Y46-X46)/X46*100 -> 3.5860777
A47: Vermont | B47: VT | C47: =Actual!M47 -> 1209.9712 | D47: =Actual!N47 -> 1243.0692 | E47: =Actual!O47 -> 1362.9 | F47: 1414.1 | G47: 1445.3 | I47: =Actual!AA47 -> 281.36932 | J47: =Actual!AB47 -> 238.81253 | K47: =Actual!AC47 -> 272.6 | L47: 223.8 | M47: 248.6 | O47: =Actual!AO47 -> 584.04754 | P47: =Actual!AP47 -> 595.17829 | Q47: =Actual!AQ47 -> 618.1 | R47: 634.5 | S47: 651.1 | U47: =Actual!BD47 -> 2754 | V47: =Actual!BE47 -> 2811.8 | W47: =Actual!BF47 -> 3026 | X47: =2817.1+135.3+63.9 -> 3016.3 | Y47: =2902.9+124.2+61.9 -> 3089 | Z47: 46038 | AA47: GF (total tax + other) + cigarettes | AC47: Vermont | AD47: =(D47-C47)/C47*100 -> 2.7354414 | AE47: =(E47-D47)/D47*100 -> 9.6399109 | AF47: =(F47-E47)/E47*100 -> 3.7566953 | AG47: =(G47-F47)/F47*100 -> 2.2063503 | AI47: =(J47-I47)/I47*100 -> -15.124887 | AJ47: =(K47-J47)/J47*100 -> 14.148116 | AK47: =(L47-K47)/K47*100 -> -17.901687 | AL47: =(M47-L47)/L47*100 -> 11.081323 | AN47: =(P47-O47)/O47*100 -> 1.9057954 | AO47: =(Q47-P47)/P47*100 -> 3.8512349 | AP47: =(R47-Q47)/Q47*100 -> 2.6532923 | AQ47: =(S47-R47)/R47*100 -> 2.6162333 | AS47: =(V47-U47)/U47*100 -> 2.0987654 | AT47: =(W47-V47)/V47*100 -> 7.617896 | AU47: =(X47-W47)/W47*100 -> -0.32055519 | AV47: =(Y47-X47)/X47*100 -> 2.4102377
A48: Virginia | B48: VA | C48: =Actual!M48 -> 18983.556 | D48: =Actual!N48 -> 20310.406 | E48: =Actual!O48 -> 21892.442 | F48: 22869.9 | G48: 23688.9 | I48: =Actual!AA48 -> 2031.1 | J48: =Actual!AB48 -> 1907.065 | K48: =Actual!AC48 -> 1878.586 | L48: 1811.7 | M48: 1825.2 | O48: =Actual!AO48 -> 6151.249 | P48: =Actual!AP48 -> 6086.775 | Q48: =Actual!AQ48 -> 6225.167 | R48: =4967.6+1457.4 -> 6425 | S48: =5079+1490.1 -> 6569.1 | U48: =Actual!BD48 -> 32727.6 | V48: =Actual!BE48 -> 34320.641 | W48: =Actual!BF48 -> 36344.441 | X48: =32182.8+5304.9 -> 37487.7 | Y48: =33155.9+5476.3 -> 38632.2 | Z48: 46008 | AA48: GF + Transportation fund | AC48: Virginia | AD48: =(D48-C48)/C48*100 -> 6.9894703 | AE48: =(E48-D48)/D48*100 -> 7.7892879 | AF48: =(F48-E48)/E48*100 -> 4.4648194 | AG48: =(G48-F48)/F48*100 -> 3.5811263 | AI48: =(J48-I48)/I48*100 -> -6.1067894 | AJ48: =(K48-J48)/J48*100 -> -1.4933419 | AK48: =(L48-K48)/K48*100 -> -3.5604439 | AL48: =(M48-L48)/L48*100 -> 0.74515648 | AN48: =(P48-O48)/O48*100 -> -1.0481449 | AO48: =(Q48-P48)/P48*100 -> 2.2736507 | AP48: =(R48-Q48)/Q48*100 -> 3.2100826 | AQ48: =(S48-R48)/R48*100 -> 2.2428016 | AS48: =(V48-U48)/U48*100 -> 4.8675766 | AT48: =(W48-V48)/V48*100 -> 5.896743 | AU48: =(X48-W48)/W48*100 -> 3.1456227 | AV48: =(Y48-X48)/X48*100 -> 3.0530014
A49: Washington | B49: WA | C49: =Actual!M49 -> N/A | D49: =Actual!N49 -> N/A | E49: =Actual!O49 -> N/A | F49: N/A | G49: N/A | I49: =Actual!AA49 -> N/A | J49: =Actual!AB49 -> N/A | K49: =Actual!AC49 -> N/A | L49: N/A | M49: N/A | O49: =Actual!AO49 -> 15805.7 | P49: =Actual!AP49 -> 15754.3 | Q49: =Actual!AQ49 -> 16114.1 | R49: =16226.2+1006 -> 17232.2 | S49: =16789.2+1019.5 -> 17808.7 | U49: =Actual!BD49 -> 30971.9 | V49: =Actual!BE49 -> 31093.5 | W49: =Actual!BF49 -> 32298.8 | X49: 34083.6 | Y49: 35674.1 | Z49: 45962 | AA49: GF | AC49: Washington | AD49: N/A | AE49: N/A | AF49: N/A | AG49: N/A | AI49: N/A | AJ49: N/A | AK49: N/A | AL49: N/A | AN49: =(P49-O49)/O49*100 -> -0.32519914 | AO49: =(Q49-P49)/P49*100 -> 2.2838209 | AP49: =(R49-Q49)/Q49*100 -> 6.9386438 | AQ49: =(S49-R49)/R49*100 -> 3.3454811 | AS49: =(V49-U49)/U49*100 -> 0.39261395 | AT49: =(W49-V49)/V49*100 -> 3.8763729 | AU49: =(X49-W49)/W49*100 -> 5.5259019 | AV49: =(Y49-X49)/X49*100 -> 4.6664672
A50: West Virginia | B50: WV | C50: =Actual!M50 -> 2663.568 | D50: =Actual!N50 -> 2239.859 | E50: =Actual!O50 -> 2126.396 | F50: 2019.556 | G50: 2172.267 | I50: =Actual!AA50 -> 419.965 | J50: =Actual!AB50 -> 465.463 | K50: =Actual!AC50 -> 376.219 | L50: 313.5 | M50: 274.3 | O50: =Actual!AO50 -> 1750.434 | P50: =Actual!AP50 -> 1816.544 | Q50: =Actual!AQ50 -> 1821.247 | R50: 1910.7 | S50: 1991.25 | U50: =Actual!BD50 -> 6483.291 | V50: =Actual!BE50 -> 5710.575 | W50: =Actual!BF50 -> 5519.363 | X50: 5323.157 | Y50: 5493.367 | Z50: 46036 | AA50: GF | AC50: West Virginia | AD50: N/A | AE50: N/A | AF50: N/A | AG50: N/A | AI50: N/A | AJ50: N/A | AK50: N/A | AL50: N/A | AN50: =(P50-O50)/O50*100 -> 3.7767776 | AO50: =(Q50-P50)/P50*100 -> 0.25889822 | AP50: =(R50-Q50)/Q50*100 -> 4.9116347 | AQ50: =(S50-R50)/R50*100 -> 4.2157325 | AS50: =(V50-U50)/U50*100 -> -11.918577 | AT50: =(W50-V50)/V50*100 -> -3.3483844 | AU50: =(X50-W50)/W50*100 -> -3.5548667 | AV50: =(Y50-X50)/X50*100 -> 3.1975386
A51: Wisconsin | B51: WI | C51: =Actual!M51 -> 9414.7 | D51: =Actual!N51 -> 9717.592 | E51: =Actual!O51 -> 10451.1 | F51: 9874.3 | G51: 10353.1 | I51: =Actual!AA51 -> 2748.5 | J51: =Actual!AB51 -> 2702.1 | K51: =Actual!AC51 -> 2761.7 | L51: 2650.6 | M51: 2691.1 | O51: =Actual!AO51 -> 7456.1 | P51: =Actual!AP51 -> 7587.5 | Q51: =Actual!AQ51 -> 7831.6 | R51: 8083.3 | S51: 8249.3 | U51: =Actual!BD51 -> 20974 | V51: =Actual!BE51 -> 21329.6 | W51: =Actual!BF51 -> 22362.9 | X51: 21944.4 | Y51: 22616.7 | Z51: 46037 | AA51: GF | AC51: Wisconsin | AD51: N/A | AE51: N/A | AF51: N/A | AG51: N/A | AI51: N/A | AJ51: N/A | AK51: N/A | AL51: N/A | AN51: =(P51-O51)/O51*100 -> 1.7623154 | AO51: =(Q51-P51)/P51*100 -> 3.2171334 | AP51: =(R51-Q51)/Q51*100 -> 3.2139027 | AQ51: =(S51-R51)/R51*100 -> 2.0536167 | AS51: =(V51-U51)/U51*100 -> 1.6954324 | AT51: =(W51-V51)/V51*100 -> 4.8444415 | AU51: =(X51-W51)/W51*100 -> -1.8714031 | AV51: =(Y51-X51)/X51*100 -> 3.0636518
A52: Wyoming | B52: WY | C52: =Actual!M52 -> N/A | D52: =Actual!N52 -> N/A | E52: =Actual!O52 -> N/A | F52: N/A | G52: N/A | I52: =Actual!AA52 -> N/A | J52: =Actual!AB52 -> N/A | K52: =Actual!U52 -> N/A | L52: N/A | M52: N/A | O52: =Actual!AO52 -> 635.93381 | P52: =Actual!AP52 -> 646.9233 | Q52: =Actual!AQ52 -> 635.79614 | R52: 633.1 | S52: 652.7 | U52: =Actual!BD52 -> 1394.5026 | V52: =Actual!BE52 -> 1664.0441 | W52: =Actual!BF52 -> 2026.7114 | X52: 1519.6 | Y52: 1854.1 | Z52: 45960 | AA52: GF | AC52: Wyoming | AD52: N/A | AE52: N/A | AF52: N/A | AG52: N/A | AI52: N/A | AJ52: N/A | AK52: N/A | AL52: N/A | AN52: =(P52-O52)/O52*100 -> 1.7280871 | AO52: =(Q52-P52)/P52*100 -> -1.7200127 | AP52: =(R52-Q52)/Q52*100 -> -0.42405731 | AQ52: =(S52-R52)/R52*100 -> 3.0958774 | AS52: =(V52-U52)/U52*100 -> 19.328864 | AT52: =(W52-V52)/V52*100 -> 21.794329 | AU52: =(X52-W52)/W52*100 -> -25.021391 | AV52: =(Y52-X52)/X52*100 -> 22.012372
A53: United States | B53: US | C53: =SUM(C3:C52) -> 488774.54 | D53: =SUM(D3:D52) -> 476135.39 | E53: =SUM(E3:E52) -> 519912.1 | F53: =SUM(F3:F52) -> 471723.25 | G53: =SUM(G3:G52) -> 489300.36 | I53: =SUM(I3:I52) -> 143924.97 | J53: =SUM(J3:J52) -> 136012.28 | K53: =SUM(K3:K52) -> 141613.62 | L53: =SUM(L3:L52) -> 125541.79 | M53: =SUM(M3:M52) -> 124837.62 | O53: =SUM(O3:O52) -> 380060.29 | P53: =SUM(P3:P52) -> 369669.41 | Q53: =SUM(Q3:Q52) -> 378516.23 | R53: =SUM(R3:R52) -> 341648.83 | S53: =SUM(S3:S52) -> 351323.02 | U53: =SUM(U3:U52) -> 1281080.9 | V53: =SUM(V3:V52) -> 1250148.8 | W53: =SUM(W3:W52) -> 1316125 | X53: =SUM(X3:X52) -> 1186869.2 | Y53: =SUM(Y3:Y52) -> 1209347.3 | AC53: United States | AD53: =(D54-C54)/C54*100 -> 1.4284212 | AE53: =(E54-D54)/D54*100 -> 9.7761688 | AF53: =(F54-E54)/E54*100 -> 4.5482671 | AG53: =(G54-F54)/F54*100 -> 3.7261505 | AI53: =(J54-I54)/I54*100 -> -1.0536684 | AJ53: =(K54-J54)/J54*100 -> 4.6552966 | AK53: =(L54-K54)/K54*100 -> -3.4395185 | AL53: =(M54-L54)/L54*100 -> -0.56090625 | AN53: =(P54-O54)/O54*100 -> 1.1380939 | AO53: =(Q54-P54)/P54*100 -> 2.5082354 | AP53: =(R54-Q54)/Q54*100 -> 3.2270546 | AQ53: =(S54-R54)/R54*100 -> 2.8316191 | AS53: =(V54-U54)/U54*100 -> 2.3958343 | AT53: =(W54-V54)/V54*100 -> 5.6061616 | AU53: =(X54-W54)/W54*100 -> 2.0867833 | AV53: =(Y54-X54)/X54*100 -> 1.8939018
A54: Median | B54: Median | C54: =C53-(C6+C15+C19+C28+C31+C35+C36+C37+C30+C32) -> 405231.04 | D54: =D53-(D6+D15+D19+D28+D31+D35+D36+D37+D30+D32) -> 411019.45 | E54: =E53-(E6+E15+E19+E28+E31+E35+E36+E37+E30+E32) -> 451201.4 | F54: =F53-(F6+F15+F19+F28+F31+F35+F36+F37+F30+F32) -> 471723.25 | G54: =G53-(G6+G15+G19+G28+G31+G35+G36+G37+G30+G32) -> 489300.36 | I54: =I53-(I6+I15+I19+I28+I31+I35+I36+I37+I30+I32) -> 125553.26 | J54: =J53-(J6+J15+J19+J28+J31+J35+J36+J37+J30+J32) -> 124230.34 | K54: =K53-(K6+K15+K19+K28+K31+K35+K36+K37+K30+K32) -> 130013.63 | L54: =L53-(L6+L15+L19+L28+L31+L35+L36+L37+L30+L32) -> 125541.79 | M54: =M53-(M6+M15+M19+M28+M31+M35+M36+M37+M30+M32) -> 124837.62 | O54: =O53-(O6+O15+O19+O28+O31+O35+O36+O37+O30+O32) -> 319236.75 | P54: =P53-(P6+P15+P19+P28+P31+P35+P36+P37+P30+P32) -> 322869.96 | Q54: =Q53-(Q6+Q15+Q19+Q28+Q31+Q35+Q36+Q37+Q30+Q32) -> 330968.3 | R54: =R53-(R6+R15+R19+R28+R31+R35+R36+R37+R30+R32) -> 341648.83 | S54: =S53-(S6+S15+S19+S28+S31+S35+S36+S37+S30+S32) -> 351323.02 | U54: =U53-(U6+U15+U19+U28+U31+U35+U36+U37+U30+U32) -> 1075132 | V54: =V53-(V6+V15+V19+V28+V31+V35+V36+V37+V30+V32) -> 1100890.3 | W54: =W53-(W6+W15+W19+W28+W31+W35+W36+W37+W30+W32) -> 1162608 | X54: =X53-(X6+X15+X19+X28+X31+X35+X36+X37+X30+X32) -> 1186869.2 | Y54: =Y53-(Y6+Y15+Y19+Y28+Y31+Y35+Y36+Y37+Y30+Y32) -> 1209347.3 | AC54: Median | AD54: =MEDIAN(AD3:AD52) -> 0.30810991 | AE54: =MEDIAN(AE3:AE52) -> 7.3010462 | AF54: =MEDIAN(AF3:AF52) -> 3.7566953 | AG54: =MEDIAN(AG3:AG52) -> 2.616092 | AI54: =MEDIAN(AI3:AI52) -> -1.0073897 | AJ54: =MEDIAN(AJ3:AJ52) -> -3.4266526 | AK54: =MEDIAN(AK3:AK52) -> -4.2790659 | AL54: =MEDIAN(AL3:AL52) -> 0.29995197 | AN54: =MEDIAN(AN3:AN52) -> 1.1242559 | AO54: =MEDIAN(AO3:AO52) -> 2.4795913 | AP54: =MEDIAN(AP3:AP52) -> 3.2100826 | AQ54: =MEDIAN(AQ3:AQ52) -> 2.8903697 | AS54: =MEDIAN(AS3:AS52) -> 2.0618149 | AT54: =MEDIAN(AT3:AT52) -> 3.4452807 | AU54: =MEDIAN(AU3:AU52) -> 0.70979368 | AV54: =MEDIAN(AV3:AV52) -> 2.2105905
AC57: >0 | AD57: =COUNTIF(AD3:AD52,">0") -> 16 | AE57: =COUNTIF(AE3:AE52,">0") -> 26 | AF57: =COUNTIF(AF3:AF52,">0") -> 22 | AG57: =COUNTIF(AG3:AG52,">0") -> 29 | AI57: =COUNTIF(AI3:AI52,">0") -> 16 | AJ57: =COUNTIF(AJ3:AJ52,">0") -> 13 | AK57: =COUNTIF(AK3:AK52,">0") -> 12 | AL57: =COUNTIF(AL3:AL52,">0") -> 18 | AN57: =COUNTIF(AN3:AN52,">0") -> 27 | AO57: =COUNTIF(AO3:AO52,">0") -> 31 | AP57: =COUNTIF(AP3:AP52,">0") -> 32 | AQ57: =COUNTIF(AQ3:AQ52,">0") -> 37 | AS57: =COUNTIF(AS3:AS52,">0") -> 30 | AT57: =COUNTIF(AT3:AT52,">0") -> 32 | AU57: =COUNTIF(AU3:AU52,">0") -> 23 | AV57: =COUNTIF(AV3:AV52,">0") -> 32
AC58: <0 | AD58: =COUNTIF(AD3:AD52,"<0") -> 15 | AE58: =COUNTIF(AE3:AE52,"<0") -> 5 | AF58: =COUNTIF(AF3:AF52,"<0") -> 9 | AG58: =COUNTIF(AG3:AG52,"<0") -> 2 | AI58: =COUNTIF(AI3:AI52,"<0") -> 18 | AJ58: =COUNTIF(AJ3:AJ52,"<0") -> 21 | AK58: =COUNTIF(AK3:AK52,"<0") -> 22 | AL58: =COUNTIF(AL3:AL52,"<0") -> 15 | AN58: =COUNTIF(AN3:AN52,"<0") -> 10 | AO58: =COUNTIF(AO3:AO52,"<0") -> 6 | AP58: =COUNTIF(AP3:AP52,"<0") -> 5 | AQ58: =COUNTIF(AQ3:AQ52,"<0") -> 0 | AS58: =COUNTIF(AS3:AS52,"<0") -> 10 | AT58: =COUNTIF(AT3:AT52,"<0") -> 8 | AU58: =COUNTIF(AU3:AU52,"<0") -> 17 | AV58: =COUNTIF(AV3:AV52,"<0") -> 8
A59: nonempty count | B59: =COUNTA(B3:B52) -> 50 | G59: =COUNTA(G3:G52) -> 40 | M59: =COUNTA(M3:M52) -> 40 | S59: =COUNTA(S3:S52) -> 40 | Y59: =COUNTA(Y3:Y52) -> 40 | AC59: N/A | AD59: =COUNTIF(AD3:AD52,"=n/a") -> 9 | AE59: =COUNTIF(AE3:AE52,"=n/a") -> 9 | AF59: =COUNTIF(AF3:AF52,"=n/a") -> 9 | AG59: =COUNTIF(AG3:AG52,"=n/a") -> 9 | AI59: =COUNTIF(AI3:AI52,"=n/a") -> 6 | AJ59: =COUNTIF(AJ3:AJ52,"=n/a") -> 6 | AK59: =COUNTIF(AK3:AK52,"=n/a") -> 6 | AL59: =COUNTIF(AL3:AL52,"=n/a") -> 6 | AN59: =COUNTIF(AN3:AN52,"=n/a") -> 3 | AO59: =COUNTIF(AO3:AO52,"=n/a") -> 3 | AP59: =COUNTIF(AP3:AP52,"=n/a") -> 3 | AQ59: =COUNTIF(AQ3:AQ52,"=n/a") -> 3 | AS59: =COUNTIF(AS3:AS52,"=n/a") -> 0 | AT59: =COUNTIF(AT3:AT52,"=n/a") -> 0 | AU59: =COUNTIF(AU3:AU52,"=n/a") -> 0 | AV59: =COUNTIF(AV3:AV52,"=n/a") -> 0
A60: numcountxus | B60: =COUNT(B3:B52) -> 0 | G60: =COUNT(G3:G52) -> 34 | M60: =COUNT(M3:M52) -> 37 | S60: =COUNT(S3:S52) -> 37 | Y60: =COUNT(Y3:Y52) -> 40 | AD60: =SUM(AD57:AD59) -> 40 | AE60: =SUM(AE57:AE59) -> 40 | AF60: =SUM(AF57:AF59) -> 40 | AG60: =SUM(AG57:AG59) -> 40 | AI60: =SUM(AI57:AI59) -> 40 | AJ60: =SUM(AJ57:AJ59) -> 40 | AK60: =SUM(AK57:AK59) -> 40 | AL60: =SUM(AL57:AL59) -> 39 | AN60: =SUM(AN57:AN59) -> 40 | AO60: =SUM(AO57:AO59) -> 40 | AP60: =SUM(AP57:AP59) -> 40 | AQ60: =SUM(AQ57:AQ59) -> 40 | AS60: =SUM(AS57:AS59) -> 40 | AT60: =SUM(AT57:AT59) -> 40 | AU60: =SUM(AU57:AU59) -> 40 | AV60: =SUM(AV57:AV59) -> 40
G61: N/A
A62: ny in? | B62: yes | G62: yes | M62: yes | S62: yes | AC62: NY has the Executive Budget numbers
AC63: median x ny | AG63: 2.6 | AL63: 0.5 | AQ63: 2.9
AC65: notable
AC66: included | AG66: ca, co, ct, ga, md, ma
AC67: missing | AG67: il, nj, nc, oh | AL67: il, nj, nc, oh | AQ67: il, nj, nc, oh
